Workbook

Sheet Supuestos
A1: Crédito en USD para maquinaria amarilla – Supuestos
A3: Concepto | B3: Valor | C3: Fuente / nota
A4: Valor de la maquinaria (COP) | B4: 400000000
A5: Aporte inicial de los inversionistas (%) | B5: 0.1
A6: Aporte inicial (COP) | B6: =B4*B5 -> 40000000 | C6: Cálculo
A7: Monto a financiar (COP) – 90 % | B7: =B4-B6 -> 360000000 | C7: Cálculo
A8: TRM (COP por USD) | B8: 3174.67 | C8: TRM vigente del 17 al 19 de oct. de 2026, certificada por la Superfinanciera; consultada el 18/10/2026 (ver fuentes abajo)
A9: Monto a financiar (USD) | B9: =B7/B8 -> 113397.61
A10: Plazo (años) | B10: 10
A11: Pagos por año | B11: 4
A12: Número de cuotas | B12: =B10*B11 -> 40 | C12: Cálculo
A13: Tasa base: Prime Rate (% anual) | B13: 0.07 | C13: 7,00 % vigente desde el 17 de sept. de 2026 (Prime de U.S. Bank y WSJ Prime); ver fuentes abajo
A14: Margen máximo SBA 7(a) (puntos sobre Prime) | B14: 0.06 | C14: Tope de Prime + 6,0 pp para préstamos de USD 50.001 a 250.000, igual para tasa fija y variable (ver fuentes abajo)
A15: Tasa nominal anual FIJA (Prime + margen) | B15: =B13+B14 -> 0.13 | C15: Cotización: tasa fija nominal anual, pagadera trimestre vencido. El tope se fija con el Prime vigente al aprobar el crédito y no cambia durante los 10 años
A16: Tasa trimestral (nominal anual / 4) | B16: =B15/B11 -> 0.0325 | C16: Cálculo
A17: Tasa efectiva anual equivalente | B17: =(1+B16)^B11-1 -> 0.13647593 | C17: Cálculo: (1 + i trimestral)^4 − 1
A18: Cuota trimestral constante (USD) | B18: =PMT(B16,B12,-B9) -> 5106.0609 | C18: Sistema francés: P·i / (1 − (1+i)^−n)
A19: Total pagado en el plazo (USD) | B19: =B18*B12 -> 204242.44 | C19: Cálculo
A20: Total de intereses (USD) | B20: =B19-B9 -> 90844.824 | C20: Cálculo
A23: Fuentes, fecha de consulta y forma de cotización
A24: Dato | B24: Valor | C24: Fuente (URL) | E24: Forma de cotización
A25: Prime Rate | B25: 7,00 % | C25: https://primerates.com/prime-rate-rises-7-percent-fed-first-hike-since-july-2023/ ; https://s203.q4cdn.com/711684571/files/doc_news/U-S--Bank-Increases-Prime-Lending-Rate-to-7-00-Percent-2026.pdf | E25: Tasa base anual; vigente desde el 17/09/2026 (antes 6,75 %). Cambia cuando la Fed mueve su tasa
A26: Tope SBA 7(a), préstamos de USD 50.001 a 250.000 | B26: Prime + 6,0 % (13,00 % con Prime de 7 %) | C26: https://www.sba.gov/es/node/8664 (Terms, conditions, and eligibility) ; https://www.nerdwallet.com/article/small-business/sba-loan-rates (topes fijos y variables, act. 16/09/2026) | E26: Tope regulatorio de la SBA; el banco puede cotizar por debajo. Tasa fija o variable
A27: TRM COP/USD | B27: 3.174,67 | C27: https://dolar.wilkinsonpc.com.co/ (reproduce la TRM certificada por la Superfinanciera; verificar en https://www.superfinanciera.gov.co) | E27: COP por 1 USD; vigente del 17 al 19 de oct. de 2026
A28: SOFR (referencia, no usada en el cálculo) | B28: 3,89 % (15/10/2026) | C28: https://fred.stlouisfed.org/series/SOFR | E28: Tasa overnight publicada por la NY Fed; promedio de 30 días: 3,87449 % (16/10/2026)
A29: Comisión de garantía SBA 7(a), año fiscal 2027 | B29: 2 % de la parte garantizada (85 %) | C29: https://colemanreport.com/sba-hot-topic-tuesday-grocery-manufacturing-and-rural-businesses-get-new-fy-2027-fee-relief/ ; https://www.nerdwallet.com/business/loans/learn/sba-7a-loan (garantía de 85 % hasta USD 150.000) | E29: Pago único al desembolso para préstamos de USD 150.000 o menos aprobados entre el 01/10/2026 y el 30/09/2027
A30: Tasa SBA 504, debenture de 10 años | B30: 6,60 % (venta del 10/09/2026) | C30: https://www.crowdfundedwealth.com/articles/sba-504-loan-rates-2026 (datos de SomerCor CDC) | E30: Tasa fija efectiva con comisiones incluidas; solo cubre el 40 % del proyecto
A31: Entidad prestamista: U.S. Bank | B31: SBA 7(a) y 504; sin cargos propios de procesamiento | C31: https://www.usbank.com/business-banking/business-lending/sba-loans.html ; https://www.usbank.com/about-us-bank/news-and-stories/article-library/us-bank-boosts-sba-lending-to-a-record-943-million-in-7a-loans.html | E31: 7(a) para equipo hasta 10 años, con opción de tasa fija o variable
A32: Requisito de propiedad de la SBA | B32: 100 % de dueños ciudadanos o nacionales de EE. UU. | C32: https://www.naggl.org/procedural-notice-revising-sop-50-10-8-for-new-citizenship-and-residency-requirements/ | E32: Aviso 5000-876626, vigente desde el 01/03/2026 para 7(a) y 504

Sheet Amortización
A1: Tabla de amortización – Sistema francés, cuotas trimestrales constantes (USD)
A2: Todos los valores se calculan con las celdas de la hoja Supuestos.
A4: Trimestre | B4: Año | C4: Saldo inicial (USD) | D4: Cuota (USD) | E4: Interés (USD) | F4: Abono a capital (USD) | G4: Saldo final (USD)
A5: 1 | B5: =ROUNDUP(A5/Supuestos!$B$11,0) -> 1 | C5: =Supuestos!$B$9 -> 113397.61 | D5: =Supuestos!$B$18 -> 5106.0609 | E5: =C5*Supuestos!$B$16 -> 3685.4224 | F5: =D5-E5 -> 1420.6385 | G5: =C5-F5 -> 111976.97
A6: 2 | B6: =ROUNDUP(A6/Supuestos!$B$11,0) -> 1 | C6: =G5 -> 111976.97 | D6: =Supuestos!$B$18 -> 5106.0609 | E6: =C6*Supuestos!$B$16 -> 3639.2517 | F6: =D6-E6 -> 1466.8092 | G6: =C6-F6 -> 110510.17
A7: 3 | B7: =ROUNDUP(A7/Supuestos!$B$11,0) -> 1 | C7: =G6 -> 110510.17 | D7: =Supuestos!$B$18 -> 5106.0609 | E7: =C7*Supuestos!$B$16 -> 3591.5804 | F7: =D7-E7 -> 1514.4805 | G7: =C7-F7 -> 108995.68
A8: 4 | B8: =ROUNDUP(A8/Supuestos!$B$11,0) -> 1 | C8: =G7 -> 108995.68 | D8: =Supuestos!$B$18 -> 5106.0609 | E8: =C8*Supuestos!$B$16 -> 3542.3598 | F8: =D8-E8 -> 1563.7012 | G8: =C8-F8 -> 107431.98
A9: 5 | B9: =ROUNDUP(A9/Supuestos!$B$11,0) -> 2 | C9: =G8 -> 107431.98 | D9: =Supuestos!$B$18 -> 5106.0609 | E9: =C9*Supuestos!$B$16 -> 3491.5395 | F9: =D9-E9 -> 1614.5215 | G9: =C9-F9 -> 105817.46
A10: 6 | B10: =ROUNDUP(A10/Supuestos!$B$11,0) -> 2 | C10: =G9 -> 105817.46 | D10: =Supuestos!$B$18 -> 5106.0609 | E10: =C10*Supuestos!$B$16 -> 3439.0675 | F10: =D10-E10 -> 1666.9934 | G10: =C10-F10 -> 104150.47
A11: 7 | B11: =ROUNDUP(A11/Supuestos!$B$11,0) -> 2 | C11: =G10 -> 104150.47 | D11: =Supuestos!$B$18 -> 5106.0609 | E11: =C11*Supuestos!$B$16 -> 3384.8902 | F11: =D11-E11 -> 1721.1707 | G11: =C11-F11 -> 102429.3
A12: 8 | B12: =ROUNDUP(A12/Supuestos!$B$11,0) -> 2 | C12: =G11 -> 102429.3 | D12: =Supuestos!$B$18 -> 5106.0609 | E12: =C12*Supuestos!$B$16 -> 3328.9522 | F12: =D12-E12 -> 1777.1087 | G12: =C12-F12 -> 100652.19
A13: 9 | B13: =ROUNDUP(A13/Supuestos!$B$11,0) -> 3 | C13: =G12 -> 100652.19 | D13: =Supuestos!$B$18 -> 5106.0609 | E13: =C13*Supuestos!$B$16 -> 3271.1962 | F13: =D13-E13 -> 1834.8648 | G13: =C13-F13 -> 98817.324
A14: 10 | B14: =ROUNDUP(A14/Supuestos!$B$11,0) -> 3 | C14: =G13 -> 98817.324 | D14: =Supuestos!$B$18 -> 5106.0609 | E14: =C14*Supuestos!$B$16 -> 3211.563 | F14: =D14-E14 -> 1894.4979 | G14: =C14-F14 -> 96922.827
A15: 11 | B15: =ROUNDUP(A15/Supuestos!$B$11,0) -> 3 | C15: =G14 -> 96922.827 | D15: =Supuestos!$B$18 -> 5106.0609 | E15: =C15*Supuestos!$B$16 -> 3149.9919 | F15: =D15-E15 -> 1956.0691 | G15: =C15-F15 -> 94966.758
A16: 12 | B16: =ROUNDUP(A16/Supuestos!$B$11,0) -> 3 | C16: =G15 -> 94966.758 | D16: =Supuestos!$B$18 -> 5106.0609 | E16: =C16*Supuestos!$B$16 -> 3086.4196 | F16: =D16-E16 -> 2019.6413 | G16: =C16-F16 -> 92947.116
A17: 13 | B17: =ROUNDUP(A17/Supuestos!$B$11,0) -> 4 | C17: =G16 -> 92947.116 | D17: =Supuestos!$B$18 -> 5106.0609 | E17: =C17*Supuestos!$B$16 -> 3020.7813 | F17: =D17-E17 -> 2085.2796 | G17: =C17-F17 -> 90861.837
... A44: 40 | B44: =ROUNDUP(A44/Supuestos!$B$11,0) -> 10 | C44: =G43 -> 4945.3375 | D44: =Supuestos!$B$18 -> 5106.0609 | E44: =C44*Supuestos!$B$16 -> 160.72347 | F44: =D44-E44 -> 4945.3375 | G44: =C44-F44 -> -1.3187673e-10
A45: Total | D45: =SUM(D5:D44) -> 204242.44 | E45: =SUM(E5:E44) -> 90844.824 | F45: =SUM(F5:F44) -> 113397.61
G47: =ROUND(G44,2) -> 0
G48: =ROUND(F45-Supuestos!B9,2) -> 0

Sheet A.3 Conversión
A1: A.3 Conversión del crédito a pesos colombianos
A2: Cada cuota en USD (constante) se multiplica por la TRM de su trimestre. Primero con la TRM spot de la fecha de valoración y luego con las trayectorias de la hoja «Trayectorias TRM».
A3: TRM spot (fecha de valoración) | B3: =Supuestos!B8 -> 3174.67
A4: Cuota trimestral (USD) | B4: =Supuestos!B18 -> 5106.0609
A5: Monto recibido (COP) | B5: =Supuestos!B7 -> 360000000
A7: Trimestre | B7: Año | C7: Cuota USD | D7: Interés USD | E7: Abono capital USD | F7: Cuota COP – spot | G7: Cuota COP – base | H7: Cuota COP – peso fuerte | I7: Cuota COP – peso débil | J7: Cuota COP – sim. P5 | K7: Cuota COP – sim. P50 | L7: Cuota COP – sim. P95 | M7: Cuota COP – sim. media | N7: Base: interés a TRM spot | O7: Base: capital a TRM spot | P7: Base: efecto cambiario sobre interés | Q7: Base: efecto cambiario sobre capital | R7: Cambio de la cuota base vs trimestre anterior
A8: 1 | B8: =Amortización!B5 -> 1 | C8: =Amortización!D5 -> 5106.0609 | D8: =Amortización!E5 -> 3685.4224 | E8: =Amortización!F5 -> 1420.6385 | F8: =$C8*'Trayectorias TRM'!C6 -> 16210058 | G8: =$C8*'Trayectorias TRM'!D6 -> 16457121 | H8: =$C8*'Trayectorias TRM'!E6 -> 16143047 | I8: =$C8*'Trayectorias TRM'!F6 -> 16836488 | J8: =$C8*'Trayectorias TRM'!G6 -> 15272255 | K8: =$C8*'Trayectorias TRM'!I6 -> 16477735 | L8: =$C8*'Trayectorias TRM'!K6 -> 17784897 | M8: =$C8*'Trayectorias TRM'!L6 -> 16497255 | N8: =D8*$B$3 -> 11700000 | O8: =E8*$B$3 -> 4510058.4 | P8: =D8*('Trayectorias TRM'!D6-$B$3) -> 178323.27 | Q8: =E8*('Trayectorias TRM'!D6-$B$3) -> 68739.176 | R8: =G8-F8 -> 247062.44
A9: 2 | B9: =Amortización!B6 -> 1 | C9: =Amortización!D6 -> 5106.0609 | D9: =Amortización!E6 -> 3639.2517 | E9: =Amortización!F6 -> 1466.8092 | F9: =$C9*'Trayectorias TRM'!C7 -> 16210058 | G9: =$C9*'Trayectorias TRM'!D7 -> 16707949 | H9: =$C9*'Trayectorias TRM'!E7 -> 16076313 | I9: =$C9*'Trayectorias TRM'!F7 -> 17487126 | J9: =$C9*'Trayectorias TRM'!G7 -> 15150281 | K9: =$C9*'Trayectorias TRM'!I7 -> 16736022 | L9: =$C9*'Trayectorias TRM'!K7 -> 18525210 | M9: =$C9*'Trayectorias TRM'!L7 -> 16774908 | N9: =D9*$B$3 -> 11553423 | O9: =E9*$B$3 -> 4656635.3 | P9: =D9*('Trayectorias TRM'!D7-$B$3) -> 354862.32 | Q9: =E9*('Trayectorias TRM'!D7-$B$3) -> 143028.12 | R9: =G9-G8 -> 250828
A10: 3 | B10: =Amortización!B7 -> 1 | C10: =Amortización!D7 -> 5106.0609 | D10: =Amortización!E7 -> 3591.5804 | E10: =Amortización!F7 -> 1514.4805 | F10: =$C10*'Trayectorias TRM'!C8 -> 16210058 | G10: =$C10*'Trayectorias TRM'!D8 -> 16962600 | H10: =$C10*'Trayectorias TRM'!E8 -> 16009854 | I10: =$C10*'Trayectorias TRM'!F8 -> 18162908 | J10: =$C10*'Trayectorias TRM'!G8 -> 15259964 | K10: =$C10*'Trayectorias TRM'!I8 -> 16977448 | L10: =$C10*'Trayectorias TRM'!K8 -> 19069517 | M10: =$C10*'Trayectorias TRM'!L8 -> 17047665 | N10: =D10*$B$3 -> 11402082 | O10: =E10*$B$3 -> 4807976 | P10: =D10*('Trayectorias TRM'!D8-$B$3) -> 529334.24 | Q10: =E10*('Trayectorias TRM'!D8-$B$3) -> 223207.15 | R10: =G10-G9 -> 254650.94
A11: 4 | B11: =Amortización!B8 -> 1 | C11: =Amortización!D8 -> 5106.0609 | D11: =Amortización!E8 -> 3542.3598 | E11: =Amortización!F8 -> 1563.7012 | F11: =$C11*'Trayectorias TRM'!C9 -> 16210058 | G11: =$C11*'Trayectorias TRM'!D9 -> 17221132 | H11: =$C11*'Trayectorias TRM'!E9 -> 15943670 | I11: =$C11*'Trayectorias TRM'!F9 -> 18864805 | J11: =$C11*'Trayectorias TRM'!G9 -> 15515505 | K11: =$C11*'Trayectorias TRM'!I9 -> 17212007 | L11: =$C11*'Trayectorias TRM'!K9 -> 19562390 | M11: =$C11*'Trayectorias TRM'!L9 -> 17319921 | N11: =D11*$B$3 -> 11245823 | O11: =E11*$B$3 -> 4964235.2 | P11: =D11*('Trayectorias TRM'!D9-$B$3) -> 701438.21 | Q11: =E11*('Trayectorias TRM'!D9-$B$3) -> 309635.33 | R11: =G11-G10 -> 258532.16
A12: 5 | B12: =Amortización!B9 -> 2 | C12: =Amortización!D9 -> 5106.0609 | D12: =Amortización!E9 -> 3491.5395 | E12: =Amortización!F9 -> 1614.5215 | F12: =$C12*'Trayectorias TRM'!C10 -> 16210058 | G12: =$C12*'Trayectorias TRM'!D10 -> 17303022 | H12: =$C12*'Trayectorias TRM'!E10 -> 16019486 | I12: =$C12*'Trayectorias TRM'!F10 -> 18954511 | J12: =$C12*'Trayectorias TRM'!G10 -> 14885803 | K12: =$C12*'Trayectorias TRM'!I10 -> 17323662 | L12: =$C12*'Trayectorias TRM'!K10 -> 20416124 | M12: =$C12*'Trayectorias TRM'!L10 -> 17443286 | N12: =D12*$B$3 -> 11084486 | O12: =E12*$B$3 -> 5125572.8 | P12: =D12*('Trayectorias TRM'!D10-$B$3) -> 747371.77 | Q12: =E12*('Trayectorias TRM'!D10-$B$3) -> 345591.9 | R12: =G12-G11 -> 81890.131
A13: 6 | B13: =Amortización!B10 -> 2 | C13: =Amortización!D10 -> 5106.0609 | D13: =Amortización!E10 -> 3439.0675 | E13: =Amortización!F10 -> 1666.9934 | F13: =$C13*'Trayectorias TRM'!C11 -> 16210058 | G13: =$C13*'Trayectorias TRM'!D11 -> 17385302 | H13: =$C13*'Trayectorias TRM'!E11 -> 16095662 | I13: =$C13*'Trayectorias TRM'!F11 -> 19044644 | J13: =$C13*'Trayectorias TRM'!G11 -> 14454139 | K13: =$C13*'Trayectorias TRM'!I11 -> 17408079 | L13: =$C13*'Trayectorias TRM'!K11 -> 21166430 | M13: =$C13*'Trayectorias TRM'!L11 -> 17561634 | N13: =D13*$B$3 -> 10917904 | O13: =E13*$B$3 -> 5292153.9 | P13: =D13*('Trayectorias TRM'!D11-$B$3) -> 791557.49 | Q13: =E13*('Trayectorias TRM'!D11-$B$3) -> 383685.72 | R13: =G13-G12 -> 82279.536
A14: 7 | B14: =Amortización!B11 -> 2 | C14: =Amortización!D11 -> 5106.0609 | D14: =Amortización!E11 -> 3384.8902 | E14: =Amortización!F11 -> 1721.1707 | F14: =$C14*'Trayectorias TRM'!C12 -> 16210058 | G14: =$C14*'Trayectorias TRM'!D12 -> 17467972 | H14: =$C14*'Trayectorias TRM'!E12 -> 16172200 | I14: =$C14*'Trayectorias TRM'!F12 -> 19135205 | J14: =$C14*'Trayectorias TRM'!G12 -> 14084081 | K14: =$C14*'Trayectorias TRM'!I12 -> 17525367 | L14: =$C14*'Trayectorias TRM'!K12 -> 21933653 | M14: =$C14*'Trayectorias TRM'!L12 -> 17705404 | N14: =D14*$B$3 -> 10745909 | O14: =E14*$B$3 -> 5464148.9 | P14: =D14*('Trayectorias TRM'!D12-$B$3) -> 833891.5 | Q14: =E14*('Trayectorias TRM'!D12-$B$3) -> 424022.5 | R14: =G14-G13 -> 82670.792
A15: 8 | B15: =Amortización!B12 -> 2 | C15: =Amortización!D12 -> 5106.0609 | D15: =Amortización!E12 -> 3328.9522 | E15: =Amortización!F12 -> 1777.1087 | F15: =$C15*'Trayectorias TRM'!C13 -> 16210058 | G15: =$C15*'Trayectorias TRM'!D13 -> 17551036 | H15: =$C15*'Trayectorias TRM'!E13 -> 16249102 | I15: =$C15*'Trayectorias TRM'!F13 -> 19226197 | J15: =$C15*'Trayectorias TRM'!G13 -> 13791879 | K15: =$C15*'Trayectorias TRM'!I13 -> 17626132 | L15: =$C15*'Trayectorias TRM'!K13 -> 22555925 | M15: =$C15*'Trayectorias TRM'!L13 -> 17822281 | N15: =D15*$B$3 -> 10568325 | O15: =E15*$B$3 -> 5641733.8 | P15: =D15*('Trayectorias TRM'!D13-$B$3) -> 874265.2 | Q15: =E15*('Trayectorias TRM'!D13-$B$3) -> 466712.72 | R15: =G15-G14 -> 83063.91
A16: 9 | B16: =Amortización!B13 -> 3 | C16: =Amortización!D13 -> 5106.0609 | D16: =Amortización!E13 -> 3271.1962 | E16: =Amortización!F13 -> 1834.8648 | F16: =$C16*'Trayectorias TRM'!C14 -> 16210058 | G16: =$C16*'Trayectorias TRM'!D14 -> 17634495 | H16: =$C16*'Trayectorias TRM'!E14 -> 16326370 | I16: =$C16*'Trayectorias TRM'!F14 -> 19317622 | J16: =$C16*'Trayectorias TRM'!G14 -> 13564801 | K16: =$C16*'Trayectorias TRM'!I14 -> 17712530 | L16: =$C16*'Trayectorias TRM'!K14 -> 23134022 | M16: =$C16*'Trayectorias TRM'!L14 -> 17946940 | N16: =D16*$B$3 -> 10384968 | O16: =E16*$B$3 -> 5825090.1 | P16: =D16*('Trayectorias TRM'!D14-$B$3) -> 912564.94 | Q16: =E16*('Trayectorias TRM'!D14-$B$3) -> 511871.86 | R16: =G16-G15 -> 83458.896
A17: 10 | B17: =Amortización!B14 -> 3 | C17: =Amortización!D14 -> 5106.0609 | D17: =Amortización!E14 -> 3211.563 | E17: =Amortización!F14 -> 1894.4979 | F17: =$C17*'Trayectorias TRM'!C15 -> 16210058 | G17: =$C17*'Trayectorias TRM'!D15 -> 17718351 | H17: =$C17*'Trayectorias TRM'!E15 -> 16404005 | I17: =$C17*'Trayectorias TRM'!F15 -> 19409481 | J17: =$C17*'Trayectorias TRM'!G15 -> 13344235 | K17: =$C17*'Trayectorias TRM'!I15 -> 17806302 | L17: =$C17*'Trayectorias TRM'!K15 -> 23820800 | M17: =$C17*'Trayectorias TRM'!L15 -> 18079269 | N17: =D17*$B$3 -> 10195653 | O17: =E17*$B$3 -> 6014405.6 | P17: =D17*('Trayectorias TRM'!D15-$B$3) -> 948671.93 | Q17: =E17*('Trayectorias TRM'!D15-$B$3) -> 559620.64 | R17: =G17-G16 -> 83855.761
A18: 11 | B18: =Amortización!B15 -> 3 | C18: =Amortización!D15 -> 5106.0609 | D18: =Amortización!E15 -> 3149.9919 | E18: =Amortización!F15 -> 1956.0691 | F18: =$C18*'Trayectorias TRM'!C16 -> 16210058 | G18: =$C18*'Trayectorias TRM'!D16 -> 17802605 | H18: =$C18*'Trayectorias TRM'!E16 -> 16482010 | I18: =$C18*'Trayectorias TRM'!F16 -> 19501777 | J18: =$C18*'Trayectorias TRM'!G16 -> 13144318 | K18: =$C18*'Trayectorias TRM'!I16 -> 17861467 | L18: =$C18*'Trayectorias TRM'!K16 -> 24397435 | M18: =$C18*'Trayectorias TRM'!L16 -> 18201770 | N18: =D18*$B$3 -> 10000185 | O18: =E18*$B$3 -> 6209873.7 | P18: =D18*('Trayectorias TRM'!D16-$B$3) -> 982461.91 | Q18: =E18*('Trayectorias TRM'!D16-$B$3) -> 610085.17 | R18: =G18-G17 -> 84254.513
A19: 12 | B19: =Amortización!B16 -> 3 | C19: =Amortización!D16 -> 5106.0609 | D19: =Amortización!E16 -> 3086.4196 | E19: =Amortización!F16 -> 2019.6413 | F19: =$C19*'Trayectorias TRM'!C17 -> 16210058 | G19: =$C19*'Trayectorias TRM'!D17 -> 17887261 | H19: =$C19*'Trayectorias TRM'!E17 -> 16560385 | I19: =$C19*'Trayectorias TRM'!F17 -> 19594512 | J19: =$C19*'Trayectorias TRM'!G17 -> 12966517 | K19: =$C19*'Trayectorias TRM'!I17 -> 17936894 | L19: =$C19*'Trayectorias TRM'!K17 -> 24934328 | M19: =$C19*'Trayectorias TRM'!L17 -> 18337267 | N19: =D19*$B$3 -> 9798363.8 | O19: =E19*$B$3 -> 6411694.6 | P19: =D19*('Trayectorias TRM'!D17-$B$3) -> 1013805 | Q19: =E19*('Trayectorias TRM'!D17-$B$3) -> 663397.28 | R19: =G19-G18 -> 84655.161
A20: 13 | B20: =Amortización!B17 -> 4 | C20: =Amortización!D17 -> 5106.0609 | D20: =Amortización!E17 -> 3020.7813 | E20: =Amortización!F17 -> 2085.2796 | F20: =$C20*'Trayectorias TRM'!C18 -> 16210058 | G20: =$C20*'Trayectorias TRM'!D18 -> 17972318 | H20: =$C20*'Trayectorias TRM'!E18 -> 16639134 | I20: =$C20*'Trayectorias TRM'!F18 -> 19687688 | J20: =$C20*'Trayectorias TRM'!G18 -> 12830507 | K20: =$C20*'Trayectorias TRM'!I18 -> 18014836 | L20: =$C20*'Trayectorias TRM'!K18 -> 25515706 | M20: =$C20*'Trayectorias TRM'!L18 -> 18458646 | N20: =D20*$B$3 -> 9589983.7 | O20: =E20*$B$3 -> 6620074.7 | P20: =D20*('Trayectorias TRM'!D18-$B$3) -> 1042565.3 | Q20: =E20*('Trayectorias TRM'!D18-$B$3) -> 719694.66 | R20: =G20-G19 -> 85057.714
... A47: 40 | B47: =Amortización!B44 -> 10 | C47: =Amortización!D44 -> 5106.0609 | D47: =Amortización!E44 -> 160.72347 | E47: =Amortización!F44 -> 4945.3375 | F47: =$C47*'Trayectorias TRM'!C45 -> 16210058 | G47: =$C47*'Trayectorias TRM'!D45 -> 20428258 | H47: =$C47*'Trayectorias TRM'!E45 -> 18912892 | I47: =$C47*'Trayectorias TRM'!F45 -> 22378035 | J47: =$C47*'Trayectorias TRM'!G45 -> 10601093 | K47: =$C47*'Trayectorias TRM'!I45 -> 20511832 | L47: =$C47*'Trayectorias TRM'!K45 -> 39723545 | M47: =$C47*'Trayectorias TRM'!L45 -> 22197403 | N47: =D47*$B$3 -> 510243.97 | O47: =E47*$B$3 -> 15699814 | P47: =D47*('Trayectorias TRM'!D45-$B$3) -> 132776.25 | Q47: =E47*('Trayectorias TRM'!D45-$B$3) -> 4085423.1 | R47: =G47-G46 -> 96680.955
A48: Total | C48: =SUM(C8:C47) -> 204242.44 | D48: =SUM(D8:D47) -> 90844.824 | E48: =SUM(E8:E47) -> 113397.61 | F48: =SUM(F8:F47) -> 6.4840234e+08 | G48: =SUM(G8:G47) -> 7.4500029e+08 | H48: =SUM(H8:H47) -> 6.9155625e+08 | I48: =SUM(I8:I47) -> 8.1368134e+08 | J48: =SUM(J8:J47) -> 4.9335431e+08 | ... Q48: =SUM(Q8:Q47) -> 62098159
A51: Resumen del costo en pesos por trayectoria
A52: Concepto | B52: TRM spot | C52: Escenario base | D52: Peso fuerte | E52: Peso débil | F52: Simulación P5 | G52: Simulación P50 | H52: Simulación P95 | I52: Simulación media
A53: Total pagado (COP) | B53: =F48 -> 6.4840234e+08 | C53: =G48 -> 7.4500029e+08 | D53: =H48 -> 6.9155625e+08 | E53: =I48 -> 8.1368134e+08 | F53: =J48 -> 4.9335431e+08 | G53: =K48 -> 7.471117e+08 | H53: =L48 -> 1.1692973e+09 | I53: =M48 -> 7.7827053e+08
A54: Diferencia frente a TRM spot (COP) | B54: =B53-$B$53 -> 0 | C54: =C53-$B$53 -> 96597952 | D54: =D53-$B$53 -> 43153914 | E54: =E53-$B$53 -> 1.65279e+08 | F54: =F53-$B$53 -> -1.5504803e+08 | G54: =G53-$B$53 -> 98709368 | H54: =H53-$B$53 -> 5.2089493e+08 | I54: =I53-$B$53 -> 1.298682e+08
A55: Diferencia frente a TRM spot (%) | B55: =B53/$B$53-1 -> 0 | C55: =C53/$B$53-1 -> 0.14897841 | D55: =D53/$B$53-1 -> 0.066554224 | E55: =E53/$B$53-1 -> 0.25490192 | F55: =F53/$B$53-1 -> -0.23912318 | G55: =G53/$B$53-1 -> 0.15223475 | H55: =H53/$B$53-1 -> 0.80335141 | I55: =I53/$B$53-1 -> 0.20028953
A56: Capital valorado a TRM spot | B56: =SUM($E$8:$E$47)*$B$3 -> 3.6e+08 | C56: =SUM($E$8:$E$47)*$B$3 -> 3.6e+08 | D56: =SUM($E$8:$E$47)*$B$3 -> 3.6e+08 | E56: =SUM($E$8:$E$47)*$B$3 -> 3.6e+08 | F56: =SUM($E$8:$E$47)*$B$3 -> 3.6e+08 | G56: =SUM($E$8:$E$47)*$B$3 -> 3.6e+08 | H56: =SUM($E$8:$E$47)*$B$3 -> 3.6e+08 | I56: =SUM($E$8:$E$47)*$B$3 -> 3.6e+08
A57: Intereses valorados a TRM spot | B57: =SUM($D$8:$D$47)*$B$3 -> 2.8840234e+08 | C57: =SUM($D$8:$D$47)*$B$3 -> 2.8840234e+08 | D57: =SUM($D$8:$D$47)*$B$3 -> 2.8840234e+08 | E57: =SUM($D$8:$D$47)*$B$3 -> 2.8840234e+08 | F57: =SUM($D$8:$D$47)*$B$3 -> 2.8840234e+08 | G57: =SUM($D$8:$D$47)*$B$3 -> 2.8840234e+08 | H57: =SUM($D$8:$D$47)*$B$3 -> 2.8840234e+08 | I57: =SUM($D$8:$D$47)*$B$3 -> 2.8840234e+08
A58: Efecto cambiario sobre intereses | B58: =SUMPRODUCT($D$8:$D$47,'Trayectorias TRM'!C$6:C$45-$B$3) -> 0 | C58: =SUMPRODUCT($D$8:$D$47,'Trayectorias TRM'!D$6:D$45-$B$3) -> 34499793 | D58: =SUMPRODUCT($D$8:$D$47,'Trayectorias TRM'!E$6:E$45-$B$3) -> 11849470 | E58: =SUMPRODUCT($D$8:$D$47,'Trayectorias TRM'!F$6:F$45-$B$3) -> 63583567 | F58: =SUMPRODUCT($D$8:$D$47,'Trayectorias TRM'!G$6:G$45-$B$3) -> -58191284 | G58: =SUMPRODUCT($D$8:$D$47,'Trayectorias TRM'!I$6:I$45-$B$3) -> 35383118 | H58: =SUMPRODUCT($D$8:$D$47,'Trayectorias TRM'!K$6:K$45-$B$3) -> 1.8176366e+08 | I58: =SUMPRODUCT($D$8:$D$47,'Trayectorias TRM'!L$6:L$45-$B$3) -> 45127940
A59: Efecto cambiario sobre capital | B59: =SUMPRODUCT($E$8:$E$47,'Trayectorias TRM'!C$6:C$45-$B$3) -> 0 | C59: =SUMPRODUCT($E$8:$E$47,'Trayectorias TRM'!D$6:D$45-$B$3) -> 62098159 | D59: =SUMPRODUCT($E$8:$E$47,'Trayectorias TRM'!E$6:E$45-$B$3) -> 31304444 | E59: =SUMPRODUCT($E$8:$E$47,'Trayectorias TRM'!F$6:F$45-$B$3) -> 1.0169544e+08 | F59: =SUMPRODUCT($E$8:$E$47,'Trayectorias TRM'!G$6:G$45-$B$3) -> -96856746 | G59: =SUMPRODUCT($E$8:$E$47,'Trayectorias TRM'!I$6:I$45-$B$3) -> 63326250 | H59: =SUMPRODUCT($E$8:$E$47,'Trayectorias TRM'!K$6:K$45-$B$3) -> 3.3913127e+08 | I59: =SUMPRODUCT($E$8:$E$47,'Trayectorias TRM'!L$6:L$45-$B$3) -> 84740258
A60: Comprobación (suma − total) | B60: =ROUND(SUM(B56:B59)-B53,0) -> 0 | C60: =ROUND(SUM(C56:C59)-C53,0) -> 0 | D60: =ROUND(SUM(D56:D59)-D53,0) -> 0 | E60: =ROUND(SUM(E56:E59)-E53,0) -> 0 | F60: =ROUND(SUM(F56:F59)-F53,0) -> 0 | G60: =ROUND(SUM(G56:G59)-G53,0) -> 0 | H60: =ROUND(SUM(H56:H59)-H53,0) -> 0 | I60: =ROUND(SUM(I56:I59)-I53,0) -> 0
A61: Cuota máxima (COP) | B61: =MAX(F8:F47) -> 16210058 | C61: =MAX(G8:G47) -> 20428258 | D61: =MAX(H8:H47) -> 18912892 | E61: =MAX(I8:I47) -> 22378035 | F61: =MAX(J8:J47) -> 15515505 | G61: =MAX(K8:K47) -> 20511832 | H61: =MAX(L8:L47) -> 39723545 | I61: =MAX(M8:M47) -> 22197403
A62: Costo efectivo anual en COP (TIR) | B62: =(1+IRR(B68:B108))^4-1 -> 0.13647593 | C62: =(1+IRR(C68:C108))^4-1 -> 0.16939587 | D62: =(1+IRR(D68:D108))^4-1 -> 0.14891638 | E62: =(1+IRR(E68:E108))^4-1 -> 0.19485355 | F62: =(1+IRR(F68:F108))^4-1 -> 0.072495105 | G62: =(1+IRR(G68:G108))^4-1 -> 0.17017612 | H62: =(1+IRR(H68:H108))^4-1 -> 0.28062054 | I62: =(1+IRR(I68:I108))^4-1 -> 0.17894916
A63: Promedio de la TRM durante el crédito | B63: =AVERAGE('Trayectorias TRM'!C$6:C$45) -> 3174.67 | C63: =AVERAGE('Trayectorias TRM'!D$6:D$45) -> 3647.6273 | D63: =AVERAGE('Trayectorias TRM'!E$6:E$45) -> 3385.9577 | E63: =AVERAGE('Trayectorias TRM'!F$6:F$45) -> 3983.8995 | F63: =AVERAGE('Trayectorias TRM'!G$6:G$45) -> 2415.5328 | G63: =AVERAGE('Trayectorias TRM'!I$6:I$45) -> 3657.9651 | H63: =AVERAGE('Trayectorias TRM'!K$6:K$45) -> 5725.0456 | I63: =AVERAGE('Trayectorias TRM'!L$6:L$45) -> 3810.5232
A66: Flujos en COP para calcular la TIR (trimestre 0 = desembolso recibido)
A67: Trimestre | B67: TRM spot | C67: Escenario base | D67: Peso fuerte | E67: Peso débil | F67: Simulación P5 | G67: Simulación P50 | H67: Simulación P95 | I67: Simulación media
A68: 0 | B68: =$B$5 -> 360000000 | C68: =$B$5 -> 360000000 | D68: =$B$5 -> 360000000 | E68: =$B$5 -> 360000000 | F68: =$B$5 -> 360000000 | G68: =$B$5 -> 360000000 | H68: =$B$5 -> 360000000 | I68: =$B$5 -> 360000000
A69: 1 | B69: =-F8 -> -16210058 | C69: =-G8 -> -16457121 | D69: =-H8 -> -16143047 | E69: =-I8 -> -16836488 | F69: =-J8 -> -15272255 | G69: =-K8 -> -16477735 | H69: =-L8 -> -17784897 | I69: =-M8 -> -16497255
A70: 2 | B70: =-F9 -> -16210058 | C70: =-G9 -> -16707949 | D70: =-H9 -> -16076313 | E70: =-I9 -> -17487126 | F70: =-J9 -> -15150281 | G70: =-K9 -> -16736022 | H70: =-L9 -> -18525210 | I70: =-M9 -> -16774908
A71: 3 | B71: =-F10 -> -16210058 | C71: =-G10 -> -16962600 | D71: =-H10 -> -16009854 | E71: =-I10 -> -18162908 | F71: =-J10 -> -15259964 | G71: =-K10 -> -16977448 | H71: =-L10 -> -19069517 | I71: =-M10 -> -17047665
A72: 4 | B72: =-F11 -> -16210058 | C72: =-G11 -> -17221132 | D72: =-H11 -> -15943670 | E72: =-I11 -> -18864805 | F72: =-J11 -> -15515505 | G72: =-K11 -> -17212007 | H72: =-L11 -> -19562390 | I72: =-M11 -> -17319921
A73: 5 | B73: =-F12 -> -16210058 | C73: =-G12 -> -17303022 | D73: =-H12 -> -16019486 | E73: =-I12 -> -18954511 | F73: =-J12 -> -14885803 | G73: =-K12 -> -17323662 | H73: =-L12 -> -20416124 | I73: =-M12 -> -17443286
A74: 6 | B74: =-F13 -> -16210058 | C74: =-G13 -> -17385302 | D74: =-H13 -> -16095662 | E74: =-I13 -> -19044644 | F74: =-J13 -> -14454139 | G74: =-K13 -> -17408079 | H74: =-L13 -> -21166430 | I74: =-M13 -> -17561634
A75: 7 | B75: =-F14 -> -16210058 | C75: =-G14 -> -17467972 | D75: =-H14 -> -16172200 | E75: =-I14 -> -19135205 | F75: =-J14 -> -14084081 | G75: =-K14 -> -17525367 | H75: =-L14 -> -21933653 | I75: =-M14 -> -17705404
A76: 8 | B76: =-F15 -> -16210058 | C76: =-G15 -> -17551036 | D76: =-H15 -> -16249102 | E76: =-I15 -> -19226197 | F76: =-J15 -> -13791879 | G76: =-K15 -> -17626132 | H76: =-L15 -> -22555925 | I76: =-M15 -> -17822281
A77: 9 | B77: =-F16 -> -16210058 | C77: =-G16 -> -17634495 | D77: =-H16 -> -16326370 | E77: =-I16 -> -19317622 | F77: =-J16 -> -13564801 | G77: =-K16 -> -17712530 | H77: =-L16 -> -23134022 | I77: =-M16 -> -17946940
A78: 10 | B78: =-F17 -> -16210058 | C78: =-G17 -> -17718351 | D78: =-H17 -> -16404005 | E78: =-I17 -> -19409481 | F78: =-J17 -> -13344235 | G78: =-K17 -> -17806302 | H78: =-L17 -> -23820800 | I78: =-M17 -> -18079269
A79: 11 | B79: =-F18 -> -16210058 | C79: =-G18 -> -17802605 | D79: =-H18 -> -16482010 | E79: =-I18 -> -19501777 | F79: =-J18 -> -13144318 | G79: =-K18 -> -17861467 | H79: =-L18 -> -24397435 | I79: =-M18 -> -18201770
A80: 12 | B80: =-F19 -> -16210058 | C80: =-G19 -> -17887261 | D80: =-H19 -> -16560385 | E80: =-I19 -> -19594512 | F80: =-J19 -> -12966517 | G80: =-K19 -> -17936894 | H80: =-L19 -> -24934328 | I80: =-M19 -> -18337267
... A108: 40 | B108: =-F47 -> -16210058 | C108: =-G47 -> -20428258 | D108: =-H47 -> -18912892 | E108: =-I47 -> -22378035 | F108: =-J47 -> -10601093 | G108: =-K47 -> -20511832 | H108: =-L47 -> -39723545 | I108: =-M47 -> -22197403
A111: Efecto sobre el flujo de caja: pago anual del crédito en pesos
A112: Año | B112: TRM spot | C112: Escenario base | D112: Peso fuerte | E112: Peso débil | F112: Simulación P95 | G112: Base − spot | H112: P95 − spot | I112: Interés en USD del año | J112: Capital en USD del año
A113: 1 | B113: =SUMIF($B$8:$B$47,$A113,F$8:F$47) -> 64840234 | C113: =SUMIF($B$8:$B$47,$A113,G$8:G$47) -> 67348801 | D113: =SUMIF($B$8:$B$47,$A113,H$8:H$47) -> 64172883 | E113: =SUMIF($B$8:$B$47,$A113,I$8:I$47) -> 71351328 | F113: =SUMIF($B$8:$B$47,$A113,L$8:L$47) -> 74942014 | G113: =C113-B113 -> 2508567.8 | H113: =F113-B113 -> 10101780 | I113: =SUMIF($B$8:$B$47,$A113,$D$8:$D$47) -> 14458.614 | J113: =SUMIF($B$8:$B$47,$A113,$E$8:$E$47) -> 5965.6295
A114: 2 | B114: =SUMIF($B$8:$B$47,$A114,F$8:F$47) -> 64840234 | C114: =SUMIF($B$8:$B$47,$A114,G$8:G$47) -> 69707332 | D114: =SUMIF($B$8:$B$47,$A114,H$8:H$47) -> 64536449 | E114: =SUMIF($B$8:$B$47,$A114,I$8:I$47) -> 76360557 | F114: =SUMIF($B$8:$B$47,$A114,L$8:L$47) -> 86072132 | G114: =C114-B114 -> 4867098.8 | H114: =F114-B114 -> 21231898 | I114: =SUMIF($B$8:$B$47,$A114,$D$8:$D$47) -> 13644.449 | J114: =SUMIF($B$8:$B$47,$A114,$E$8:$E$47) -> 6779.7943
A115: 3 | B115: =SUMIF($B$8:$B$47,$A115,F$8:F$47) -> 64840234 | C115: =SUMIF($B$8:$B$47,$A115,G$8:G$47) -> 71042712 | D115: =SUMIF($B$8:$B$47,$A115,H$8:H$47) -> 65772771 | E115: =SUMIF($B$8:$B$47,$A115,I$8:I$47) -> 77823392 | F115: =SUMIF($B$8:$B$47,$A115,L$8:L$47) -> 96286585 | G115: =C115-B115 -> 6202478.7 | H115: =F115-B115 -> 31446352 | I115: =SUMIF($B$8:$B$47,$A115,$D$8:$D$47) -> 12719.171 | J115: =SUMIF($B$8:$B$47,$A115,$E$8:$E$47) -> 7705.073
A116: 4 | B116: =SUMIF($B$8:$B$47,$A116,F$8:F$47) -> 64840234 | C116: =SUMIF($B$8:$B$47,$A116,G$8:G$47) -> 72403674 | D116: =SUMIF($B$8:$B$47,$A116,H$8:H$47) -> 67032777 | E116: =SUMIF($B$8:$B$47,$A116,I$8:I$47) -> 79314251 | F116: =SUMIF($B$8:$B$47,$A116,L$8:L$47) -> 1.0539415e+08 | G116: =C116-B116 -> 7563440.4 | H116: =F116-B116 -> 40553915 | I116: =SUMIF($B$8:$B$47,$A116,$D$8:$D$47) -> 11667.614 | J116: =SUMIF($B$8:$B$47,$A116,$E$8:$E$47) -> 8756.63
A117: 5 | B117: =SUMIF($B$8:$B$47,$A117,F$8:F$47) -> 64840234 | C117: =SUMIF($B$8:$B$47,$A117,G$8:G$47) -> 73790708 | D117: =SUMIF($B$8:$B$47,$A117,H$8:H$47) -> 68316920 | E117: =SUMIF($B$8:$B$47,$A117,I$8:I$47) -> 80833670 | F117: =SUMIF($B$8:$B$47,$A117,L$8:L$47) -> 1.1382212e+08 | G117: =C117-B117 -> 8950474 | H117: =F117-B117 -> 48981888 | I117: =SUMIF($B$8:$B$47,$A117,$D$8:$D$47) -> 10472.544 | J117: =SUMIF($B$8:$B$47,$A117,$E$8:$E$47) -> 9951.6992
A118: 6 | B118: =SUMIF($B$8:$B$47,$A118,F$8:F$47) -> 64840234 | C118: =SUMIF($B$8:$B$47,$A118,G$8:G$47) -> 75204313 | D118: =SUMIF($B$8:$B$47,$A118,H$8:H$47) -> 69625664 | E118: =SUMIF($B$8:$B$47,$A118,I$8:I$47) -> 82382197 | F118: =SUMIF($B$8:$B$47,$A118,L$8:L$47) -> 1.2231275e+08 | G118: =C118-B118 -> 10364079 | H118: =F118-B118 -> 57472514 | I118: =SUMIF($B$8:$B$47,$A118,$D$8:$D$47) -> 9114.3771 | J118: =SUMIF($B$8:$B$47,$A118,$E$8:$E$47) -> 11309.867
A119: 7 | B119: =SUMIF($B$8:$B$47,$A119,F$8:F$47) -> 64840234 | C119: =SUMIF($B$8:$B$47,$A119,G$8:G$47) -> 76644998 | D119: =SUMIF($B$8:$B$47,$A119,H$8:H$47) -> 70959480 | E119: =SUMIF($B$8:$B$47,$A119,I$8:I$47) -> 83960388 | F119: =SUMIF($B$8:$B$47,$A119,L$8:L$47) -> 1.3051989e+08 | G119: =C119-B119 -> 11804764 | H119: =F119-B119 -> 65679656 | I119: =SUMIF($B$8:$B$47,$A119,$D$8:$D$47) -> 7570.8526 | J119: =SUMIF($B$8:$B$47,$A119,$E$8:$E$47) -> 12853.391
A120: 8 | B120: =SUMIF($B$8:$B$47,$A120,F$8:F$47) -> 64840234 | C120: =SUMIF($B$8:$B$47,$A120,G$8:G$47) -> 78113282 | D120: =SUMIF($B$8:$B$47,$A120,H$8:H$47) -> 72318847 | E120: =SUMIF($B$8:$B$47,$A120,I$8:I$47) -> 85568813 | F120: =SUMIF($B$8:$B$47,$A120,L$8:L$47) -> 1.3819827e+08 | G120: =C120-B120 -> 13273049 | H120: =F120-B120 -> 73358039 | I120: =SUMIF($B$8:$B$47,$A120,$D$8:$D$47) -> 5816.6741 | J120: =SUMIF($B$8:$B$47,$A120,$E$8:$E$47) -> 14607.57
A121: 9 | B121: =SUMIF($B$8:$B$47,$A121,F$8:F$47) -> 64840234 | C121: =SUMIF($B$8:$B$47,$A121,G$8:G$47) -> 79609695 | D121: =SUMIF($B$8:$B$47,$A121,H$8:H$47) -> 73704255 | E121: =SUMIF($B$8:$B$47,$A121,I$8:I$47) -> 87208051 | F121: =SUMIF($B$8:$B$47,$A121,L$8:L$47) -> 1.4624215e+08 | G121: =C121-B121 -> 14769461 | H121: =F121-B121 -> 81401919 | I121: =SUMIF($B$8:$B$47,$A121,$D$8:$D$47) -> 3823.0925 | J121: =SUMIF($B$8:$B$47,$A121,$E$8:$E$47) -> 16601.151
A122: 10 | B122: =SUMIF($B$8:$B$47,$A122,F$8:F$47) -> 64840234 | C122: =SUMIF($B$8:$B$47,$A122,G$8:G$47) -> 81134773 | D122: =SUMIF($B$8:$B$47,$A122,H$8:H$47) -> 75116204 | E122: =SUMIF($B$8:$B$47,$A122,I$8:I$47) -> 88878691 | F122: =SUMIF($B$8:$B$47,$A122,L$8:L$47) -> 1.5550721e+08 | G122: =C122-B122 -> 16294540 | H122: =F122-B122 -> 90666972 | I122: =SUMIF($B$8:$B$47,$A122,$D$8:$D$47) -> 1557.435 | J122: =SUMIF($B$8:$B$47,$A122,$E$8:$E$47) -> 18866.809
A125: Resultados de la simulación (20.000 trayectorias; valores calculados en Python con la ventana de flotación libre)
A126: Indicador | B126: Media | C126: P5 | D126: P50 | E126: P95
A127: Total pagado en COP | B127: 7.7827053e+08 | C127: 5.2916188e+08 | D127: 7.5213107e+08 | E127: 1.1159474e+09
A128: Diferencia frente a TRM spot (COP) | B128: 1.298682e+08 | C128: -1.1924046e+08 | D128: 1.0372874e+08 | E128: 4.6754508e+08
A129: Efecto cambiario sobre intereses (COP) | B129: 45127940 | C129: -42309213 | D129: 37506525 | E129: 1.5921551e+08
A130: Efecto cambiario sobre capital (COP) | B130: 84740258 | C130: -79608410 | D130: 65984067 | E130: 3.1017546e+08
A131: Costo efectivo anual en COP | B131: 0.17387099 | C131: 0.090894799 | D131: 0.17200251 | E131: 0.26265013
A132: Cuota máxima del crédito (COP) | B132: 26242543 | C132: 17305116 | D132: 24075996 | E132: 42304973
A133: Probabilidad de pagar más que con la TRM spot | B133: 0.7479
A134: Probabilidad de que el costo efectivo en COP supere 20 % EA | B134: 0.2995

Sheet B Supuestos
A1: Parte B – Supuestos de la cobertura y coherencia del nominal
A2: Celdas amarillas = parámetros que se pueden cambiar (todo el análisis de las hojas B.2 y B.3 con fórmulas se recalcula).
A3: Parámetro | B3: Valor | C3: Fuente / cálculo
A4: Porcentaje de la exposición cubierto | B4: 0.75
A5: Trimestre en que se inicia la cobertura (fin del año 6) | B5: 24
A6: Cuota trimestral (USD) | B6: =Supuestos!B18 -> 5106.0609 | C6: Hoja Supuestos
A7: Cuotas pendientes al fin del año 6 | B7: =Supuestos!B12-B5 -> 16 | C7: 40 − 24
A8: Exposición pendiente (USD) | B8: =B6*B7 -> 81696.975 | C8: Pagos programados de los años 7 a 10
A9: Total a cubrir (USD) | B9: =B4*B8 -> 61272.731 | C9: 75 % de la exposición pendiente
A10: i_COP para pactar los forwards (EA) | B10: ='B.1 Forward'!B35 -> 0.12949826 | C10: Tasa implícita en el forward de mercado (hoja B.1)
A11: i_USD para pactar los forwards (EA) | B11: ='B.1 Forward'!B25 -> 0.0447 | C11: Tesoro de EE. UU. a 1 año (hoja B.1)
A12: Prima forward anual | B12: =(1+B10)/(1+B11)-1 -> 0.081169961 | C12: (1 + i_COP) / (1 + i_USD) − 1
A13: Tasa de descuento en pesos para el VPN (EA) | B13: 0.13 | C13: TES a 10 años por encima de 13 % (La República, 21/10/2026)
A14: Tasa de descuento trimestral | B14: =(1+B13)^(1/4)-1 -> 0.031025985 | C14: Cálculo
A15: Tolerancia presupuestal | B15: 0.1 | C15: «Fracaso de la cobertura»: costo cubierto del año > presupuesto al forward + 10 %
A16: Umbral de pérdida cambiaria extrema | B16: 0.2 | C16: Depreciación > 20 % en el año del forward (como 2002, 2008-09, 2014-15, 2020 y 2022)
A18: Forwards y coherencia entre nominal cubierto y obligación real
A19: Forward | B19: Año que cubre | C19: Trimestre de pacto | D19: Trimestre de vencimiento | E19: Pagos USD del año | F19: Nominal (USD) | G19: ¿Nominal ≤ pagos del año? | H19: Obligación pendiente al pactar (USD) | I19: Nominal vigente + por pactar (USD) | J19: ¿Cubierto ≤ obligación? | K19: Saldo de capital al pactar (USD)
A20: 1 | B20: 7 | C20: =$B$5+4*(A20-1) -> 24 | D20: =C20+4 -> 28 | E20: =SUMIF(Amortización!$B$5:$B$44,B20,Amortización!$D$5:$D$44) -> 20424.244 | F20: =$B$4*E20 -> 15318.183 | G20: =IF(F20<=E20+0.005,"Sí","No") -> Sí | H20: =SUMIF(Amortización!$A$5:$A$44,">"&C20,Amortización!$D$5:$D$44) -> 81696.975 | I20: =SUM(F20:$F$23) -> 61272.731 | J20: =IF(I20<=H20+0.005,"Sí","No") -> Sí | K20: =INDEX(Amortización!$G$5:$G$44,C20) -> 62928.921
A21: 2 | B21: 8 | C21: =$B$5+4*(A21-1) -> 28 | D21: =C21+4 -> 32 | E21: =SUMIF(Amortización!$B$5:$B$44,B21,Amortización!$D$5:$D$44) -> 20424.244 | F21: =$B$4*E21 -> 15318.183 | G21: =IF(F21<=E21+0.005,"Sí","No") -> Sí | H21: =SUMIF(Amortización!$A$5:$A$44,">"&C21,Amortización!$D$5:$D$44) -> 61272.731 | I21: =SUM(F21:$F$23) -> 45954.548 | J21: =IF(I21<=H21+0.005,"Sí","No") -> Sí | K21: =INDEX(Amortización!$G$5:$G$44,C21) -> 50075.529
A22: 3 | B22: 9 | C22: =$B$5+4*(A22-1) -> 32 | D22: =C22+4 -> 36 | E22: =SUMIF(Amortización!$B$5:$B$44,B22,Amortización!$D$5:$D$44) -> 20424.244 | F22: =$B$4*E22 -> 15318.183 | G22: =IF(F22<=E22+0.005,"Sí","No") -> Sí | H22: =SUMIF(Amortización!$A$5:$A$44,">"&C22,Amortización!$D$5:$D$44) -> 40848.487 | I22: =SUM(F22:$F$23) -> 30636.366 | J22: =IF(I22<=H22+0.005,"Sí","No") -> Sí | K22: =INDEX(Amortización!$G$5:$G$44,C22) -> 35467.96
A23: 4 | B23: 10 | C23: =$B$5+4*(A23-1) -> 36 | D23: =C23+4 -> 40 | E23: =SUMIF(Amortización!$B$5:$B$44,B23,Amortización!$D$5:$D$44) -> 20424.244 | F23: =$B$4*E23 -> 15318.183 | G23: =IF(F23<=E23+0.005,"Sí","No") -> Sí | H23: =SUMIF(Amortización!$A$5:$A$44,">"&C23,Amortización!$D$5:$D$44) -> 20424.244 | I23: =SUM(F23:$F$23) -> 15318.183 | J23: =IF(I23<=H23+0.005,"Sí","No") -> Sí | K23: =INDEX(Amortización!$G$5:$G$44,C23) -> 18866.809
A24: Total | E24: =SUM(E20:E23) -> 81696.975 | F24: =SUM(F20:F23) -> 61272.731
A25: Comprobación: total nominal = total a cubrir | F25: =IF(ABS(F24-B9)<0.01,"Correcto","Revisar") -> Correcto

Sheet B.1 Forward
A1: B.1 Cotización y valoración del forward USD/COP
A2: Valores en azul = datos consultados (con fuente); las demás cifras son fórmulas. La cotización de SET-FX para forwards no es de acceso público; se usa la curva forward USD/COP de Cbonds (precio medio al cierre de Londres) y se verifica con la TRM oficial y el cierre de SET-FX.
A4: Dato | B4: Valor (COP por USD) | C4: Fuente | D4: Fecha del dato | E4: Fecha de consulta | F4: Nota
A5: Spot (S/N) | B5: 3132.07 | C5: Cbonds, USD/COP S/N FX Forward Rate (Mid), https://cbonds.com.tr/indexes/215883/ | D5: 46322 | E5: 46323 | F5: Spot de referencia para los puntos forward
A6: Forward 6 meses | B6: 3252.9 | C6: Cbonds, misma página (tenor 6M) | D6: 46322 | E6: 46323 | F6: Plazo superior a seis meses
A7: Forward 1 año | B7: 3386.3 | C7: Cbonds, USD/COP 1Y FX Forward Rate (Mid), https://cbonds.com/indexes/215895/ | D7: 46322 | E7: 46323 | F7: Plazo de cada forward de la estrategia
A8: Forward 2 años | B8: 3654.14 | C8: Cbonds, misma página (tenor 2Y) | D8: 46322 | E8: 46323 | F8: Referencia de la pendiente de la curva
A9: TRM vigente | B9: 3148.02 | C9: Banco de la República, https://totoro.banrep.gov.co/estadisticas-economicas/ | D9: 46323 | E9: 46323 | F9: Tasa oficial (promedio del día hábil anterior)
A10: Cierre promedio SET-FX | B10: 3157.57 | C10: Infobae con datos de SET-FX, https://www.infobae.com/colombia/2026/10/26/dolar-hoy-en-colombia-cotizacion-de-cierre-del-26-de-octubre/ | D10: 46321 | E10: 46323 | F10: Mercado spot interbancario colombiano
A12: Puntos forward y devaluación implícita
A13: Plazo | B13: Años | C13: Forward | D13: Puntos forward (COP) | E13: Devaluación implícita del plazo | F13: Devaluación implícita anual
A14: 6 meses | B14: 0.5 | C14: =B6 -> 3252.9 | D14: =C14-$B$5 -> 120.83 | E14: =C14/$B$5-1 -> 0.03857832 | F14: =(1+E14)^(1/B14)-1 -> 0.078644928
A15: 1 año | B15: 1 | C15: =B7 -> 3386.3 | D15: =C15-$B$5 -> 254.23 | E15: =C15/$B$5-1 -> 0.081169961 | F15: =(1+E15)^(1/B15)-1 -> 0.081169961
A16: 2 años | B16: 2 | C16: =B8 -> 3654.14 | D16: =C16-$B$5 -> 522.07 | E16: =C16/$B$5-1 -> 0.16668529 | F16: =(1+E16)^(1/B16)-1 -> 0.080132071
A18: Tasas de interés de referencia
A19: Tasa | B19: Valor | C19: Fuente | D19: Fecha del dato | E19: Plazo | F19: Convención
A20: Tasa de política del Banco de la República | B20: 0.1225 | C20: https://totoro.banrep.gov.co/estadisticas-economicas/ | D20: 46323 | E20: Un día | F20: Efectiva anual
A21: Tasa esperada del Banco de la República a fin de 2026 (encuesta) | B21: 0.125 | C21: Fedesarrollo-BVC, Encuesta de Opinión Financiera vía Portafolio, https://www.portafolio.co/economia/gobierno/una-inflacion-de-6-87-elevaria-las-tasas-del-banco-de-la-republica-a-12-50-al-cierre-de-2026-advierte-estudio-504862 | D21: 46316 | E21: Hasta dic. 2026 | F21: Efectiva anual
A22: TES a 1 año (TCO, subasta) | B22: 0.1348 | C22: La República, https://www.larepublica.co/economia/las-tasas-de-los-bonos-tes-de-corto-plazo-alcanzaron-maximos-de-mas-de-dos-decadas-4394066 | D22: 46154 | E22: 1 año | F22: Efectiva anual (dato de mayo: desactualizado)
A23: IBR a 1 mes | B23: 0.1156 | C23: Banco de Bogotá Internacional, https://www.bancodebogotainternacional.com/bbi/es/economicindicator | D23: 46322 | E23: 1 mes | F23: Nominal anual
A24: Fed funds efectiva | B24: 0.0388 | C24: Fed H.15, https://www.federalreserve.gov/releases/h15/ | D24: 46321 | E24: Un día | F24: Actual/360
A25: Tesoro de EE. UU. a 1 año (constant maturity) | B25: 0.0447 | C25: Fed H.15, https://www.federalreserve.gov/releases/h15/ | D25: 46321 | E25: 1 año | F25: Rendimiento equivalente de bono (semestral)
A27: Forward teórico a 1 año por paridad cubierta de tasas: F = S × (1 + i_COP) / (1 + i_USD)
A28: Combinación de tasas | B28: i_COP | C28: i_USD | D28: Forward teórico | E28: Forward observado | F28: Diferencia (COP) | G28: Diferencia (%) | H28: Lectura
A29: (a) Política BanRep vs Tesoro 1 año (base) | B29: =B20 -> 0.1225 | C29: =B25 -> 0.0447 | D29: =$B$5*(1+B29)/(1+C29) -> 3365.3188 | E29: =$B$7 -> 3386.3 | F29: =E29-D29 -> 20.981176 | G29: =E29/D29-1 -> 0.0062345286 | H29: Tasas usadas en A.1; i_COP es a un día
A30: (b) Tasa BanRep esperada vs Tesoro 1 año | B30: =B21 -> 0.125 | C30: =B25 -> 0.0447 | D30: =$B$5*(1+B30)/(1+C30) -> 3372.814 | E30: =$B$7 -> 3386.3 | F30: =E30-D30 -> 13.486034 | G30: =E30/D30-1 -> 0.0039984519 | H30: Incorpora la subida esperada para octubre
A31: (c) TES 1 año vs Tesoro 1 año | B31: =B22 -> 0.1348 | C31: =B25 -> 0.0447 | D31: =$B$5*(1+B31)/(1+C31) -> 3402.1949 | E31: =$B$7 -> 3386.3 | F31: =E31-D31 -> -15.894923 | G31: =E31/D31-1 -> -0.0046719613 | H31: Mismo plazo, pero incluye riesgo soberano y el dato es de mayo
A32: (d) Política BanRep vs fed funds | B32: =B20 -> 0.1225 | C32: =B24 -> 0.0388 | D32: =$B$5*(1+B32)/(1+C32) -> 3384.4326 | E32: =$B$7 -> 3386.3 | F32: =E32-D32 -> 1.8674095 | G32: =E32/D32-1 -> 0.00055176443 | H32: Plazos de un día: no corresponde a un forward de 1 año
A33: (e) Igual que (a), Tesoro convertido a efectiva anual | B33: =B20 -> 0.1225 | C33: =(1+B25/2)^2-1 -> 0.045199523 | D33: =$B$5*(1+B33)/(1+C33) -> 3363.7105 | E33: =$B$7 -> 3386.3 | F33: =E33-D33 -> 22.589532 | G33: =E33/D33-1 -> 0.0067156589 | H33: Efecto de la convención de capitalización
A35: Tasa en pesos implícita en el forward observado (con Tesoro 1 año) | B35: =$B$7/$B$5*(1+B25)-1 -> 0.12949826
A36: Diferencia frente a la tasa de política (pb) | B36: =(B35-B20)*10000 -> 69.982583

Sheet B.2 Escenarios
A1: B.2 Escenarios de protección y costo de oportunidad
A2: Parte 1 (fórmulas): para cada escenario de la hoja «Trayectorias B» se compara el forward pactado con la TRM al vencimiento. Parte 2 (valores de la simulación de 20.000 caminos): proporciones bajo innovaciones normales y t de Student.
A4: Escenario | B4: Forward | C4: Año | D4: TRM al pactar | E4: Forward pactado | F4: TRM al vencimiento | G4: Spot − forward (COP/USD) | H4: Resultado del forward | I4: Liquidación NDF (COP) | J4: Costo del año sin cobertura (COP) | K4: Costo combinado: 75 % cubierto + 25 % abierto (COP) | L4: Presupuesto al forward (COP) | M4: Desviación vs presupuesto sin cobertura | N4: Desviación vs presupuesto con cobertura | O4: Precio efectivo por USD con cobertura
A5: Favorable – Normal | B5: 1 | C5: 7 | D5: =INDEX('Trayectorias B'!$C$5:$I$45,'B Supuestos'!$C$20+1,1) -> 3826.6551 | E5: =D5*(1+'B Supuestos'!$B$12) -> 4137.2646 | F5: =INDEX('Trayectorias B'!$C$5:$I$45,'B Supuestos'!$D$20+1,1) -> 3005.8223 | G5: =F5-E5 -> -1131.4422 | H5: =IF(G5>0,"Protección","Costo de oportunidad") -> Costo de oportunidad | I5: ='B Supuestos'!$F$20*G5 -> -17331639 | J5: ='B Supuestos'!$B$6*SUM(INDEX('Trayectorias B'!$C$5:$I$45,'B Supuestos'!$C$20+2,1):INDEX('Trayectorias B'!$C$5:$I$45,'B Supuestos'!$D$20+1,1)) -> 72122755 | K5: =J5-I5 -> 89454394 | L5: =4*'B Supuestos'!$B$6*E5 -> 84500499 | M5: =J5/L5-1 -> -0.14648131 | N5: =K5/L5-1 -> 0.058625622 | O5: =K5/(4*'B Supuestos'!$B$6) -> 4379.8143
A6: Favorable – Normal | B6: 2 | C6: 8 | D6: =INDEX('Trayectorias B'!$C$5:$I$45,'B Supuestos'!$C$21+1,1) -> 3005.8223 | E6: =D6*(1+'B Supuestos'!$B$12) -> 3249.8048 | F6: =INDEX('Trayectorias B'!$C$5:$I$45,'B Supuestos'!$D$21+1,1) -> 3041.5009 | G6: =F6-E6 -> -208.30393 | H6: =IF(G6>0,"Protección","Costo de oportunidad") -> Costo de oportunidad | I6: ='B Supuestos'!$F$21*G6 -> -3190837.6 | J6: ='B Supuestos'!$B$6*SUM(INDEX('Trayectorias B'!$C$5:$I$45,'B Supuestos'!$C$21+2,1):INDEX('Trayectorias B'!$C$5:$I$45,'B Supuestos'!$D$21+1,1)) -> 62865873 | K6: =J6-I6 -> 66056711 | L6: =4*'B Supuestos'!$B$6*E6 -> 66374806 | M6: =J6/L6-1 -> -0.052865425 | N6: =K6/L6-1 -> -0.0047924011 | O6: =K6/(4*'B Supuestos'!$B$6) -> 3234.2305
A7: Favorable – Normal | B7: 3 | C7: 9 | D7: =INDEX('Trayectorias B'!$C$5:$I$45,'B Supuestos'!$C$22+1,1) -> 3041.5009 | E7: =D7*(1+'B Supuestos'!$B$12) -> 3288.3794 | F7: =INDEX('Trayectorias B'!$C$5:$I$45,'B Supuestos'!$D$22+1,1) -> 3249.0582 | G7: =F7-E7 -> -39.321225 | H7: =IF(G7>0,"Protección","Costo de oportunidad") -> Costo de oportunidad | I7: ='B Supuestos'!$F$22*G7 -> -602329.71 | J7: ='B Supuestos'!$B$6*SUM(INDEX('Trayectorias B'!$C$5:$I$45,'B Supuestos'!$C$22+2,1):INDEX('Trayectorias B'!$C$5:$I$45,'B Supuestos'!$D$22+1,1)) -> 66938316 | K7: =J7-I7 -> 67540646 | L7: =4*'B Supuestos'!$B$6*E7 -> 67162662 | M7: =J7/L7-1 -> -0.003340339 | N7: =K7/L7-1 -> 0.0056278836 | O7: =K7/(4*'B Supuestos'!$B$6) -> 3306.886
A8: Favorable – Normal | B8: 4 | C8: 10 | D8: =INDEX('Trayectorias B'!$C$5:$I$45,'B Supuestos'!$C$23+1,1) -> 3249.0582 | E8: =D8*(1+'B Supuestos'!$B$12) -> 3512.7841 | F8: =INDEX('Trayectorias B'!$C$5:$I$45,'B Supuestos'!$D$23+1,1) -> 2915.2257 | G8: =F8-E8 -> -597.55843 | H8: =IF(G8>0,"Protección","Costo de oportunidad") -> Costo de oportunidad | I8: ='B Supuestos'!$F$23*G8 -> -9153509.2 | J8: ='B Supuestos'!$B$6*SUM(INDEX('Trayectorias B'!$C$5:$I$45,'B Supuestos'!$C$23+2,1):INDEX('Trayectorias B'!$C$5:$I$45,'B Supuestos'!$D$23+1,1)) -> 63576219 | K8: =J8-I8 -> 72729728 | L8: =4*'B Supuestos'!$B$6*E8 -> 71745959 | M8: =J8/L8-1 -> -0.11387039 | N8: =K8/L8-1 -> 0.013711839 | O8: =K8/(4*'B Supuestos'!$B$6) -> 3560.9508
A9: Central – Normal | B9: 1 | C9: 7 | D9: =INDEX('Trayectorias B'!$C$5:$I$45,'B Supuestos'!$C$20+1,2) -> 3695.2578 | E9: =D9*(1+'B Supuestos'!$B$12) -> 3995.2017 | F9: =INDEX('Trayectorias B'!$C$5:$I$45,'B Supuestos'!$D$20+1,2) -> 3721.6324 | G9: =F9-E9 -> -273.56932 | H9: =IF(G9>0,"Protección","Costo de oportunidad") -> Costo de oportunidad | I9: ='B Supuestos'!$F$20*G9 -> -4190584.9 | J9: ='B Supuestos'!$B$6*SUM(INDEX('Trayectorias B'!$C$5:$I$45,'B Supuestos'!$C$20+2,2):INDEX('Trayectorias B'!$C$5:$I$45,'B Supuestos'!$D$20+1,2)) -> 73789513 | K9: =J9-I9 -> 77980098 | L9: =4*'B Supuestos'!$B$6*E9 -> 81598973 | M9: =J9/L9-1 -> -0.095705369 | N9: =K9/L9-1 -> -0.044349515 | O9: =K9/(4*'B Supuestos'!$B$6) -> 3818.0164
A10: Central – Normal | B10: 2 | C10: 8 | D10: =INDEX('Trayectorias B'!$C$5:$I$45,'B Supuestos'!$C$21+1,2) -> 3721.6324 | E10: =D10*(1+'B Supuestos'!$B$12) -> 4023.7171 | F10: =INDEX('Trayectorias B'!$C$5:$I$45,'B Supuestos'!$D$21+1,2) -> 3336.8079 | G10: =F10-E10 -> -686.90924 | H10: =IF(G10>0,"Protección","Costo de oportunidad") -> Costo de oportunidad | I10: ='B Supuestos'!$F$21*G10 -> -10522201 | J10: ='B Supuestos'!$B$6*SUM(INDEX('Trayectorias B'!$C$5:$I$45,'B Supuestos'!$C$21+2,2):INDEX('Trayectorias B'!$C$5:$I$45,'B Supuestos'!$D$21+1,2)) -> 74197868 | K10: =J10-I10 -> 84720070 | L10: =4*'B Supuestos'!$B$6*E10 -> 82181379 | M10: =J10/L10-1 -> -0.097145005 | N10: =K10/L10-1 -> 0.030891314 | O10: =K10/(4*'B Supuestos'!$B$6) -> 4148.015
A11: Central – Normal | B11: 3 | C11: 9 | D11: =INDEX('Trayectorias B'!$C$5:$I$45,'B Supuestos'!$C$22+1,2) -> 3336.8079 | E11: =D11*(1+'B Supuestos'!$B$12) -> 3607.6564 | F11: =INDEX('Trayectorias B'!$C$5:$I$45,'B Supuestos'!$D$22+1,2) -> 3548.8586 | G11: =F11-E11 -> -58.797842 | H11: =IF(G11>0,"Protección","Costo de oportunidad") -> Costo de oportunidad | I11: ='B Supuestos'!$F$22*G11 -> -900676.09 | J11: ='B Supuestos'!$B$6*SUM(INDEX('Trayectorias B'!$C$5:$I$45,'B Supuestos'!$C$22+2,2):INDEX('Trayectorias B'!$C$5:$I$45,'B Supuestos'!$D$22+1,2)) -> 68742292 | K11: =J11-I11 -> 69642968 | L11: =4*'B Supuestos'!$B$6*E11 -> 73683654 | M11: =J11/L11-1 -> -0.06706185 | N11: =K11/L11-1 -> -0.054838296 | O11: =K11/(4*'B Supuestos'!$B$6) -> 3409.8187
A12: Central – Normal | B12: 4 | C12: 10 | D12: =INDEX('Trayectorias B'!$C$5:$I$45,'B Supuestos'!$C$23+1,2) -> 3548.8586 | E12: =D12*(1+'B Supuestos'!$B$12) -> 3836.9193 | F12: =INDEX('Trayectorias B'!$C$5:$I$45,'B Supuestos'!$D$23+1,2) -> 3994.0644 | G12: =F12-E12 -> 157.14514 | H12: =IF(G12>0,"Protección","Costo de oportunidad") -> Protección | I12: ='B Supuestos'!$F$23*G12 -> 2407177.9 | J12: ='B Supuestos'!$B$6*SUM(INDEX('Trayectorias B'!$C$5:$I$45,'B Supuestos'!$C$23+2,2):INDEX('Trayectorias B'!$C$5:$I$45,'B Supuestos'!$D$23+1,2)) -> 78835204 | K12: =J12-I12 -> 76428026 | L12: =4*'B Supuestos'!$B$6*E12 -> 78366175 | M12: =J12/L12-1 -> 0.0059850963 | N12: =K12/L12-1 -> -0.024731956 | O12: =K12/(4*'B Supuestos'!$B$6) -> 3742.0248
A13: Adverso – Normal | B13: 1 | C13: 7 | D13: =INDEX('Trayectorias B'!$C$5:$I$45,'B Supuestos'!$C$20+1,3) -> 3823.1388 | E13: =D13*(1+'B Supuestos'!$B$12) -> 4133.4629 | F13: =INDEX('Trayectorias B'!$C$5:$I$45,'B Supuestos'!$D$20+1,3) -> 4709.8614 | G13: =F13-E13 -> 576.39853 | H13: =IF(G13>0,"Protección","Costo de oportunidad") -> Protección | I13: ='B Supuestos'!$F$20*G13 -> 8829378 | J13: ='B Supuestos'!$B$6*SUM(INDEX('Trayectorias B'!$C$5:$I$45,'B Supuestos'!$C$20+2,3):INDEX('Trayectorias B'!$C$5:$I$45,'B Supuestos'!$D$20+1,3)) -> 87962724 | K13: =J13-I13 -> 79133346 | L13: =4*'B Supuestos'!$B$6*E13 -> 84422853 | M13: =J13/L13-1 -> 0.041930245 | N13: =K13/L13-1 -> -0.06265492 | O13: =K13/(4*'B Supuestos'!$B$6) -> 3874.4811
A14: Adverso – Normal | B14: 2 | C14: 8 | D14: =INDEX('Trayectorias B'!$C$5:$I$45,'B Supuestos'!$C$21+1,3) -> 4709.8614 | E14: =D14*(1+'B Supuestos'!$B$12) -> 5092.1607 | F14: =INDEX('Trayectorias B'!$C$5:$I$45,'B Supuestos'!$D$21+1,3) -> 5059.3468 | G14: =F14-E14 -> -32.813908 | H14: =IF(G14>0,"Protección","Costo de oportunidad") -> Costo de oportunidad | I14: ='B Supuestos'!$F$21*G14 -> -502649.44 | J14: ='B Supuestos'!$B$6*SUM(INDEX('Trayectorias B'!$C$5:$I$45,'B Supuestos'!$C$21+2,3):INDEX('Trayectorias B'!$C$5:$I$45,'B Supuestos'!$D$21+1,3)) -> 96891375 | K14: =J14-I14 -> 97394025 | L14: =4*'B Supuestos'!$B$6*E14 -> 1.0400353e+08 | M14: =J14/L14-1 -> -0.068383783 | N14: =K14/L14-1 -> -0.063550779 | O14: =K14/(4*'B Supuestos'!$B$6) -> 4768.5499
A15: Adverso – Normal | B15: 3 | C15: 9 | D15: =INDEX('Trayectorias B'!$C$5:$I$45,'B Supuestos'!$C$22+1,3) -> 5059.3468 | E15: =D15*(1+'B Supuestos'!$B$12) -> 5470.0137 | F15: =INDEX('Trayectorias B'!$C$5:$I$45,'B Supuestos'!$D$22+1,3) -> 5425.4503 | G15: =F15-E15 -> -44.56346 | H15: =IF(G15>0,"Protección","Costo de oportunidad") -> Costo de oportunidad | I15: ='B Supuestos'!$F$22*G15 -> -682631.23 | J15: ='B Supuestos'!$B$6*SUM(INDEX('Trayectorias B'!$C$5:$I$45,'B Supuestos'!$C$22+2,3):INDEX('Trayectorias B'!$C$5:$I$45,'B Supuestos'!$D$22+1,3)) -> 1.0206275e+08 | K15: =J15-I15 -> 1.0274538e+08 | L15: =4*'B Supuestos'!$B$6*E15 -> 1.1172089e+08 | M15: =J15/L15-1 -> -0.086448899 | N15: =K15/L15-1 -> -0.080338751 | O15: =K15/(4*'B Supuestos'!$B$6) -> 5030.5597
A16: Adverso – Normal | B16: 4 | C16: 10 | D16: =INDEX('Trayectorias B'!$C$5:$I$45,'B Supuestos'!$C$23+1,3) -> 5425.4503 | E16: =D16*(1+'B Supuestos'!$B$12) -> 5865.8339 | F16: =INDEX('Trayectorias B'!$C$5:$I$45,'B Supuestos'!$D$23+1,3) -> 5759.8568 | G16: =F16-E16 -> -105.97703 | H16: =IF(G16>0,"Protección","Costo de oportunidad") -> Costo de oportunidad | I16: ='B Supuestos'!$F$23*G16 -> -1623375.6 | J16: ='B Supuestos'!$B$6*SUM(INDEX('Trayectorias B'!$C$5:$I$45,'B Supuestos'!$C$23+2,3):INDEX('Trayectorias B'!$C$5:$I$45,'B Supuestos'!$D$23+1,3)) -> 1.1484962e+08 | K16: =J16-I16 -> 1.16473e+08 | L16: =4*'B Supuestos'!$B$6*E16 -> 1.1980522e+08 | M16: =J16/L16-1 -> -0.041363771 | N16: =K16/L16-1 -> -0.027813647 | O16: =K16/(4*'B Supuestos'!$B$6) -> 5702.6836
A17: Favorable – t | B17: 1 | C17: 7 | D17: =INDEX('Trayectorias B'!$C$5:$I$45,'B Supuestos'!$C$20+1,4) -> 3590.8697 | E17: =D17*(1+'B Supuestos'!$B$12) -> 3882.3404 | F17: =INDEX('Trayectorias B'!$C$5:$I$45,'B Supuestos'!$D$20+1,4) -> 3219.7964 | G17: =F17-E17 -> -662.54404 | H17: =IF(G17>0,"Protección","Costo de oportunidad") -> Costo de oportunidad | I17: ='B Supuestos'!$F$20*G17 -> -10148971 | J17: ='B Supuestos'!$B$6*SUM(INDEX('Trayectorias B'!$C$5:$I$45,'B Supuestos'!$C$20+2,4):INDEX('Trayectorias B'!$C$5:$I$45,'B Supuestos'!$D$20+1,4)) -> 70125882 | K17: =J17-I17 -> 80274853 | L17: =4*'B Supuestos'!$B$6*E17 -> 79293866 | M17: =J17/L17-1 -> -0.11562035 | N17: =K17/L17-1 -> 0.012371527 | O17: =K17/(4*'B Supuestos'!$B$6) -> 3930.3709
A18: Favorable – t | B18: 2 | C18: 8 | D18: =INDEX('Trayectorias B'!$C$5:$I$45,'B Supuestos'!$C$21+1,4) -> 3219.7964 | E18: =D18*(1+'B Supuestos'!$B$12) -> 3481.1471 | F18: =INDEX('Trayectorias B'!$C$5:$I$45,'B Supuestos'!$D$21+1,4) -> 2966.9503 | G18: =F18-E18 -> -514.19684 | H18: =IF(G18>0,"Protección","Costo de oportunidad") -> Costo de oportunidad | I18: ='B Supuestos'!$F$21*G18 -> -7876561.2 | J18: ='B Supuestos'!$B$6*SUM(INDEX('Trayectorias B'!$C$5:$I$45,'B Supuestos'!$C$21+2,4):INDEX('Trayectorias B'!$C$5:$I$45,'B Supuestos'!$D$21+1,4)) -> 64081734 | K18: =J18-I18 -> 71958295 | L18: =4*'B Supuestos'!$B$6*E18 -> 71099797 | M18: =J18/L18-1 -> -0.098707217 | N18: =K18/L18-1 -> 0.012074551 | O18: =K18/(4*'B Supuestos'!$B$6) -> 3523.1804
A19: Favorable – t | B19: 3 | C19: 9 | D19: =INDEX('Trayectorias B'!$C$5:$I$45,'B Supuestos'!$C$22+1,4) -> 2966.9503 | E19: =D19*(1+'B Supuestos'!$B$12) -> 3207.7775 | F19: =INDEX('Trayectorias B'!$C$5:$I$45,'B Supuestos'!$D$22+1,4) -> 3286.7372 | G19: =F19-E19 -> 78.959728 | H19: =IF(G19>0,"Protección","Costo de oportunidad") -> Protección | I19: ='B Supuestos'!$F$22*G19 -> 1209519.5 | J19: ='B Supuestos'!$B$6*SUM(INDEX('Trayectorias B'!$C$5:$I$45,'B Supuestos'!$C$22+2,4):INDEX('Trayectorias B'!$C$5:$I$45,'B Supuestos'!$D$22+1,4)) -> 65036998 | K19: =J19-I19 -> 63827479 | L19: =4*'B Supuestos'!$B$6*E19 -> 65516429 | M19: =J19/L19-1 -> -0.0073177267 | N19: =K19/L19-1 -> -0.025779043 | O19: =K19/(4*'B Supuestos'!$B$6) -> 3125.0841
A20: Favorable – t | B20: 4 | C20: 10 | D20: =INDEX('Trayectorias B'!$C$5:$I$45,'B Supuestos'!$C$23+1,4) -> 3286.7372 | E20: =D20*(1+'B Supuestos'!$B$12) -> 3553.5216 | F20: =INDEX('Trayectorias B'!$C$5:$I$45,'B Supuestos'!$D$23+1,4) -> 2741.3926 | G20: =F20-E20 -> -812.12893 | H20: =IF(G20>0,"Protección","Costo de oportunidad") -> Costo de oportunidad | I20: ='B Supuestos'!$F$23*G20 -> -12440339 | J20: ='B Supuestos'!$B$6*SUM(INDEX('Trayectorias B'!$C$5:$I$45,'B Supuestos'!$C$23+2,4):INDEX('Trayectorias B'!$C$5:$I$45,'B Supuestos'!$D$23+1,4)) -> 62925711 | K20: =J20-I20 -> 75366050 | L20: =4*'B Supuestos'!$B$6*E20 -> 72577990 | M20: =J20/L20-1 -> -0.13299183 | N20: =K20/L20-1 -> 0.038414673 | O20: =K20/(4*'B Supuestos'!$B$6) -> 3690.0289
A21: Central – t | B21: 1 | C21: 7 | D21: =INDEX('Trayectorias B'!$C$5:$I$45,'B Supuestos'!$C$20+1,5) -> 3784.6602 | E21: =D21*(1+'B Supuestos'!$B$12) -> 4091.8609 | F21: =INDEX('Trayectorias B'!$C$5:$I$45,'B Supuestos'!$D$20+1,5) -> 4345.86 | G21: =F21-E21 -> 253.99909 | H21: =IF(G21>0,"Protección","Costo de oportunidad") -> Protección | I21: ='B Supuestos'!$F$20*G21 -> 3890804.5 | J21: ='B Supuestos'!$B$6*SUM(INDEX('Trayectorias B'!$C$5:$I$45,'B Supuestos'!$C$20+2,5):INDEX('Trayectorias B'!$C$5:$I$45,'B Supuestos'!$D$20+1,5)) -> 85292505 | K21: =J21-I21 -> 81401701 | L21: =4*'B Supuestos'!$B$6*E21 -> 83573164 | M21: =J21/L21-1 -> 0.020572893 | N21: =K21/L21-1 -> -0.025982775 | O21: =K21/(4*'B Supuestos'!$B$6) -> 3985.543
A22: Central – t | B22: 2 | C22: 8 | D22: =INDEX('Trayectorias B'!$C$5:$I$45,'B Supuestos'!$C$21+1,5) -> 4345.86 | E22: =D22*(1+'B Supuestos'!$B$12) -> 4698.6132 | F22: =INDEX('Trayectorias B'!$C$5:$I$45,'B Supuestos'!$D$21+1,5) -> 4535.5778 | G22: =F22-E22 -> -163.0355 | H22: =IF(G22>0,"Protección","Costo de oportunidad") -> Costo de oportunidad | I22: ='B Supuestos'!$F$21*G22 -> -2497407.5 | J22: ='B Supuestos'!$B$6*SUM(INDEX('Trayectorias B'!$C$5:$I$45,'B Supuestos'!$C$21+2,5):INDEX('Trayectorias B'!$C$5:$I$45,'B Supuestos'!$D$21+1,5)) -> 94635838 | K22: =J22-I22 -> 97133246 | L22: =4*'B Supuestos'!$B$6*E22 -> 95965622 | M22: =J22/L22-1 -> -0.013856873 | N22: =K22/L22-1 -> 0.012167108 | O22: =K22/(4*'B Supuestos'!$B$6) -> 4755.7818
A23: Central – t | B23: 3 | C23: 9 | D23: =INDEX('Trayectorias B'!$C$5:$I$45,'B Supuestos'!$C$22+1,5) -> 4535.5778 | E23: =D23*(1+'B Supuestos'!$B$12) -> 4903.7304 | F23: =INDEX('Trayectorias B'!$C$5:$I$45,'B Supuestos'!$D$22+1,5) -> 4959.0442 | G23: =F23-E23 -> 55.313744 | H23: =IF(G23>0,"Protección","Costo de oportunidad") -> Protección | I23: ='B Supuestos'!$F$22*G23 -> 847306.03 | J23: ='B Supuestos'!$B$6*SUM(INDEX('Trayectorias B'!$C$5:$I$45,'B Supuestos'!$C$22+2,5):INDEX('Trayectorias B'!$C$5:$I$45,'B Supuestos'!$D$22+1,5)) -> 96674367 | K23: =J23-I23 -> 95827061 | L23: =4*'B Supuestos'!$B$6*E23 -> 1.0015499e+08 | M23: =J23/L23-1 -> -0.034752322 | N23: =K23/L23-1 -> -0.043212271 | O23: =K23/(4*'B Supuestos'!$B$6) -> 4691.8291
A24: Central – t | B24: 4 | C24: 10 | D24: =INDEX('Trayectorias B'!$C$5:$I$45,'B Supuestos'!$C$23+1,5) -> 4959.0442 | E24: =D24*(1+'B Supuestos'!$B$12) -> 5361.5696 | F24: =INDEX('Trayectorias B'!$C$5:$I$45,'B Supuestos'!$D$23+1,5) -> 4141.8056 | G24: =F24-E24 -> -1219.764 | H24: =IF(G24>0,"Protección","Costo de oportunidad") -> Costo de oportunidad | I24: ='B Supuestos'!$F$23*G24 -> -18684567 | J24: ='B Supuestos'!$B$6*SUM(INDEX('Trayectorias B'!$C$5:$I$45,'B Supuestos'!$C$23+2,5):INDEX('Trayectorias B'!$C$5:$I$45,'B Supuestos'!$D$23+1,5)) -> 84988567 | K24: =J24-I24 -> 1.0367313e+08 | L24: =4*'B Supuestos'!$B$6*E24 -> 1.09506e+08 | M24: =J24/L24-1 -> -0.22389125 | N24: =K24/L24-1 -> -0.053265292 | O24: =K24/(4*'B Supuestos'!$B$6) -> 5075.984
A25: Adverso – t | B25: 1 | C25: 7 | D25: =INDEX('Trayectorias B'!$C$5:$I$45,'B Supuestos'!$C$20+1,6) -> 3691.5684 | E25: =D25*(1+'B Supuestos'!$B$12) -> 3991.2129 | F25: =INDEX('Trayectorias B'!$C$5:$I$45,'B Supuestos'!$D$20+1,6) -> 3954.1369 | G25: =F25-E25 -> -37.076001 | H25: =IF(G25>0,"Protección","Costo de oportunidad") -> Costo de oportunidad | I25: ='B Supuestos'!$F$20*G25 -> -567936.96 | J25: ='B Supuestos'!$B$6*SUM(INDEX('Trayectorias B'!$C$5:$I$45,'B Supuestos'!$C$20+2,6):INDEX('Trayectorias B'!$C$5:$I$45,'B Supuestos'!$D$20+1,6)) -> 79033633 | K25: =J25-I25 -> 79601570 | L25: =4*'B Supuestos'!$B$6*E25 -> 81517504 | M25: =J25/L25-1 -> -0.030470401 | N25: =K25/L25-1 -> -0.023503345 | O25: =K25/(4*'B Supuestos'!$B$6) -> 3897.406
A26: Adverso – t | B26: 2 | C26: 8 | D26: =INDEX('Trayectorias B'!$C$5:$I$45,'B Supuestos'!$C$21+1,6) -> 3954.1369 | E26: =D26*(1+'B Supuestos'!$B$12) -> 4275.094 | F26: =INDEX('Trayectorias B'!$C$5:$I$45,'B Supuestos'!$D$21+1,6) -> 5356.5356 | G26: =F26-E26 -> 1081.4416 | H26: =IF(G26>0,"Protección","Costo de oportunidad") -> Protección | I26: ='B Supuestos'!$F$21*G26 -> 16565721 | J26: ='B Supuestos'!$B$6*SUM(INDEX('Trayectorias B'!$C$5:$I$45,'B Supuestos'!$C$21+2,6):INDEX('Trayectorias B'!$C$5:$I$45,'B Supuestos'!$D$21+1,6)) -> 1.0110693e+08 | K26: =J26-I26 -> 84541210 | L26: =4*'B Supuestos'!$B$6*E26 -> 87315561 | M26: =J26/L26-1 -> 0.15794859 | N26: =K26/L26-1 -> -0.031773843 | O26: =K26/(4*'B Supuestos'!$B$6) -> 4139.2578
A27: Adverso – t | B27: 3 | C27: 9 | D27: =INDEX('Trayectorias B'!$C$5:$I$45,'B Supuestos'!$C$22+1,6) -> 5356.5356 | E27: =D27*(1+'B Supuestos'!$B$12) -> 5791.3254 | F27: =INDEX('Trayectorias B'!$C$5:$I$45,'B Supuestos'!$D$22+1,6) -> 5423.644 | G27: =F27-E27 -> -367.68144 | H27: =IF(G27>0,"Protección","Costo de oportunidad") -> Costo de oportunidad | I27: ='B Supuestos'!$F$22*G27 -> -5632211.4 | J27: ='B Supuestos'!$B$6*SUM(INDEX('Trayectorias B'!$C$5:$I$45,'B Supuestos'!$C$22+2,6):INDEX('Trayectorias B'!$C$5:$I$45,'B Supuestos'!$D$22+1,6)) -> 1.0230832e+08 | K27: =J27-I27 -> 1.0794053e+08 | L27: =4*'B Supuestos'!$B$6*E27 -> 1.1828344e+08 | M27: =J27/L27-1 -> -0.13505797 | N27: =K27/L27-1 -> -0.087441739 | O27: =K27/(4*'B Supuestos'!$B$6) -> 5284.9218
A28: Adverso – t | B28: 4 | C28: 10 | D28: =INDEX('Trayectorias B'!$C$5:$I$45,'B Supuestos'!$C$23+1,6) -> 5423.644 | E28: =D28*(1+'B Supuestos'!$B$12) -> 5863.881 | F28: =INDEX('Trayectorias B'!$C$5:$I$45,'B Supuestos'!$D$23+1,6) -> 5659.3115 | G28: =F28-E28 -> -204.56949 | H28: =IF(G28>0,"Protección","Costo de oportunidad") -> Costo de oportunidad | I28: ='B Supuestos'!$F$23*G28 -> -3133632.9 | J28: ='B Supuestos'!$B$6*SUM(INDEX('Trayectorias B'!$C$5:$I$45,'B Supuestos'!$C$23+2,6):INDEX('Trayectorias B'!$C$5:$I$45,'B Supuestos'!$D$23+1,6)) -> 1.1988166e+08 | K28: =J28-I28 -> 1.2301529e+08 | L28: =4*'B Supuestos'!$B$6*E28 -> 1.1976533e+08 | M28: =J28/L28-1 -> 0.00097125471 | N28: =K28/L28-1 -> 0.027136029 | O28: =K28/(4*'B Supuestos'!$B$6) -> 6023.0034
A29: Base A.1 (mediana) | B29: 1 | C29: 7 | D29: =INDEX('Trayectorias B'!$C$5:$I$45,'B Supuestos'!$C$20+1,7) -> 3708.3529 | E29: =D29*(1+'B Supuestos'!$B$12) -> 4009.3598 | F29: =INDEX('Trayectorias B'!$C$5:$I$45,'B Supuestos'!$D$20+1,7) -> 3779.3936 | G29: =F29-E29 -> -229.96613 | H29: =IF(G29>0,"Protección","Costo de oportunidad") -> Costo de oportunidad | I29: ='B Supuestos'!$F$20*G29 -> -3522663.2 | J29: ='B Supuestos'!$B$6*SUM(INDEX('Trayectorias B'!$C$5:$I$45,'B Supuestos'!$C$20+2,7):INDEX('Trayectorias B'!$C$5:$I$45,'B Supuestos'!$D$20+1,7)) -> 76644998 | K29: =J29-I29 -> 80167661 | L29: =4*'B Supuestos'!$B$6*E29 -> 81888141 | M29: =J29/L29-1 -> -0.064028108 | N29: =K29/L29-1 -> -0.021010118 | O29: =K29/(4*'B Supuestos'!$B$6) -> 3925.1226
A30: Base A.1 (mediana) | B30: 2 | C30: 8 | D30: =INDEX('Trayectorias B'!$C$5:$I$45,'B Supuestos'!$C$21+1,7) -> 3779.3936 | E30: =D30*(1+'B Supuestos'!$B$12) -> 4086.1669 | F30: =INDEX('Trayectorias B'!$C$5:$I$45,'B Supuestos'!$D$21+1,7) -> 3851.7953 | G30: =F30-E30 -> -234.37158 | H30: =IF(G30>0,"Protección","Costo de oportunidad") -> Costo de oportunidad | I30: ='B Supuestos'!$F$21*G30 -> -3590146.7 | J30: ='B Supuestos'!$B$6*SUM(INDEX('Trayectorias B'!$C$5:$I$45,'B Supuestos'!$C$21+2,7):INDEX('Trayectorias B'!$C$5:$I$45,'B Supuestos'!$D$21+1,7)) -> 78113282 | K30: =J30-I30 -> 81703429 | L30: =4*'B Supuestos'!$B$6*E30 -> 83456868 | M30: =J30/L30-1 -> -0.064028108 | N30: =K30/L30-1 -> -0.021010118 | O30: =K30/(4*'B Supuestos'!$B$6) -> 4000.316
A31: Base A.1 (mediana) | B31: 3 | C31: 9 | D31: =INDEX('Trayectorias B'!$C$5:$I$45,'B Supuestos'!$C$22+1,7) -> 3851.7953 | E31: =D31*(1+'B Supuestos'!$B$12) -> 4164.4454 | F31: =INDEX('Trayectorias B'!$C$5:$I$45,'B Supuestos'!$D$22+1,7) -> 3925.5839 | G31: =F31-E31 -> -238.86142 | H31: =IF(G31>0,"Protección","Costo de oportunidad") -> Costo de oportunidad | I31: ='B Supuestos'!$F$22*G31 -> -3658922.9 | J31: ='B Supuestos'!$B$6*SUM(INDEX('Trayectorias B'!$C$5:$I$45,'B Supuestos'!$C$22+2,7):INDEX('Trayectorias B'!$C$5:$I$45,'B Supuestos'!$D$22+1,7)) -> 79609695 | K31: =J31-I31 -> 83268617 | L31: =4*'B Supuestos'!$B$6*E31 -> 85055647 | M31: =J31/L31-1 -> -0.064028108 | N31: =K31/L31-1 -> -0.021010118 | O31: =K31/(4*'B Supuestos'!$B$6) -> 4076.9499
A32: Base A.1 (mediana) | B32: 4 | C32: 10 | D32: =INDEX('Trayectorias B'!$C$5:$I$45,'B Supuestos'!$C$23+1,7) -> 3925.5839 | E32: =D32*(1+'B Supuestos'!$B$12) -> 4244.2234 | F32: =INDEX('Trayectorias B'!$C$5:$I$45,'B Supuestos'!$D$23+1,7) -> 4000.7861 | G32: =F32-E32 -> -243.43728 | H32: =IF(G32>0,"Protección","Costo de oportunidad") -> Costo de oportunidad | I32: ='B Supuestos'!$F$23*G32 -> -3729016.7 | J32: ='B Supuestos'!$B$6*SUM(INDEX('Trayectorias B'!$C$5:$I$45,'B Supuestos'!$C$23+2,7):INDEX('Trayectorias B'!$C$5:$I$45,'B Supuestos'!$D$23+1,7)) -> 81134773 | K32: =J32-I32 -> 84863790 | L32: =4*'B Supuestos'!$B$6*E32 -> 86685053 | M32: =J32/L32-1 -> -0.064028108 | N32: =K32/L32-1 -> -0.021010118 | O32: =K32/(4*'B Supuestos'!$B$6) -> 4155.0518
A35: Parte 2. Resultados de la simulación (20.000 caminos por distribución; los cuatro forwards agrupados)
A36: Indicador | B36: Normal | C36: t de Student (ν = 8,9, estimado) | D36: t de Student de estrés (ν = 4) | E36: Lectura
A37: Proporción con protección (spot al vencimiento > forward) | B37: 0.3252625 | C37: 0.32445 | D37: 0.3065375 | E37: El forward se liquida a favor: sin él, la empresa habría pagado más.
A38: Proporción con costo de oportunidad (spot < forward) | B38: 0.6747375 | C38: 0.67555 | D38: 0.6934625 | E38: El forward se liquida en contra: sin él, la empresa habría pagado menos.
A39: Proporción con pérdida cambiaria extrema (depreciación anual > 20 %) | B39: 0.1057125 | C39: 0.1036 | D39: 0.0915125 | E39: Años con choques como los de 2015 o 2022 (≈ 11 % de los años desde 1999).
A40: Proporción con depreciación anual > 30 % | B40: 0.0304625 | C40: 0.0332875 | D40: 0.0314625 | E40: Cola más extrema: aquí la t de Student pesa más que la normal.
A41: Proporción con apreciación anual > 20 % (costo de oportunidad extremo) | B41: 0.032475 | C41: 0.0324875 | D41: 0.0309625 | E41: Años en los que el forward cuesta mucho frente al spot.
A42: En años extremos: sobrecosto sin cobertura vs spot del pacto | B42: 0.17094047 | C42: 0.17578223 | D42: 0.1843285 | E42: Cuánto más cuestan las cuotas del año frente a la TRM del día del pacto.
A43: En años extremos: sobrecosto con cobertura vs spot del pacto | B43: 0.022500885 | C43: 0.022551756 | D43: 0.019169458 | E43: Con el 75 % cubierto, el sobrecosto se reduce a una fracción.
A44: En años extremos: pérdida sin cobertura vs spot del pacto (COP) | B44: 14164857 | C44: 14550271 | D44: 15325619 | E44: Pérdida cambiaria media en esos años.
A45: En años extremos: pérdida con cobertura vs spot del pacto (COP) | B45: 1849358.6 | C45: 1872242 | D45: 1629375.9 | E45: Pérdida que queda con la cobertura.
A46: Pérdida del derivado (liquidación negativa) | B46: 0.6747375 | C46: 0.67555 | D46: 0.6934625 | E46: «Pérdida del derivado»: el NDF termina en contra.
A47: Pérdida del derivado y cobertura exitosa | B47: 0.6741 | C47: 0.6745 | D47: 0.6908875 | E47: El derivado pierde, pero el costo del año queda dentro del presupuesto: la cobertura cumplió su función.
A48: Ganancia del derivado y cobertura exitosa | B48: 0.325175 | C48: 0.324175 | D48: 0.3055875 | E48: El derivado gana y el costo queda dentro del presupuesto.
... A50: Sin cobertura: costo > presupuesto + 10 % | B50: 0.0381 | C50: 0.0396625 | D50: 0.0365875 | E50: Misma prueba sin cobertura, para comparar.
A52: Resultados por forward (simulación)
A53: Distribución | B53: Forward | C53: Año | D53: Forward pactado (mediana) | E53: TRM al vencimiento (mediana) | F53: Prob. protección | G53: Prob. costo de oportunidad | H53: Prob. depreciación > 20 % | I53: Liquidación media (COP) | J53: Liquidación P5 (COP) | K53: Liquidación P95 (COP) | L53: Desv. est. costo del año sin cobertura | M53: Desv. est. costo del año con cobertura
A54: Normal | B54: 1 | C54: 7 | D54: 4021.9637 | E54: 3779.5747 | F54: 0.3191 | G54: 0.6809 | H54: 0.1053 | I54: -3231975.5 | J54: -16606378 | K54: 10751068 | L54: 26402532 | M54: 26391498
A55: Normal | B55: 2 | C55: 8 | D55: 4086.3626 | E55: 3864.1682 | F55: 0.32505 | G55: 0.67495 | H55: 0.1014 | I55: -3318259.6 | J55: -17229592 | K55: 10877207 | L55: 29417353 | M55: 29777189
A56: Normal | B56: 3 | C56: 9 | D56: 4177.8226 | E56: 3931.7844 | F56: 0.3289 | G56: 0.6711 | H56: 0.1094 | I56: -3276399.3 | J56: -17751150 | K56: 11731469 | L56: 32510767 | M56: 32874160
A57: Normal | B57: 4 | C57: 10 | D57: 4250.9271 | E57: 4017.1538 | F57: 0.328 | G57: 0.672 | H57: 0.10675 | I57: -3478463.9 | J57: -18822675 | K57: 11846723 | L57: 35528129 | M57: 36147092
A58: t (ν = 8,9) | B58: 1 | C58: 7 | D58: 4022.8459 | E58: 3799.5378 | F58: 0.3276 | G58: 0.6724 | H58: 0.10185 | I58: -3168174.2 | J58: -16644785 | K58: 10788572 | L58: 26372316 | M58: 26495145
A59: t (ν = 8,9) | B59: 2 | C59: 8 | D59: 4107.9461 | E59: 3875.9856 | F59: 0.32295 | G59: 0.67705 | H59: 0.10535 | I59: -3199210.7 | J59: -17085031 | K59: 11247280 | L59: 29500984 | M59: 29618907
A60: t (ν = 8,9) | B60: 3 | C60: 9 | D60: 4190.5992 | E60: 3940.8112 | F60: 0.3249 | G60: 0.6751 | H60: 0.1043 | I60: -3274643.8 | J60: -17950605 | K60: 11405229 | L60: 32634678 | M60: 33006068
A61: t (ν = 8,9) | B61: 4 | C61: 10 | D61: 4260.6867 | E61: 4036.3027 | F61: 0.32235 | G61: 0.67765 | H61: 0.1029 | I61: -3404450.7 | J61: -18478055 | K61: 11807870 | L61: 35770884 | M61: 36337188

Sheet B.3 Flujo consolidado
A1: B.3 Flujo consolidado del crédito con y sin cobertura
A2: Elija el escenario en la celda amarilla (lista desplegable). Todas las columnas son fórmulas: compra inicial, aporte propio, desembolso, cuotas en USD, conversión a pesos y liquidación de los cuatro NDF.
A4: Escenario | B4: Central – Normal
A5: N.º de columna del escenario | B5: =MATCH(B4,'Trayectorias B'!$C$4:$I$4,0) -> 2
A7: Trimestre | B7: Fecha | C7: Compra de la maquinaria (COP) | D7: Aporte propio (COP) | E7: Desembolso (USD) | F7: TRM | G7: Desembolso (COP) | H7: Cuota (USD) | I7: Cuota (COP) | J7: Forward que vence | K7: TRM al pactar | L7: Forward pactado | M7: Nominal (USD) | N7: Liquidación NDF (COP) | O7: Flujo neto sin cobertura (COP) | P7: Flujo neto con cobertura (COP) | Q7: Flujo del crédito sin cobertura (COP) | R7: Flujo del crédito con cobertura (COP)
A8: 0 | B8: ='Trayectorias TRM'!B5 -> 46313 | C8: =-Supuestos!$B$4 -> -400000000 | D8: =Supuestos!$B$6 -> 40000000 | E8: =Supuestos!$B$9 -> 113397.61 | F8: =INDEX('Trayectorias B'!$C$5:$I$45,1,$B$5) -> 3174.67 | G8: =E8*F8 -> 360000000 | H8: 0 | I8: =H8*F8 -> 0 | J8: =IFERROR(MATCH(A8,'B Supuestos'!$D$20:$D$23,0),"") | K8: =IF(J8="","",INDEX('Trayectorias B'!$C$5:$I$45,A8-3,$B$5)) | L8: =IF(J8="","",K8*(1+'B Supuestos'!$B$12)) | M8: =IF(J8="","",INDEX('B Supuestos'!$F$20:$F$23,J8)) | N8: =IF(J8="",0,M8*(F8-L8)) -> 0 | O8: =C8+D8+G8+I8 -> 0 | P8: =O8+N8 -> 0 | Q8: =G8+I8 -> 360000000 | R8: =Q8+N8 -> 360000000
A9: 1 | B9: ='Trayectorias TRM'!B6 -> 46405 | C9: 0 | D9: 0 | E9: 0 | F9: =INDEX('Trayectorias B'!$C$5:$I$45,2,$B$5) -> 3631.1782 | G9: =E9*F9 -> 0 | H9: =-Amortización!D5 -> -5106.0609 | I9: =H9*F9 -> -18541017 | J9: =IFERROR(MATCH(A9,'B Supuestos'!$D$20:$D$23,0),"") | K9: =IF(J9="","",INDEX('Trayectorias B'!$C$5:$I$45,A9-3,$B$5)) | L9: =IF(J9="","",K9*(1+'B Supuestos'!$B$12)) | M9: =IF(J9="","",INDEX('B Supuestos'!$F$20:$F$23,J9)) | N9: =IF(J9="",0,M9*(F9-L9)) -> 0 | O9: =C9+D9+G9+I9 -> -18541017 | P9: =O9+N9 -> -18541017 | Q9: =G9+I9 -> -18541017 | R9: =Q9+N9 -> -18541017
A10: 2 | B10: ='Trayectorias TRM'!B7 -> 46495 | C10: 0 | D10: 0 | E10: 0 | F10: =INDEX('Trayectorias B'!$C$5:$I$45,3,$B$5) -> 3900.2509 | G10: =E10*F10 -> 0 | H10: =-Amortización!D6 -> -5106.0609 | I10: =H10*F10 -> -19914919 | J10: =IFERROR(MATCH(A10,'B Supuestos'!$D$20:$D$23,0),"") | K10: =IF(J10="","",INDEX('Trayectorias B'!$C$5:$I$45,A10-3,$B$5)) | L10: =IF(J10="","",K10*(1+'B Supuestos'!$B$12)) | M10: =IF(J10="","",INDEX('B Supuestos'!$F$20:$F$23,J10)) | N10: =IF(J10="",0,M10*(F10-L10)) -> 0 | O10: =C10+D10+G10+I10 -> -19914919 | P10: =O10+N10 -> -19914919 | Q10: =G10+I10 -> -19914919 | R10: =Q10+N10 -> -19914919
A11: 3 | B11: ='Trayectorias TRM'!B8 -> 46586 | C11: 0 | D11: 0 | E11: 0 | F11: =INDEX('Trayectorias B'!$C$5:$I$45,4,$B$5) -> 3706.7001 | G11: =E11*F11 -> 0 | H11: =-Amortización!D7 -> -5106.0609 | I11: =H11*F11 -> -18926636 | J11: =IFERROR(MATCH(A11,'B Supuestos'!$D$20:$D$23,0),"") | K11: =IF(J11="","",INDEX('Trayectorias B'!$C$5:$I$45,A11-3,$B$5)) | L11: =IF(J11="","",K11*(1+'B Supuestos'!$B$12)) | M11: =IF(J11="","",INDEX('B Supuestos'!$F$20:$F$23,J11)) | N11: =IF(J11="",0,M11*(F11-L11)) -> 0 | O11: =C11+D11+G11+I11 -> -18926636 | P11: =O11+N11 -> -18926636 | Q11: =G11+I11 -> -18926636 | R11: =Q11+N11 -> -18926636
A12: 4 | B12: ='Trayectorias TRM'!B9 -> 46678 | C12: 0 | D12: 0 | E12: 0 | F12: =INDEX('Trayectorias B'!$C$5:$I$45,5,$B$5) -> 3594.9326 | G12: =E12*F12 -> 0 | H12: =-Amortización!D8 -> -5106.0609 | I12: =H12*F12 -> -18355945 | J12: =IFERROR(MATCH(A12,'B Supuestos'!$D$20:$D$23,0),"") | K12: =IF(J12="","",INDEX('Trayectorias B'!$C$5:$I$45,A12-3,$B$5)) | L12: =IF(J12="","",K12*(1+'B Supuestos'!$B$12)) | M12: =IF(J12="","",INDEX('B Supuestos'!$F$20:$F$23,J12)) | N12: =IF(J12="",0,M12*(F12-L12)) -> 0 | O12: =C12+D12+G12+I12 -> -18355945 | P12: =O12+N12 -> -18355945 | Q12: =G12+I12 -> -18355945 | R12: =Q12+N12 -> -18355945
A13: 5 | B13: ='Trayectorias TRM'!B10 -> 46770 | C13: 0 | D13: 0 | E13: 0 | F13: =INDEX('Trayectorias B'!$C$5:$I$45,6,$B$5) -> 3470.9255 | G13: =E13*F13 -> 0 | H13: =-Amortización!D9 -> -5106.0609 | I13: =H13*F13 -> -17722757 | J13: =IFERROR(MATCH(A13,'B Supuestos'!$D$20:$D$23,0),"") | K13: =IF(J13="","",INDEX('Trayectorias B'!$C$5:$I$45,A13-3,$B$5)) | L13: =IF(J13="","",K13*(1+'B Supuestos'!$B$12)) | M13: =IF(J13="","",INDEX('B Supuestos'!$F$20:$F$23,J13)) | N13: =IF(J13="",0,M13*(F13-L13)) -> 0 | O13: =C13+D13+G13+I13 -> -17722757 | P13: =O13+N13 -> -17722757 | Q13: =G13+I13 -> -17722757 | R13: =Q13+N13 -> -17722757
A14: 6 | B14: ='Trayectorias TRM'!B11 -> 46861 | C14: 0 | D14: 0 | E14: 0 | F14: =INDEX('Trayectorias B'!$C$5:$I$45,7,$B$5) -> 3226.1468 | G14: =E14*F14 -> 0 | H14: =-Amortización!D10 -> -5106.0609 | I14: =H14*F14 -> -16472902 | J14: =IFERROR(MATCH(A14,'B Supuestos'!$D$20:$D$23,0),"") | K14: =IF(J14="","",INDEX('Trayectorias B'!$C$5:$I$45,A14-3,$B$5)) | L14: =IF(J14="","",K14*(1+'B Supuestos'!$B$12)) | M14: =IF(J14="","",INDEX('B Supuestos'!$F$20:$F$23,J14)) | N14: =IF(J14="",0,M14*(F14-L14)) -> 0 | O14: =C14+D14+G14+I14 -> -16472902 | P14: =O14+N14 -> -16472902 | Q14: =G14+I14 -> -16472902 | R14: =Q14+N14 -> -16472902
A15: 7 | B15: ='Trayectorias TRM'!B12 -> 46952 | C15: 0 | D15: 0 | E15: 0 | F15: =INDEX('Trayectorias B'!$C$5:$I$45,8,$B$5) -> 3390.1106 | G15: =E15*F15 -> 0 | H15: =-Amortización!D11 -> -5106.0609 | I15: =H15*F15 -> -17310111 | J15: =IFERROR(MATCH(A15,'B Supuestos'!$D$20:$D$23,0),"") | K15: =IF(J15="","",INDEX('Trayectorias B'!$C$5:$I$45,A15-3,$B$5)) | L15: =IF(J15="","",K15*(1+'B Supuestos'!$B$12)) | M15: =IF(J15="","",INDEX('B Supuestos'!$F$20:$F$23,J15)) | N15: =IF(J15="",0,M15*(F15-L15)) -> 0 | O15: =C15+D15+G15+I15 -> -17310111 | P15: =O15+N15 -> -17310111 | Q15: =G15+I15 -> -17310111 | R15: =Q15+N15 -> -17310111
A16: 8 | B16: ='Trayectorias TRM'!B13 -> 47044 | C16: 0 | D16: 0 | E16: 0 | F16: =INDEX('Trayectorias B'!$C$5:$I$45,9,$B$5) -> 3289.9541 | G16: =E16*F16 -> 0 | H16: =-Amortización!D12 -> -5106.0609 | I16: =H16*F16 -> -16798706 | J16: =IFERROR(MATCH(A16,'B Supuestos'!$D$20:$D$23,0),"") | K16: =IF(J16="","",INDEX('Trayectorias B'!$C$5:$I$45,A16-3,$B$5)) | L16: =IF(J16="","",K16*(1+'B Supuestos'!$B$12)) | M16: =IF(J16="","",INDEX('B Supuestos'!$F$20:$F$23,J16)) | N16: =IF(J16="",0,M16*(F16-L16)) -> 0 | O16: =C16+D16+G16+I16 -> -16798706 | P16: =O16+N16 -> -16798706 | Q16: =G16+I16 -> -16798706 | R16: =Q16+N16 -> -16798706
A17: 9 | B17: ='Trayectorias TRM'!B14 -> 47136 | C17: 0 | D17: 0 | E17: 0 | F17: =INDEX('Trayectorias B'!$C$5:$I$45,10,$B$5) -> 3263.5351 | G17: =E17*F17 -> 0 | H17: =-Amortización!D13 -> -5106.0609 | I17: =H17*F17 -> -16663809 | J17: =IFERROR(MATCH(A17,'B Supuestos'!$D$20:$D$23,0),"") | K17: =IF(J17="","",INDEX('Trayectorias B'!$C$5:$I$45,A17-3,$B$5)) | L17: =IF(J17="","",K17*(1+'B Supuestos'!$B$12)) | M17: =IF(J17="","",INDEX('B Supuestos'!$F$20:$F$23,J17)) | N17: =IF(J17="",0,M17*(F17-L17)) -> 0 | O17: =C17+D17+G17+I17 -> -16663809 | P17: =O17+N17 -> -16663809 | Q17: =G17+I17 -> -16663809 | R17: =Q17+N17 -> -16663809
A18: 10 | B18: ='Trayectorias TRM'!B15 -> 47226 | C18: 0 | D18: 0 | E18: 0 | F18: =INDEX('Trayectorias B'!$C$5:$I$45,11,$B$5) -> 3466.0194 | G18: =E18*F18 -> 0 | H18: =-Amortización!D14 -> -5106.0609 | I18: =H18*F18 -> -17697706 | J18: =IFERROR(MATCH(A18,'B Supuestos'!$D$20:$D$23,0),"") | K18: =IF(J18="","",INDEX('Trayectorias B'!$C$5:$I$45,A18-3,$B$5)) | L18: =IF(J18="","",K18*(1+'B Supuestos'!$B$12)) | M18: =IF(J18="","",INDEX('B Supuestos'!$F$20:$F$23,J18)) | N18: =IF(J18="",0,M18*(F18-L18)) -> 0 | O18: =C18+D18+G18+I18 -> -17697706 | P18: =O18+N18 -> -17697706 | Q18: =G18+I18 -> -17697706 | R18: =Q18+N18 -> -17697706
A19: 11 | B19: ='Trayectorias TRM'!B16 -> 47317 | C19: 0 | D19: 0 | E19: 0 | F19: =INDEX('Trayectorias B'!$C$5:$I$45,12,$B$5) -> 3381.85 | G19: =E19*F19 -> 0 | H19: =-Amortización!D15 -> -5106.0609 | I19: =H19*F19 -> -17267932 | J19: =IFERROR(MATCH(A19,'B Supuestos'!$D$20:$D$23,0),"") | K19: =IF(J19="","",INDEX('Trayectorias B'!$C$5:$I$45,A19-3,$B$5)) | L19: =IF(J19="","",K19*(1+'B Supuestos'!$B$12)) | M19: =IF(J19="","",INDEX('B Supuestos'!$F$20:$F$23,J19)) | N19: =IF(J19="",0,M19*(F19-L19)) -> 0 | O19: =C19+D19+G19+I19 -> -17267932 | P19: =O19+N19 -> -17267932 | Q19: =G19+I19 -> -17267932 | R19: =Q19+N19 -> -17267932
A20: 12 | B20: ='Trayectorias TRM'!B17 -> 47409 | C20: 0 | D20: 0 | E20: 0 | F20: =INDEX('Trayectorias B'!$C$5:$I$45,13,$B$5) -> 3567.1392 | G20: =E20*F20 -> 0 | H20: =-Amortización!D16 -> -5106.0609 | I20: =H20*F20 -> -18214030 | J20: =IFERROR(MATCH(A20,'B Supuestos'!$D$20:$D$23,0),"") | K20: =IF(J20="","",INDEX('Trayectorias B'!$C$5:$I$45,A20-3,$B$5)) | L20: =IF(J20="","",K20*(1+'B Supuestos'!$B$12)) | M20: =IF(J20="","",INDEX('B Supuestos'!$F$20:$F$23,J20)) | N20: =IF(J20="",0,M20*(F20-L20)) -> 0 | O20: =C20+D20+G20+I20 -> -18214030 | P20: =O20+N20 -> -18214030 | Q20: =G20+I20 -> -18214030 | R20: =Q20+N20 -> -18214030
A21: 13 | B21: ='Trayectorias TRM'!B18 -> 47501 | C21: 0 | D21: 0 | E21: 0 | F21: =INDEX('Trayectorias B'!$C$5:$I$45,14,$B$5) -> 3880.807 | G21: =E21*F21 -> 0 | H21: =-Amortización!D17 -> -5106.0609 | I21: =H21*F21 -> -19815637 | J21: =IFERROR(MATCH(A21,'B Supuestos'!$D$20:$D$23,0),"") | K21: =IF(J21="","",INDEX('Trayectorias B'!$C$5:$I$45,A21-3,$B$5)) | L21: =IF(J21="","",K21*(1+'B Supuestos'!$B$12)) | M21: =IF(J21="","",INDEX('B Supuestos'!$F$20:$F$23,J21)) | N21: =IF(J21="",0,M21*(F21-L21)) -> 0 | O21: =C21+D21+G21+I21 -> -19815637 | P21: =O21+N21 -> -19815637 | Q21: =G21+I21 -> -19815637 | R21: =Q21+N21 -> -19815637
A22: 14 | B22: ='Trayectorias TRM'!B19 -> 47591 | C22: 0 | D22: 0 | E22: 0 | F22: =INDEX('Trayectorias B'!$C$5:$I$45,15,$B$5) -> 3994.7046 | G22: =E22*F22 -> 0 | H22: =-Amortización!D18 -> -5106.0609 | I22: =H22*F22 -> -20397205 | J22: =IFERROR(MATCH(A22,'B Supuestos'!$D$20:$D$23,0),"") | K22: =IF(J22="","",INDEX('Trayectorias B'!$C$5:$I$45,A22-3,$B$5)) | L22: =IF(J22="","",K22*(1+'B Supuestos'!$B$12)) | M22: =IF(J22="","",INDEX('B Supuestos'!$F$20:$F$23,J22)) | N22: =IF(J22="",0,M22*(F22-L22)) -> 0 | O22: =C22+D22+G22+I22 -> -20397205 | P22: =O22+N22 -> -20397205 | Q22: =G22+I22 -> -20397205 | R22: =Q22+N22 -> -20397205
A23: 15 | B23: ='Trayectorias TRM'!B20 -> 47682 | C23: 0 | D23: 0 | E23: 0 | F23: =INDEX('Trayectorias B'!$C$5:$I$45,16,$B$5) -> 3918.5697 | G23: =E23*F23 -> 0 | H23: =-Amortización!D19 -> -5106.0609 | I23: =H23*F23 -> -20008456 | J23: =IFERROR(MATCH(A23,'B Supuestos'!$D$20:$D$23,0),"") | K23: =IF(J23="","",INDEX('Trayectorias B'!$C$5:$I$45,A23-3,$B$5)) | L23: =IF(J23="","",K23*(1+'B Supuestos'!$B$12)) | M23: =IF(J23="","",INDEX('B Supuestos'!$F$20:$F$23,J23)) | N23: =IF(J23="",0,M23*(F23-L23)) -> 0 | O23: =C23+D23+G23+I23 -> -20008456 | P23: =O23+N23 -> -20008456 | Q23: =G23+I23 -> -20008456 | R23: =Q23+N23 -> -20008456
A24: 16 | B24: ='Trayectorias TRM'!B21 -> 47774 | C24: 0 | D24: 0 | E24: 0 | F24: =INDEX('Trayectorias B'!$C$5:$I$45,17,$B$5) -> 3629.4964 | G24: =E24*F24 -> 0 | H24: =-Amortización!D20 -> -5106.0609 | I24: =H24*F24 -> -18532430 | J24: =IFERROR(MATCH(A24,'B Supuestos'!$D$20:$D$23,0),"") | K24: =IF(J24="","",INDEX('Trayectorias B'!$C$5:$I$45,A24-3,$B$5)) | L24: =IF(J24="","",K24*(1+'B Supuestos'!$B$12)) | M24: =IF(J24="","",INDEX('B Supuestos'!$F$20:$F$23,J24)) | N24: =IF(J24="",0,M24*(F24-L24)) -> 0 | O24: =C24+D24+G24+I24 -> -18532430 | P24: =O24+N24 -> -18532430 | Q24: =G24+I24 -> -18532430 | R24: =Q24+N24 -> -18532430
A25: 17 | B25: ='Trayectorias TRM'!B22 -> 47866 | C25: 0 | D25: 0 | E25: 0 | F25: =INDEX('Trayectorias B'!$C$5:$I$45,18,$B$5) -> 3663.742 | G25: =E25*F25 -> 0 | H25: =-Amortización!D21 -> -5106.0609 | I25: =H25*F25 -> -18707290 | J25: =IFERROR(MATCH(A25,'B Supuestos'!$D$20:$D$23,0),"") | K25: =IF(J25="","",INDEX('Trayectorias B'!$C$5:$I$45,A25-3,$B$5)) | L25: =IF(J25="","",K25*(1+'B Supuestos'!$B$12)) | M25: =IF(J25="","",INDEX('B Supuestos'!$F$20:$F$23,J25)) | N25: =IF(J25="",0,M25*(F25-L25)) -> 0 | O25: =C25+D25+G25+I25 -> -18707290 | P25: =O25+N25 -> -18707290 | Q25: =G25+I25 -> -18707290 | R25: =Q25+N25 -> -18707290
A26: 18 | B26: ='Trayectorias TRM'!B23 -> 47956 | C26: 0 | D26: 0 | E26: 0 | F26: =INDEX('Trayectorias B'!$C$5:$I$45,19,$B$5) -> 3655.6138 | G26: =E26*F26 -> 0 | H26: =-Amortización!D22 -> -5106.0609 | I26: =H26*F26 -> -18665787 | J26: =IFERROR(MATCH(A26,'B Supuestos'!$D$20:$D$23,0),"") | K26: =IF(J26="","",INDEX('Trayectorias B'!$C$5:$I$45,A26-3,$B$5)) | L26: =IF(J26="","",K26*(1+'B Supuestos'!$B$12)) | M26: =IF(J26="","",INDEX('B Supuestos'!$F$20:$F$23,J26)) | N26: =IF(J26="",0,M26*(F26-L26)) -> 0 | O26: =C26+D26+G26+I26 -> -18665787 | P26: =O26+N26 -> -18665787 | Q26: =G26+I26 -> -18665787 | R26: =Q26+N26 -> -18665787
A27: 19 | B27: ='Trayectorias TRM'!B24 -> 48047 | C27: 0 | D27: 0 | E27: 0 | F27: =INDEX('Trayectorias B'!$C$5:$I$45,20,$B$5) -> 3684.9573 | G27: =E27*F27 -> 0 | H27: =-Amortización!D23 -> -5106.0609 | I27: =H27*F27 -> -18815616 | J27: =IFERROR(MATCH(A27,'B Supuestos'!$D$20:$D$23,0),"") | K27: =IF(J27="","",INDEX('Trayectorias B'!$C$5:$I$45,A27-3,$B$5)) | L27: =IF(J27="","",K27*(1+'B Supuestos'!$B$12)) | M27: =IF(J27="","",INDEX('B Supuestos'!$F$20:$F$23,J27)) | N27: =IF(J27="",0,M27*(F27-L27)) -> 0 | O27: =C27+D27+G27+I27 -> -18815616 | P27: =O27+N27 -> -18815616 | Q27: =G27+I27 -> -18815616 | R27: =Q27+N27 -> -18815616
A28: 20 | B28: ='Trayectorias TRM'!B25 -> 48139 | C28: 0 | D28: 0 | E28: 0 | F28: =INDEX('Trayectorias B'!$C$5:$I$45,21,$B$5) -> 3507.8901 | G28: =E28*F28 -> 0 | H28: =-Amortización!D24 -> -5106.0609 | I28: =H28*F28 -> -17911500 | J28: =IFERROR(MATCH(A28,'B Supuestos'!$D$20:$D$23,0),"") | K28: =IF(J28="","",INDEX('Trayectorias B'!$C$5:$I$45,A28-3,$B$5)) | L28: =IF(J28="","",K28*(1+'B Supuestos'!$B$12)) | M28: =IF(J28="","",INDEX('B Supuestos'!$F$20:$F$23,J28)) | N28: =IF(J28="",0,M28*(F28-L28)) -> 0 | O28: =C28+D28+G28+I28 -> -17911500 | P28: =O28+N28 -> -17911500 | Q28: =G28+I28 -> -17911500 | R28: =Q28+N28 -> -17911500
A29: 21 | B29: ='Trayectorias TRM'!B26 -> 48231 | C29: 0 | D29: 0 | E29: 0 | F29: =INDEX('Trayectorias B'!$C$5:$I$45,22,$B$5) -> 4012.6216 | G29: =E29*F29 -> 0 | H29: =-Amortización!D25 -> -5106.0609 | I29: =H29*F29 -> -20488690 | J29: =IFERROR(MATCH(A29,'B Supuestos'!$D$20:$D$23,0),"") | K29: =IF(J29="","",INDEX('Trayectorias B'!$C$5:$I$45,A29-3,$B$5)) | L29: =IF(J29="","",K29*(1+'B Supuestos'!$B$12)) | M29: =IF(J29="","",INDEX('B Supuestos'!$F$20:$F$23,J29)) | N29: =IF(J29="",0,M29*(F29-L29)) -> 0 | O29: =C29+D29+G29+I29 -> -20488690 | P29: =O29+N29 -> -20488690 | Q29: =G29+I29 -> -20488690 | R29: =Q29+N29 -> -20488690
A30: 22 | B30: ='Trayectorias TRM'!B27 -> 48322 | C30: 0 | D30: 0 | E30: 0 | F30: =INDEX('Trayectorias B'!$C$5:$I$45,23,$B$5) -> 3795.7529 | G30: =E30*F30 -> 0 | H30: =-Amortización!D26 -> -5106.0609 | I30: =H30*F30 -> -19381345 | J30: =IFERROR(MATCH(A30,'B Supuestos'!$D$20:$D$23,0),"") | K30: =IF(J30="","",INDEX('Trayectorias B'!$C$5:$I$45,A30-3,$B$5)) | L30: =IF(J30="","",K30*(1+'B Supuestos'!$B$12)) | M30: =IF(J30="","",INDEX('B Supuestos'!$F$20:$F$23,J30)) | N30: =IF(J30="",0,M30*(F30-L30)) -> 0 | O30: =C30+D30+G30+I30 -> -19381345 | P30: =O30+N30 -> -19381345 | Q30: =G30+I30 -> -19381345 | R30: =Q30+N30 -> -19381345
A31: 23 | B31: ='Trayectorias TRM'!B28 -> 48413 | C31: 0 | D31: 0 | E31: 0 | F31: =INDEX('Trayectorias B'!$C$5:$I$45,24,$B$5) -> 3655.6528 | G31: =E31*F31 -> 0 | H31: =-Amortización!D27 -> -5106.0609 | I31: =H31*F31 -> -18665986 | J31: =IFERROR(MATCH(A31,'B Supuestos'!$D$20:$D$23,0),"") | K31: =IF(J31="","",INDEX('Trayectorias B'!$C$5:$I$45,A31-3,$B$5)) | L31: =IF(J31="","",K31*(1+'B Supuestos'!$B$12)) | M31: =IF(J31="","",INDEX('B Supuestos'!$F$20:$F$23,J31)) | N31: =IF(J31="",0,M31*(F31-L31)) -> 0 | O31: =C31+D31+G31+I31 -> -18665986 | P31: =O31+N31 -> -18665986 | Q31: =G31+I31 -> -18665986 | R31: =Q31+N31 -> -18665986
A32: 24 | B32: ='Trayectorias TRM'!B29 -> 48505 | C32: 0 | D32: 0 | E32: 0 | F32: =INDEX('Trayectorias B'!$C$5:$I$45,25,$B$5) -> 3695.2578 | G32: =E32*F32 -> 0 | H32: =-Amortización!D28 -> -5106.0609 | I32: =H32*F32 -> -18868211 | J32: =IFERROR(MATCH(A32,'B Supuestos'!$D$20:$D$23,0),"") | K32: =IF(J32="","",INDEX('Trayectorias B'!$C$5:$I$45,A32-3,$B$5)) | L32: =IF(J32="","",K32*(1+'B Supuestos'!$B$12)) | M32: =IF(J32="","",INDEX('B Supuestos'!$F$20:$F$23,J32)) | N32: =IF(J32="",0,M32*(F32-L32)) -> 0 | O32: =C32+D32+G32+I32 -> -18868211 | P32: =O32+N32 -> -18868211 | Q32: =G32+I32 -> -18868211 | R32: =Q32+N32 -> -18868211
A33: 25 | B33: ='Trayectorias TRM'!B30 -> 48597 | C33: 0 | D33: 0 | E33: 0 | F33: =INDEX('Trayectorias B'!$C$5:$I$45,26,$B$5) -> 3445.9939 | G33: =E33*F33 -> 0 | H33: =-Amortización!D29 -> -5106.0609 | I33: =H33*F33 -> -17595455 | J33: =IFERROR(MATCH(A33,'B Supuestos'!$D$20:$D$23,0),"") | K33: =IF(J33="","",INDEX('Trayectorias B'!$C$5:$I$45,A33-3,$B$5)) | L33: =IF(J33="","",K33*(1+'B Supuestos'!$B$12)) | M33: =IF(J33="","",INDEX('B Supuestos'!$F$20:$F$23,J33)) | N33: =IF(J33="",0,M33*(F33-L33)) -> 0 | O33: =C33+D33+G33+I33 -> -17595455 | P33: =O33+N33 -> -17595455 | Q33: =G33+I33 -> -17595455 | R33: =Q33+N33 -> -17595455
A34: 26 | B34: ='Trayectorias TRM'!B31 -> 48687 | C34: 0 | D34: 0 | E34: 0 | F34: =INDEX('Trayectorias B'!$C$5:$I$45,27,$B$5) -> 3454.4975 | G34: =E34*F34 -> 0 | H34: =-Amortización!D30 -> -5106.0609 | I34: =H34*F34 -> -17638875 | J34: =IFERROR(MATCH(A34,'B Supuestos'!$D$20:$D$23,0),"") | K34: =IF(J34="","",INDEX('Trayectorias B'!$C$5:$I$45,A34-3,$B$5)) | L34: =IF(J34="","",K34*(1+'B Supuestos'!$B$12)) | M34: =IF(J34="","",INDEX('B Supuestos'!$F$20:$F$23,J34)) | N34: =IF(J34="",0,M34*(F34-L34)) -> 0 | O34: =C34+D34+G34+I34 -> -17638875 | P34: =O34+N34 -> -17638875 | Q34: =G34+I34 -> -17638875 | R34: =Q34+N34 -> -17638875
A35: 27 | B35: ='Trayectorias TRM'!B32 -> 48778 | C35: 0 | D35: 0 | E35: 0 | F35: =INDEX('Trayectorias B'!$C$5:$I$45,28,$B$5) -> 3829.234 | G35: =E35*F35 -> 0 | H35: =-Amortización!D31 -> -5106.0609 | I35: =H35*F35 -> -19552302 | J35: =IFERROR(MATCH(A35,'B Supuestos'!$D$20:$D$23,0),"") | K35: =IF(J35="","",INDEX('Trayectorias B'!$C$5:$I$45,A35-3,$B$5)) | L35: =IF(J35="","",K35*(1+'B Supuestos'!$B$12)) | M35: =IF(J35="","",INDEX('B Supuestos'!$F$20:$F$23,J35)) | N35: =IF(J35="",0,M35*(F35-L35)) -> 0 | O35: =C35+D35+G35+I35 -> -19552302 | P35: =O35+N35 -> -19552302 | Q35: =G35+I35 -> -19552302 | R35: =Q35+N35 -> -19552302
A36: 28 | B36: ='Trayectorias TRM'!B33 -> 48870 | C36: 0 | D36: 0 | E36: 0 | F36: =INDEX('Trayectorias B'!$C$5:$I$45,29,$B$5) -> 3721.6324 | G36: =E36*F36 -> 0 | H36: =-Amortización!D32 -> -5106.0609 | I36: =H36*F36 -> -19002882 | J36: =IFERROR(MATCH(A36,'B Supuestos'!$D$20:$D$23,0),"") -> 1 | K36: =IF(J36="","",INDEX('Trayectorias B'!$C$5:$I$45,A36-3,$B$5)) -> 3695.2578 | L36: =IF(J36="","",K36*(1+'B Supuestos'!$B$12)) -> 3995.2017 | M36: =IF(J36="","",INDEX('B Supuestos'!$F$20:$F$23,J36)) -> 15318.183 | N36: =IF(J36="",0,M36*(F36-L36)) -> -4190584.9 | O36: =C36+D36+G36+I36 -> -19002882 | P36: =O36+N36 -> -23193466 | Q36: =G36+I36 -> -19002882 | R36: =Q36+N36 -> -23193466
A37: 29 | B37: ='Trayectorias TRM'!B34 -> 48962 | C37: 0 | D37: 0 | E37: 0 | F37: =INDEX('Trayectorias B'!$C$5:$I$45,30,$B$5) -> 3666.9433 | G37: =E37*F37 -> 0 | H37: =-Amortización!D33 -> -5106.0609 | I37: =H37*F37 -> -18723636 | J37: =IFERROR(MATCH(A37,'B Supuestos'!$D$20:$D$23,0),"") | K37: =IF(J37="","",INDEX('Trayectorias B'!$C$5:$I$45,A37-3,$B$5)) | L37: =IF(J37="","",K37*(1+'B Supuestos'!$B$12)) | M37: =IF(J37="","",INDEX('B Supuestos'!$F$20:$F$23,J37)) | N37: =IF(J37="",0,M37*(F37-L37)) -> 0 | O37: =C37+D37+G37+I37 -> -18723636 | P37: =O37+N37 -> -18723636 | Q37: =G37+I37 -> -18723636 | R37: =Q37+N37 -> -18723636
A38: 30 | B38: ='Trayectorias TRM'!B35 -> 49052 | C38: 0 | D38: 0 | E38: 0 | F38: =INDEX('Trayectorias B'!$C$5:$I$45,31,$B$5) -> 3743.9193 | G38: =E38*F38 -> 0 | H38: =-Amortización!D34 -> -5106.0609 | I38: =H38*F38 -> -19116680 | J38: =IFERROR(MATCH(A38,'B Supuestos'!$D$20:$D$23,0),"") | K38: =IF(J38="","",INDEX('Trayectorias B'!$C$5:$I$45,A38-3,$B$5)) | L38: =IF(J38="","",K38*(1+'B Supuestos'!$B$12)) | M38: =IF(J38="","",INDEX('B Supuestos'!$F$20:$F$23,J38)) | N38: =IF(J38="",0,M38*(F38-L38)) -> 0 | O38: =C38+D38+G38+I38 -> -19116680 | P38: =O38+N38 -> -19116680 | Q38: =G38+I38 -> -19116680 | R38: =Q38+N38 -> -19116680
A39: 31 | B39: ='Trayectorias TRM'!B36 -> 49143 | C39: 0 | D39: 0 | E39: 0 | F39: =INDEX('Trayectorias B'!$C$5:$I$45,32,$B$5) -> 3783.6619 | G39: =E39*F39 -> 0 | H39: =-Amortización!D35 -> -5106.0609 | I39: =H39*F39 -> -19319608 | J39: =IFERROR(MATCH(A39,'B Supuestos'!$D$20:$D$23,0),"") | K39: =IF(J39="","",INDEX('Trayectorias B'!$C$5:$I$45,A39-3,$B$5)) | L39: =IF(J39="","",K39*(1+'B Supuestos'!$B$12)) | M39: =IF(J39="","",INDEX('B Supuestos'!$F$20:$F$23,J39)) | N39: =IF(J39="",0,M39*(F39-L39)) -> 0 | O39: =C39+D39+G39+I39 -> -19319608 | P39: =O39+N39 -> -19319608 | Q39: =G39+I39 -> -19319608 | R39: =Q39+N39 -> -19319608
A40: 32 | B40: ='Trayectorias TRM'!B37 -> 49235 | C40: 0 | D40: 0 | E40: 0 | F40: =INDEX('Trayectorias B'!$C$5:$I$45,33,$B$5) -> 3336.8079 | G40: =E40*F40 -> 0 | H40: =-Amortización!D36 -> -5106.0609 | I40: =H40*F40 -> -17037944 | J40: =IFERROR(MATCH(A40,'B Supuestos'!$D$20:$D$23,0),"") -> 2 | K40: =IF(J40="","",INDEX('Trayectorias B'!$C$5:$I$45,A40-3,$B$5)) -> 3721.6324 | L40: =IF(J40="","",K40*(1+'B Supuestos'!$B$12)) -> 4023.7171 | M40: =IF(J40="","",INDEX('B Supuestos'!$F$20:$F$23,J40)) -> 15318.183 | N40: =IF(J40="",0,M40*(F40-L40)) -> -10522201 | O40: =C40+D40+G40+I40 -> -17037944 | P40: =O40+N40 -> -27560145 | Q40: =G40+I40 -> -17037944 | R40: =Q40+N40 -> -27560145
A41: 33 | B41: ='Trayectorias TRM'!B38 -> 49327 | C41: 0 | D41: 0 | E41: 0 | F41: =INDEX('Trayectorias B'!$C$5:$I$45,34,$B$5) -> 3214.6259 | G41: =E41*F41 -> 0 | H41: =-Amortización!D37 -> -5106.0609 | I41: =H41*F41 -> -16414075 | J41: =IFERROR(MATCH(A41,'B Supuestos'!$D$20:$D$23,0),"") | K41: =IF(J41="","",INDEX('Trayectorias B'!$C$5:$I$45,A41-3,$B$5)) | L41: =IF(J41="","",K41*(1+'B Supuestos'!$B$12)) | M41: =IF(J41="","",INDEX('B Supuestos'!$F$20:$F$23,J41)) | N41: =IF(J41="",0,M41*(F41-L41)) -> 0 | O41: =C41+D41+G41+I41 -> -16414075 | P41: =O41+N41 -> -16414075 | Q41: =G41+I41 -> -16414075 | R41: =Q41+N41 -> -16414075
A42: 34 | B42: ='Trayectorias TRM'!B39 -> 49417 | C42: 0 | D42: 0 | E42: 0 | F42: =INDEX('Trayectorias B'!$C$5:$I$45,35,$B$5) -> 3333.7776 | G42: =E42*F42 -> 0 | H42: =-Amortización!D38 -> -5106.0609 | I42: =H42*F42 -> -17022472 | J42: =IFERROR(MATCH(A42,'B Supuestos'!$D$20:$D$23,0),"") | K42: =IF(J42="","",INDEX('Trayectorias B'!$C$5:$I$45,A42-3,$B$5)) | L42: =IF(J42="","",K42*(1+'B Supuestos'!$B$12)) | M42: =IF(J42="","",INDEX('B Supuestos'!$F$20:$F$23,J42)) | N42: =IF(J42="",0,M42*(F42-L42)) -> 0 | O42: =C42+D42+G42+I42 -> -17022472 | P42: =O42+N42 -> -17022472 | Q42: =G42+I42 -> -17022472 | R42: =Q42+N42 -> -17022472
A43: 35 | B43: ='Trayectorias TRM'!B40 -> 49508 | C43: 0 | D43: 0 | E43: 0 | F43: =INDEX('Trayectorias B'!$C$5:$I$45,36,$B$5) -> 3365.6192 | G43: =E43*F43 -> 0 | H43: =-Amortización!D39 -> -5106.0609 | I43: =H43*F43 -> -17185057 | J43: =IFERROR(MATCH(A43,'B Supuestos'!$D$20:$D$23,0),"") | K43: =IF(J43="","",INDEX('Trayectorias B'!$C$5:$I$45,A43-3,$B$5)) | L43: =IF(J43="","",K43*(1+'B Supuestos'!$B$12)) | M43: =IF(J43="","",INDEX('B Supuestos'!$F$20:$F$23,J43)) | N43: =IF(J43="",0,M43*(F43-L43)) -> 0 | O43: =C43+D43+G43+I43 -> -17185057 | P43: =O43+N43 -> -17185057 | Q43: =G43+I43 -> -17185057 | R43: =Q43+N43 -> -17185057
A44: 36 | B44: ='Trayectorias TRM'!B41 -> 49600 | C44: 0 | D44: 0 | E44: 0 | F44: =INDEX('Trayectorias B'!$C$5:$I$45,37,$B$5) -> 3548.8586 | G44: =E44*F44 -> 0 | H44: =-Amortización!D40 -> -5106.0609 | I44: =H44*F44 -> -18120688 | J44: =IFERROR(MATCH(A44,'B Supuestos'!$D$20:$D$23,0),"") -> 3 | K44: =IF(J44="","",INDEX('Trayectorias B'!$C$5:$I$45,A44-3,$B$5)) -> 3336.8079 | L44: =IF(J44="","",K44*(1+'B Supuestos'!$B$12)) -> 3607.6564 | M44: =IF(J44="","",INDEX('B Supuestos'!$F$20:$F$23,J44)) -> 15318.183 | N44: =IF(J44="",0,M44*(F44-L44)) -> -900676.09 | O44: =C44+D44+G44+I44 -> -18120688 | P44: =O44+N44 -> -19021364 | Q44: =G44+I44 -> -18120688 | R44: =Q44+N44 -> -19021364
A45: 37 | B45: ='Trayectorias TRM'!B42 -> 49692 | C45: 0 | D45: 0 | E45: 0 | F45: =INDEX('Trayectorias B'!$C$5:$I$45,38,$B$5) -> 3674.0702 | G45: =E45*F45 -> 0 | H45: =-Amortización!D41 -> -5106.0609 | I45: =H45*F45 -> -18760026 | J45: =IFERROR(MATCH(A45,'B Supuestos'!$D$20:$D$23,0),"") | K45: =IF(J45="","",INDEX('Trayectorias B'!$C$5:$I$45,A45-3,$B$5)) | L45: =IF(J45="","",K45*(1+'B Supuestos'!$B$12)) | M45: =IF(J45="","",INDEX('B Supuestos'!$F$20:$F$23,J45)) | N45: =IF(J45="",0,M45*(F45-L45)) -> 0 | O45: =C45+D45+G45+I45 -> -18760026 | P45: =O45+N45 -> -18760026 | Q45: =G45+I45 -> -18760026 | R45: =Q45+N45 -> -18760026
A46: 38 | B46: ='Trayectorias TRM'!B43 -> 49783 | C46: 0 | D46: 0 | E46: 0 | F46: =INDEX('Trayectorias B'!$C$5:$I$45,39,$B$5) -> 3823.7906 | G46: =E46*F46 -> 0 | H46: =-Amortización!D42 -> -5106.0609 | I46: =H46*F46 -> -19524508 | J46: =IFERROR(MATCH(A46,'B Supuestos'!$D$20:$D$23,0),"") | K46: =IF(J46="","",INDEX('Trayectorias B'!$C$5:$I$45,A46-3,$B$5)) | L46: =IF(J46="","",K46*(1+'B Supuestos'!$B$12)) | M46: =IF(J46="","",INDEX('B Supuestos'!$F$20:$F$23,J46)) | N46: =IF(J46="",0,M46*(F46-L46)) -> 0 | O46: =C46+D46+G46+I46 -> -19524508 | P46: =O46+N46 -> -19524508 | Q46: =G46+I46 -> -19524508 | R46: =Q46+N46 -> -19524508
A47: 39 | B47: ='Trayectorias TRM'!B44 -> 49874 | C47: 0 | D47: 0 | E47: 0 | F47: =INDEX('Trayectorias B'!$C$5:$I$45,40,$B$5) -> 3947.6093 | G47: =E47*F47 -> 0 | H47: =-Amortización!D43 -> -5106.0609 | I47: =H47*F47 -> -20156733 | J47: =IFERROR(MATCH(A47,'B Supuestos'!$D$20:$D$23,0),"") | K47: =IF(J47="","",INDEX('Trayectorias B'!$C$5:$I$45,A47-3,$B$5)) | L47: =IF(J47="","",K47*(1+'B Supuestos'!$B$12)) | M47: =IF(J47="","",INDEX('B Supuestos'!$F$20:$F$23,J47)) | N47: =IF(J47="",0,M47*(F47-L47)) -> 0 | O47: =C47+D47+G47+I47 -> -20156733 | P47: =O47+N47 -> -20156733 | Q47: =G47+I47 -> -20156733 | R47: =Q47+N47 -> -20156733
A48: 40 | B48: ='Trayectorias TRM'!B45 -> 49966 | C48: 0 | D48: 0 | E48: 0 | F48: =INDEX('Trayectorias B'!$C$5:$I$45,41,$B$5) -> 3994.0644 | G48: =E48*F48 -> 0 | H48: =-Amortización!D44 -> -5106.0609 | I48: =H48*F48 -> -20393936 | J48: =IFERROR(MATCH(A48,'B Supuestos'!$D$20:$D$23,0),"") -> 4 | K48: =IF(J48="","",INDEX('Trayectorias B'!$C$5:$I$45,A48-3,$B$5)) -> 3548.8586 | L48: =IF(J48="","",K48*(1+'B Supuestos'!$B$12)) -> 3836.9193 | M48: =IF(J48="","",INDEX('B Supuestos'!$F$20:$F$23,J48)) -> 15318.183 | N48: =IF(J48="",0,M48*(F48-L48)) -> 2407177.9 | O48: =C48+D48+G48+I48 -> -20393936 | P48: =O48+N48 -> -17986758 | Q48: =G48+I48 -> -20393936 | R48: =Q48+N48 -> -17986758
A49: Total | C49: =SUM(C8:C48) -> -400000000 | D49: =SUM(D8:D48) -> 40000000 | E49: =SUM(E8:E48) -> 113397.61 | G49: =SUM(G8:G48) -> 360000000 | H49: =SUM(H8:H48) -> -204242.44 | I49: =SUM(I8:I48) -> -7.397095e+08 | N49: =SUM(N8:N48) -> -13206284 | O49: =SUM(O8:O48) -> -7.397095e+08 | P49: =SUM(P8:P48) -> -7.5291579e+08 | Q49: =SUM(Q8:Q48) -> -3.797095e+08 | R49: =SUM(R8:R48) -> -3.9291579e+08
A51: Indicadores del escenario elegido
A52: Indicador | B52: Sin cobertura | C52: Con cobertura | D52: Diferencia
A53: Costo total de las cuotas (COP) | B53: =-SUM(Q9:Q48) -> 7.397095e+08 | C53: =-SUM(R9:R48) -> 7.5291579e+08 | D53: =C53-B53 -> 13206284
A54: Costo de las cuotas de los años 7-10 (COP) | B54: =-SUM(Q33:Q48) -> 2.9556488e+08 | C54: =-SUM(R33:R48) -> 3.0877116e+08 | D54: =C54-B54 -> 13206284
A55: Costo efectivo anual del crédito en pesos (TIR) | B55: =(1+IRR(Q8:Q48))^4-1 -> 0.17357896 | C55: =(1+IRR(R8:R48))^4-1 -> 0.17692405 | D55: =C55-B55 -> 0.0033450968
A56: VPN de las cuotas al 13 % EA (COP) | B56: =-NPV('B Supuestos'!$B$14,Q9:Q48) -> 4.1904208e+08 | C56: =-NPV('B Supuestos'!$B$14,R9:R48) -> 4.2437206e+08 | D56: =C56-B56 -> 5329977.3
A57: Resultado acumulado de los forwards (COP) | B57: 0 | C57: =SUM(N8:N48) -> -13206284 | D57: =C57-B57 -> -13206284
A58: Comprobación: compra = aporte + desembolso | B58: =IF(ABS(C8+D8+G8)<1,"Correcto","Revisar") -> Correcto
A61: Comparación de escenarios (fórmulas sobre la hoja «Flujos escenarios B»)
A62: Escenario | B62: TRM año 6 (trim. 24) | C62: TRM año 10 (trim. 40) | D62: Depreciación durante la cobertura | E62: Costo total sin cobertura (COP) | F62: Costo total con cobertura (COP) | G62: Resultado de los forwards (COP) | H62: Costo años 7-10 sin cobertura (COP) | I62: Costo años 7-10 con cobertura (COP) | J62: Presupuesto años 7-10 al forward (COP) | K62: Desviación vs presupuesto sin cobertura | L62: Desviación vs presupuesto con cobertura | M62: Costo efectivo anual sin cobertura | N62: Costo efectivo anual con cobertura | O62: VPN cuotas sin cobertura (COP) | P62: VPN cuotas con cobertura (COP)
A63: Favorable – Normal | B63: =INDEX('Trayectorias B'!$C$5:$I$45,25,1) -> 3826.6551 | C63: =INDEX('Trayectorias B'!$C$5:$I$45,41,1) -> 2915.2257 | D63: =C63/B63-1 -> -0.23817914 | E63: =-SUM('Flujos escenarios B'!B6:B45) -> 6.9478498e+08 | F63: =-SUM('Flujos escenarios B'!C6:C45) -> 7.250633e+08 | G63: =E63-F63 -> -30278315 | H63: =-SUM('Flujos escenarios B'!B30:B45) -> 2.6550316e+08 | I63: =-SUM('Flujos escenarios B'!C30:C45) -> 2.9578148e+08 | J63: =SUMIF('B.2 Escenarios'!$A$5:$A$32,A63,'B.2 Escenarios'!$L$5:$L$32) -> 2.8978393e+08 | K63: =H63/J63-1 -> -0.083789197 | L63: =I63/J63-1 -> 0.020696636 | M63: =(1+IRR('Flujos escenarios B'!B5:B45))^4-1 -> 0.15575437 | N63: =(1+IRR('Flujos escenarios B'!C5:C45))^4-1 -> 0.16325205 | O63: =-NPV('B Supuestos'!$B$14,'Flujos escenarios B'!B6:B45) -> 3.9467457e+08 | P63: =-NPV('B Supuestos'!$B$14,'Flujos escenarios B'!C6:C45) -> 4.0613885e+08
A64: Central – Normal | B64: =INDEX('Trayectorias B'!$C$5:$I$45,25,2) -> 3695.2578 | C64: =INDEX('Trayectorias B'!$C$5:$I$45,41,2) -> 3994.0644 | D64: =C64/B64-1 -> 0.080862207 | E64: =-SUM('Flujos escenarios B'!D6:D45) -> 7.397095e+08 | F64: =-SUM('Flujos escenarios B'!E6:E45) -> 7.5291579e+08 | G64: =E64-F64 -> -13206284 | H64: =-SUM('Flujos escenarios B'!D30:D45) -> 2.9556488e+08 | I64: =-SUM('Flujos escenarios B'!E30:E45) -> 3.0877116e+08 | J64: =SUMIF('B.2 Escenarios'!$A$5:$A$32,A64,'B.2 Escenarios'!$L$5:$L$32) -> 3.1583018e+08 | K64: =H64/J64-1 -> -0.064165189 | L64: =I64/J64-1 -> -0.022350679 | M64: =(1+IRR('Flujos escenarios B'!D5:D45))^4-1 -> 0.17357896 | N64: =(1+IRR('Flujos escenarios B'!E5:E45))^4-1 -> 0.17692405 | O64: =-NPV('B Supuestos'!$B$14,'Flujos escenarios B'!D6:D45) -> 4.1904208e+08 | P64: =-NPV('B Supuestos'!$B$14,'Flujos escenarios B'!E6:E45) -> 4.2437206e+08
A65: Adverso – Normal | B65: =INDEX('Trayectorias B'!$C$5:$I$45,25,3) -> 3823.1388 | C65: =INDEX('Trayectorias B'!$C$5:$I$45,41,3) -> 5759.8568 | D65: =C65/B65-1 -> 0.50657799 | E65: =-SUM('Flujos escenarios B'!F6:F45) -> 8.2991287e+08 | F65: =-SUM('Flujos escenarios B'!G6:G45) -> 8.2389214e+08 | G65: =E65-F65 -> 6020721.7 | H65: =-SUM('Flujos escenarios B'!F30:F45) -> 4.0176647e+08 | I65: =-SUM('Flujos escenarios B'!G30:G45) -> 3.9574575e+08 | J65: =SUMIF('B.2 Escenarios'!$A$5:$A$32,A65,'B.2 Escenarios'!$L$5:$L$32) -> 4.199525e+08 | K65: =H65/J65-1 -> -0.043304964 | L65: =I65/J65-1 -> -0.057641637 | M65: =(1+IRR('Flujos escenarios B'!F5:F45))^4-1 -> 0.18996016 | N65: =(1+IRR('Flujos escenarios B'!G5:G45))^4-1 -> 0.18826807 | O65: =-NPV('B Supuestos'!$B$14,'Flujos escenarios B'!F6:F45) -> 4.4872095e+08 | P65: =-NPV('B Supuestos'!$B$14,'Flujos escenarios B'!G6:G45) -> 4.4586247e+08
A66: Favorable – t | B66: =INDEX('Trayectorias B'!$C$5:$I$45,25,4) -> 3590.8697 | C66: =INDEX('Trayectorias B'!$C$5:$I$45,41,4) -> 2741.3926 | D66: =C66/B66-1 -> -0.23656582 | E66: =-SUM('Flujos escenarios B'!H6:H45) -> 6.8476828e+08 | F66: =-SUM('Flujos escenarios B'!I6:I45) -> 7.1402463e+08 | G66: =E66-F66 -> -29256352 | H66: =-SUM('Flujos escenarios B'!H30:H45) -> 2.6217032e+08 | I66: =-SUM('Flujos escenarios B'!I30:I45) -> 2.9142668e+08 | J66: =SUMIF('B.2 Escenarios'!$A$5:$A$32,A66,'B.2 Escenarios'!$L$5:$L$32) -> 2.8848808e+08 | K66: =H66/J66-1 -> -0.091226501 | L66: =I66/J66-1 -> 0.010186186 | M66: =(1+IRR('Flujos escenarios B'!H5:H45))^4-1 -> 0.15228112 | N66: =(1+IRR('Flujos escenarios B'!I5:I45))^4-1 -> 0.15924786 | O66: =-NPV('B Supuestos'!$B$14,'Flujos escenarios B'!H6:H45) -> 3.8981641e+08 | P66: =-NPV('B Supuestos'!$B$14,'Flujos escenarios B'!I6:I45) -> 4.0035533e+08
A67: Central – t | B67: =INDEX('Trayectorias B'!$C$5:$I$45,25,5) -> 3784.6602 | C67: =INDEX('Trayectorias B'!$C$5:$I$45,41,5) -> 4141.8056 | D67: =C67/B67-1 -> 0.094366592 | E67: =-SUM('Flujos escenarios B'!J6:J45) -> 7.9012434e+08 | F67: =-SUM('Flujos escenarios B'!K6:K45) -> 8.0656821e+08 | G67: =E67-F67 -> -16443864 | H67: =-SUM('Flujos escenarios B'!J30:J45) -> 3.6159128e+08 | I67: =-SUM('Flujos escenarios B'!K30:K45) -> 3.7803514e+08 | J67: =SUMIF('B.2 Escenarios'!$A$5:$A$32,A67,'B.2 Escenarios'!$L$5:$L$32) -> 3.8919977e+08 | K67: =H67/J67-1 -> -0.070936568 | L67: =I67/J67-1 -> -0.028686122 | M67: =(1+IRR('Flujos escenarios B'!J5:J45))^4-1 -> 0.17682756 | N67: =(1+IRR('Flujos escenarios B'!K5:K45))^4-1 -> 0.17907178 | O67: =-NPV('B Supuestos'!$B$14,'Flujos escenarios B'!J6:J45) -> 4.2925275e+08 | P67: =-NPV('B Supuestos'!$B$14,'Flujos escenarios B'!K6:K45) -> 4.3376055e+08
A68: Adverso – t | B68: =INDEX('Trayectorias B'!$C$5:$I$45,25,6) -> 3691.5684 | C68: =INDEX('Trayectorias B'!$C$5:$I$45,41,6) -> 5659.3115 | D68: =C68/B68-1 -> 0.53303714 | E68: =-SUM('Flujos escenarios B'!L6:L45) -> 8.2405804e+08 | F68: =-SUM('Flujos escenarios B'!M6:M45) -> 8.168261e+08 | G68: =E68-F68 -> 7231939.3 | H68: =-SUM('Flujos escenarios B'!L30:L45) -> 4.0233054e+08 | I68: =-SUM('Flujos escenarios B'!M30:M45) -> 3.950986e+08 | J68: =SUMIF('B.2 Escenarios'!$A$5:$A$32,A68,'B.2 Escenarios'!$L$5:$L$32) -> 4.0688184e+08 | K68: =H68/J68-1 -> -0.011185803 | L68: =I68/J68-1 -> -0.028959856 | M68: =(1+IRR('Flujos escenarios B'!L5:L45))^4-1 -> 0.18074058 | N68: =(1+IRR('Flujos escenarios B'!M5:M45))^4-1 -> 0.17892737 | O68: =-NPV('B Supuestos'!$B$14,'Flujos escenarios B'!L6:L45) -> 4.3785373e+08 | P68: =-NPV('B Supuestos'!$B$14,'Flujos escenarios B'!M6:M45) -> 4.3466179e+08
A69: Base A.1 (mediana) | B69: =INDEX('Trayectorias B'!$C$5:$I$45,25,7) -> 3708.3529 | C69: =INDEX('Trayectorias B'!$C$5:$I$45,41,7) -> 4000.7861 | D69: =C69/B69-1 -> 0.07885799 | E69: =-SUM('Flujos escenarios B'!N6:N45) -> 7.4500029e+08 | F69: =-SUM('Flujos escenarios B'!O6:O45) -> 7.5950104e+08 | G69: =E69-F69 -> -14500749 | H69: =-SUM('Flujos escenarios B'!N30:N45) -> 3.1550275e+08 | I69: =-SUM('Flujos escenarios B'!O30:O45) -> 3.300035e+08 | J69: =SUMIF('B.2 Escenarios'!$A$5:$A$32,A69,'B.2 Escenarios'!$L$5:$L$32) -> 3.3708571e+08 | K69: =H69/J69-1 -> -0.064028108 | L69: =I69/J69-1 -> -0.021010118 | M69: =(1+IRR('Flujos escenarios B'!N5:N45))^4-1 -> 0.16939587 | N69: =(1+IRR('Flujos escenarios B'!O5:O45))^4-1 -> 0.17248706 | O69: =-NPV('B Supuestos'!$B$14,'Flujos escenarios B'!N6:N45) -> 4.1510248e+08 | P69: =-NPV('B Supuestos'!$B$14,'Flujos escenarios B'!O6:O45) -> 4.2026681e+08

Sheet B.3 Evaluación
A1: B.3 Evaluación financiera de la estrategia de cobertura
A2: Valores de cobertura_forward.py (20.000 caminos por distribución). «Rodante» = estrategia del enunciado: cuatro forwards de 1 año, cada uno pactado al cierre del año anterior. «Strip» = variante de comparación: los cuatro precios se fijan al final del año 6 (plazos de 1 a 4 años).
A4: Indicador | B4: Normal – sin cobertura | C4: Normal – rodante | D4: Normal – strip | E4: t (ν = 8,9) – sin cobertura | F4: t (ν = 8,9) – rodante | G4: t (ν = 8,9) – strip
A5: Costo total de las 40 cuotas: media | B5: 7.7827053e+08 | C5: 7.9157563e+08 | D5: 8.1394126e+08 | E5: 7.7803574e+08 | F5: 7.9108222e+08 | G5: 8.1295388e+08
A6: Costo total: desviación estándar | B6: 1.8293749e+08 | C6: 1.8336519e+08 | D6: 1.8479496e+08 | E6: 1.8323305e+08 | F6: 1.8342485e+08 | G6: 1.8491284e+08
A7: Costo total: percentil 95 | B7: 1.1159474e+09 | C7: 1.1275482e+09 | D7: 1.1541249e+09 | E7: 1.1120055e+09 | F7: 1.1258016e+09 | G7: 1.148852e+09
A8: Costo total: percentil 99 | B8: 1.3194887e+09 | C8: 1.3345086e+09 | D8: 1.3569463e+09 | E8: 1.3254744e+09 | F8: 1.3382467e+09 | G8: 1.3592132e+09
A9: Costo total: CVaR 95 % (media del peor 5 %) | B9: 1.2444016e+09 | C9: 1.2575252e+09 | D9: 1.2810396e+09 | E9: 1.2457024e+09 | F9: 1.2571908e+09 | G9: 1.2806161e+09
A10: Cuotas de los años 7-10: media | B10: 3.3748765e+08 | C10: 3.5079275e+08 | D10: 3.7315837e+08 | E10: 3.381086e+08 | F10: 3.5115508e+08 | G10: 3.7302674e+08
A11: Cuotas de los años 7-10: desviación estándar | B11: 1.1964768e+08 | C11: 1.1808091e+08 | D11: 1.1676743e+08 | E11: 1.2010858e+08 | F11: 1.1823706e+08 | G11: 1.1681067e+08
A12: Cuotas de los años 7-10: CVaR 95 % | B12: 6.513458e+08 | C12: 6.5848904e+08 | D12: 6.7409318e+08 | E12: 6.5515362e+08 | F12: 6.6086905e+08 | G12: 6.7520809e+08
A13: Visto desde el año 6: sobrecosto medio frente a la TRM del año 6 | B13: 0.059629332 | C13: 0.10139634 | D13: 0.171849 | E13: 0.062298064 | F13: 0.10331872 | G13: 0.17204983
A14: Visto desde el año 6: desviación estándar del sobrecosto | B14: 0.17031746 | C14: 0.13195078 | D14: 0.032158914 | E14: 0.17375676 | F14: 0.13496989 | G14: 0.032894314
A15: Visto desde el año 6: sobrecosto P95 | B15: 0.35953889 | C15: 0.33316493 | D15: 0.22820105 | E15: 0.3736989 | F15: 0.34483402 | G15: 0.23015059
A16: Visto desde el año 6: sobrecosto P99 | B16: 0.52750899 | C16: 0.45958379 | D16: 0.2590483 | E16: 0.54084651 | F16: 0.47331585 | G16: 0.26210396
... A19: VPN de las cuotas al 13 % EA: media | B19: 4.2999789e+08 | C19: 4.3473525e+08 | D19: 4.4189101e+08 | E19: 4.2963558e+08 | F19: 4.3427866e+08 | G19: 4.4127549e+08
A21: Indicador de la cobertura | B21: Normal | C21: t (ν = 8,9) | D21: t de estrés (ν = 4)
A22: Resultado acumulado de los 4 forwards: media (COP) | B22: -13305098 | C22: -13046479 | D22: -13187606
A23: Resultado acumulado de los 4 forwards: P5 (COP) | B23: -39419323 | C23: -38986088 | D23: -39048512
A24: Resultado acumulado de los 4 forwards: P95 (COP) | B24: 14963554 | C24: 15428088 | D24: 15119397
A25: Prob. de que la cobertura rodante cueste más que no cubrir | B25: 0.817 | C25: 0.81295 | D25: 0.8242
A26: Strip: resultado acumulado de los 4 forwards, media (COP) | B26: -35670721 | C26: -34918140 | D26: -35164240
A27: Strip: prob. de que cueste más que no cubrir | B27: 0.79385 | C27: 0.78795 | D27: 0.8014
A28: Desv. estándar de la desviación anual vs presupuesto – sin cobertura | B28: 0.084979898 | C28: 0.085483824 | D28: 0.085830856
A29: Desv. estándar de la desviación anual vs presupuesto – con cobertura | B29: 0.038234714 | C29: 0.038241885 | D29: 0.040591342
A30: Fracaso de la cobertura (costo cubierto > presupuesto + 10 %) | B30: 0.000725 | C30: 0.001325 | D30: 0.003525
A31: Sin cobertura: costo > presupuesto + 10 % | B31: 0.0381 | C31: 0.0396625 | D31: 0.0365875
A33: Sensibilidad a las tasas de interés (innovaciones normales; mismas trayectorias de la TRM)
A34: i_COP | B34: i_USD | C34: Prima forward | D34: Prob. protección | E34: Resultado medio de los forwards (COP) | F34: Prob. de que la cobertura cueste más | G34: Costo total medio con cobertura (COP) | H34: Resultado medio del strip (COP) | I34: Fracaso de la cobertura
A35: 0.06 | B35: 0.03 | C35: 0.029126214 | D35: 0.4680625 | E35: -356466.23 | F35: 0.5611 | G35: 7.78627e+08 | H35: -1017724.6 | I35: 0.0027625
A36: 0.06 | B36: 0.0447 | C36: 0.014645353 | D36: 0.5118 | E36: 3246413.1 | F36: 0.4764 | G36: 7.7502412e+08 | H36: 8012536.9 | I36: 0.0038625
A37: 0.06 | B37: 0.06 | C37: 0 | D37: 0.557 | E37: 6890218.4 | F37: 0.38795 | G37: 7.7138032e+08 | H37: 16885097 | I37: 0.005775
A38: 0.08 | B38: 0.03 | C38: 0.048543689 | D38: 0.41345 | E38: -5187589.3 | F38: 0.67 | G38: 7.8345812e+08 | H38: -13537802 | I38: 0.0015875
A39: 0.08 | B39: 0.0447 | C39: 0.033789605 | D39: 0.4551375 | E39: -1516731.2 | F39: 0.58875 | G39: 7.7978727e+08 | H39: -3981203.4 | I39: 0.0023875
A40: 0.08 | B40: 0.06 | C40: 0.018867925 | D40: 0.4993375 | E40: 2195825.2 | F40: 0.50005 | G40: 7.7607471e+08 | H40: 5406019.7 | I40: 0.0034875
A41: 0.1 | B41: 0.03 | C41: 0.067961165 | D41: 0.36015 | E41: -10018712 | F41: 0.76355 | G41: 7.8828925e+08 | H41: -26541513 | I41: 0.000975
A42: 0.1 | B42: 0.0447 | C42: 0.052933857 | D42: 0.4009625 | E42: -6279875.4 | F42: 0.6924 | G42: 7.8455041e+08 | H42: -16435058 | I42: 0.0014375
A43: 0.1 | B43: 0.06 | C43: 0.037735849 | D43: 0.4443375 | E43: -2498568 | F43: 0.61115 | G43: 7.807691e+08 | H43: -6510270.5 | I43: 0.002125
A44: 0.1225 | B44: 0.03 | C44: 0.089805825 | D44: 0.3038 | E44: -15453726 | F44: 0.84585 | G44: 7.9372426e+08 | H44: -41765877 | I44: 0.0006
A45: 0.1225 | B45: 0.0447 | C45: 0.07447114 | D45: 0.3420875 | E45: -11638413 | F45: 0.7911 | G45: 7.8990895e+08 | H45: -31011823 | I45: 0.000875
A46: 0.1225 | B46: 0.06 | C46: 0.058962264 | D46: 0.384575 | E46: -7779760.3 | F46: 0.72025 | G46: 7.8605029e+08 | H46: -20454028 | I46: 0.0012375
... A52: 0.14 | B52: 0.06 | C52: 0.075471698 | D52: 0.3394875 | E52: -11887354 | F52: 0.7962 | G52: 7.9015789e+08 | H52: -31703882 | I52: 0.000825

Sheet Trayectorias TRM
A1: Trayectorias trimestrales de la TRM usadas en el punto A.3 (COP por USD)
A2: Fuente: simulacion_trm.py (20.000 trayectorias, semilla 42). Año 1 anclado a los escenarios del análisis fundamental; años 2 a 10 con deriva y volatilidad históricas de la ventana de flotación libre (1999–2026). Escenarios = camino mediano de cada uno.
A4: Trimestre | B4: Fecha | C4: TRM spot constante | D4: Escenario base | E4: Escenario peso fuerte | F4: Escenario peso débil | G4: Simulación P5 | H4: Simulación P25 | I4: Simulación P50 | J4: Simulación P75 | K4: Simulación P95 | L4: Simulación media
A5: 0 | B5: 46313 | C5: =Supuestos!$B$8 -> 3174.67 | D5: 3174.67 | E5: 3174.67 | F5: 3174.67 | G5: 3174.67 | H5: 3174.67 | I5: 3174.67 | J5: 3174.67 | K5: 3174.67 | L5: 3174.67
A6: 1 | B6: 46405 | C6: =Supuestos!$B$8 -> 3174.67 | D6: 3223.0561 | E6: 3161.5461 | F6: 3297.3536 | G6: 2991.0053 | H6: 3126.9376 | I6: 3227.0934 | J6: 3330.1246 | K6: 3483.0953 | L6: 3230.9162
A7: 2 | B7: 46495 | C7: =Supuestos!$B$8 -> 3174.67 | D7: 3272.1797 | E7: 3148.4764 | F7: 3424.7783 | G7: 2967.1171 | H7: 3145.1168 | I7: 3277.6777 | J7: 3417.2693 | K7: 3628.0824 | L7: 3285.2934
A8: 3 | B8: 46586 | C8: =Supuestos!$B$8 -> 3174.67 | D8: 3322.052 | E8: 3135.4608 | F8: 3557.1272 | G8: 2988.5981 | H8: 3178.3872 | I8: 3324.96 | J8: 3484.9085 | K8: 3734.6827 | L8: 3338.7116
A9: 4 | B9: 46678 | C9: =Supuestos!$B$8 -> 3174.67 | D9: 3372.6844 | E9: 3122.499 | F9: 3694.5906 | G9: 3038.6446 | H9: 3228.2458 | I9: 3370.8974 | J9: 3523.3701 | K9: 3831.2098 | L9: 3392.0318
A10: 5 | B10: 46770 | C10: =Supuestos!$B$8 -> 3174.67 | D10: 3388.7222 | E10: 3137.3471 | F10: 3712.1592 | G10: 2915.3203 | H10: 3187.0272 | I10: 3392.7645 | J10: 3621.9184 | K10: 3998.4099 | L10: 3416.1922
A11: 6 | B11: 46861 | C11: =Supuestos!$B$8 -> 3174.67 | D11: 3404.8363 | E11: 3152.2659 | F11: 3729.8113 | G11: 2830.7808 | H11: 3157.849 | I11: 3409.2972 | J11: 3691.3358 | K11: 4145.354 | L11: 3439.3702
A12: 7 | B12: 46952 | C12: =Supuestos!$B$8 -> 3174.67 | D12: 3421.027 | E12: 3167.2556 | F12: 3747.5473 | G12: 2758.3064 | H12: 3143.7334 | I12: 3432.2675 | J12: 3761.7339 | K12: 4295.6114 | L12: 3467.5269
A13: 8 | B13: 47044 | C13: =Supuestos!$B$8 -> 3174.67 | D13: 3437.2947 | E13: 3182.3166 | F13: 3765.3677 | G13: 2701.08 | H13: 3120.8648 | I13: 3452.0019 | J13: 3812.4873 | K13: 4417.4805 | L13: 3490.4169
A14: 9 | B14: 47136 | C14: =Supuestos!$B$8 -> 3174.67 | D14: 3453.6398 | E14: 3197.4491 | F14: 3783.2729 | G14: 2656.6077 | H14: 3107.7612 | I14: 3468.9227 | J14: 3867.3321 | K14: 4530.6984 | L14: 3514.8308
A15: 10 | B15: 47226 | C15: =Supuestos!$B$8 -> 3174.67 | D15: 3470.0626 | E15: 3212.6537 | F15: 3801.2631 | G15: 2613.4108 | H15: 3092.4521 | I15: 3487.2874 | J15: 3921.9839 | K15: 4665.201 | L15: 3540.7469
A16: 11 | B16: 47317 | C16: =Supuestos!$B$8 -> 3174.67 | D16: 3486.5635 | E16: 3227.9305 | F16: 3819.3389 | G16: 2574.2579 | H16: 3088.6581 | I16: 3498.0912 | J16: 3969.4717 | K16: 4778.1324 | L16: 3564.7381
... A45: 40 | B45: 49966 | C45: =Supuestos!$B$8 -> 3174.67 | D45: 4000.7861 | E45: 3704.0082 | F45: 4382.6416 | G45: 2076.1783 | H45: 3057.7228 | I45: 4017.1538 | J45: 5256.3784 | K45: 7779.685 | L45: 4347.2656

Sheet Trayectorias B
A1: Trayectorias de la TRM para los escenarios de la parte B (COP por USD)
A4: Trimestre | B4: Fecha | C4: Favorable – Normal | D4: Central – Normal | E4: Adverso – Normal | F4: Favorable – t | G4: Central – t | H4: Adverso – t | I4: Base A.1 (mediana)
A5: 0 | B5: ='Trayectorias TRM'!B5 -> 46313 | C5: 3174.67 | D5: 3174.67 | E5: 3174.67 | F5: 3174.67 | G5: 3174.67 | H5: 3174.67 | I5: ='Trayectorias TRM'!D5 -> 3174.67
A6: 1 | B6: ='Trayectorias TRM'!B6 -> 46405 | C6: 3095.4506 | D6: 3631.1782 | E6: 3430.813 | F6: 2954.5628 | G6: 3141.8404 | H6: 3313.4482 | I6: ='Trayectorias TRM'!D6 -> 3223.0561
A7: 2 | B7: ='Trayectorias TRM'!B7 -> 46495 | C7: 3131.0968 | D7: 3900.2509 | E7: 3496.9951 | F7: 3009.9807 | G7: 3279.3947 | H7: 3089.4189 | I7: ='Trayectorias TRM'!D7 -> 3272.1797
A8: 3 | B8: ='Trayectorias TRM'!B8 -> 46586 | C8: 3474.9484 | D8: 3706.7001 | E8: 3890.0762 | F8: 3101.5505 | G8: 3200.8404 | H8: 2972.6619 | I8: ='Trayectorias TRM'!D8 -> 3322.052
A9: 4 | B9: ='Trayectorias TRM'!B9 -> 46678 | C9: 3384.2465 | D9: 3594.9326 | E9: 3876.2441 | F9: 3171.8953 | G9: 3256.7808 | H9: 3061.5915 | I9: ='Trayectorias TRM'!D9 -> 3372.6844
A10: 5 | B10: ='Trayectorias TRM'!B10 -> 46770 | C10: 3358.1771 | D10: 3470.9255 | E10: 3889.8843 | F10: 3504.2311 | G10: 3228.1761 | H10: 3253.1521 | I10: ='Trayectorias TRM'!D10 -> 3388.7222
A11: 6 | B11: ='Trayectorias TRM'!B11 -> 46861 | C11: 3429.9947 | D11: 3226.1468 | E11: 4038.1503 | F11: 3178.579 | G11: 3128.6616 | H11: 3326.6631 | I11: ='Trayectorias TRM'!D11 -> 3404.8363
A12: 7 | B12: ='Trayectorias TRM'!B12 -> 46952 | C12: 3227.5306 | D12: 3390.1106 | E12: 3707.3104 | F12: 3164.5227 | G12: 3147.3898 | H12: 3250.0105 | I12: ='Trayectorias TRM'!D12 -> 3421.027
A13: 8 | B13: ='Trayectorias TRM'!B13 -> 47044 | C13: 3052.944 | D13: 3289.9541 | E13: 3166.6371 | F13: 3394.0172 | G13: 3081.2016 | H13: 3323.9066 | I13: ='Trayectorias TRM'!D13 -> 3437.2947
A14: 9 | B14: ='Trayectorias TRM'!B14 -> 47136 | C14: 2995.0094 | D14: 3263.5351 | E14: 3183.3013 | F14: 3417.4865 | G14: 3209.0488 | H14: 3234.0764 | I14: ='Trayectorias TRM'!D14 -> 3453.6398
A15: 10 | B15: ='Trayectorias TRM'!B15 -> 47226 | C15: 2927.1418 | D15: 3466.0194 | E15: 3756.3847 | F15: 3447.7535 | G15: 3099.8244 | H15: 3366.009 | I15: ='Trayectorias TRM'!D15 -> 3470.0626
A16: 11 | B16: ='Trayectorias TRM'!B16 -> 47317 | C16: 2736.9914 | D16: 3381.85 | E16: 3400.4933 | F16: 3761.2281 | G16: 3325.411 | H16: 3354.7078 | I16: ='Trayectorias TRM'!D16 -> 3486.5635
... A45: 40 | B45: ='Trayectorias TRM'!B45 -> 49966 | C45: 2915.2257 | D45: 3994.0644 | E45: 5759.8568 | F45: 2741.3926 | G45: 4141.8056 | H45: 5659.3115 | I45: ='Trayectorias TRM'!D45 -> 4000.7861

Sheet Flujos escenarios B
A1: Flujos del crédito en pesos por escenario (auxiliar para la hoja B.3)
A2: Trimestre 0 = desembolso recibido (+); trimestres 1-40 = cuotas pagadas (−) y, con cobertura, liquidación de los NDF al vencimiento.
A4: Trimestre | B4: Favorable – Normal – sin cobertura | C4: Favorable – Normal – con cobertura | D4: Central – Normal – sin cobertura | E4: Central – Normal – con cobertura | F4: Adverso – Normal – sin cobertura | G4: Adverso – Normal – con cobertura | H4: Favorable – t – sin cobertura | I4: Favorable – t – con cobertura | J4: Central – t – sin cobertura | K4: Central – t – con cobertura | L4: Adverso – t – sin cobertura | M4: Adverso – t – con cobertura | N4: Base A.1 (mediana) – sin cobertura | O4: Base A.1 (mediana) – con cobertura
A5: 0 | B5: =Supuestos!$B$7 -> 360000000 | C5: =Supuestos!$B$7 -> 360000000 | D5: =Supuestos!$B$7 -> 360000000 | E5: =Supuestos!$B$7 -> 360000000 | F5: =Supuestos!$B$7 -> 360000000 | G5: =Supuestos!$B$7 -> 360000000 | H5: =Supuestos!$B$7 -> 360000000 | I5: =Supuestos!$B$7 -> 360000000 | ... O5: =Supuestos!$B$7 -> 360000000
A6: 1 | B6: =-'B Supuestos'!$B$6*INDEX('Trayectorias B'!$C$5:$I$45,2,1) -> -15805559 | C6: =B6+IF(ISNUMBER(MATCH(1,'B Supuestos'!$D$20:$D$23,0)),INDEX('B Supuestos'!$F$20:$F$23,MATCH(1,'B Supuestos'!$D$20:$D$23,0))*(INDEX('Trayectorias B'!$C$5:$I$45,2,1)-INDEX('Trayectorias B'!$C$5:$I$45,1,1)*(1+'B Supuestos'!$B$12)),0) -> -15805559 | D6: =-'B Supuestos'!$B$6*INDEX('Trayectorias B'!$C$5:$I$45,2,2) -> -18541017 | E6: =D6+IF(ISNUMBER(MATCH(1,'B Supuestos'!$D$20:$D$23,0)),INDEX('B Supuestos'!$F$20:$F$23,MATCH(1,'B Supuestos'!$D$20:$D$23,0))*(INDEX('Trayectorias B'!$C$5:$I$45,2,2)-INDEX('Trayectorias B'!$C$5:$I$45,1,2)*(1+'B Supuestos'!$B$12)),0) -> -18541017 | F6: =-'B Supuestos'!$B$6*INDEX('Trayectorias B'!$C$5:$I$45,2,3) -> -17517940 | G6: =F6+IF(ISNUMBER(MATCH(1,'B Supuestos'!$D$20:$D$23,0)),INDEX('B Supuestos'!$F$20:$F$23,MATCH(1,'B Supuestos'!$D$20:$D$23,0))*(INDEX('Trayectorias B'!$C$5:$I$45,2,3)-INDEX('Trayectorias B'!$C$5:$I$45,1,3)*(1+'B Supuestos'!$B$12)),0) -> -17517940 | H6: =-'B Supuestos'!$B$6*INDEX('Trayectorias B'!$C$5:$I$45,2,4) -> -15086178 | I6: =H6+IF(ISNUMBER(MATCH(1,'B Supuestos'!$D$20:$D$23,0)),INDEX('B Supuestos'!$F$20:$F$23,MATCH(1,'B Supuestos'!$D$20:$D$23,0))*(INDEX('Trayectorias B'!$C$5:$I$45,2,4)-INDEX('Trayectorias B'!$C$5:$I$45,1,4)*(1+'B Supuestos'!$B$12)),0) -> -15086178 | J6: =-'B Supuestos'!$B$6*INDEX('Trayectorias B'!$C$5:$I$45,2,5) -> -16042429 | K6: =J6+IF(ISNUMBER(MATCH(1,'B Supuestos'!$D$20:$D$23,0)),INDEX('B Supuestos'!$F$20:$F$23,MATCH(1,'B Supuestos'!$D$20:$D$23,0))*(INDEX('Trayectorias B'!$C$5:$I$45,2,5)-INDEX('Trayectorias B'!$C$5:$I$45,1,5)*(1+'B Supuestos'!$B$12)),0) -> -16042429 | L6: =-'B Supuestos'!$B$6*INDEX('Trayectorias B'!$C$5:$I$45,2,6) -> -16918668 | M6: =L6+IF(ISNUMBER(MATCH(1,'B Supuestos'!$D$20:$D$23,0)),INDEX('B Supuestos'!$F$20:$F$23,MATCH(1,'B Supuestos'!$D$20:$D$23,0))*(INDEX('Trayectorias B'!$C$5:$I$45,2,6)-INDEX('Trayectorias B'!$C$5:$I$45,1,6)*(1+'B Supuestos'!$B$12)),0) -> -16918668 | N6: =-'B Supuestos'!$B$6*INDEX('Trayectorias B'!$C$5:$I$45,2,7) -> -16457121 | O6: =N6+IF(ISNUMBER(MATCH(1,'B Supuestos'!$D$20:$D$23,0)),INDEX('B Supuestos'!$F$20:$F$23,MATCH(1,'B Supuestos'!$D$20:$D$23,0))*(INDEX('Trayectorias B'!$C$5:$I$45,2,7)-INDEX('Trayectorias B'!$C$5:$I$45,1,7)*(1+'B Supuestos'!$B$12)),0) -> -16457121
A7: 2 | B7: =-'B Supuestos'!$B$6*INDEX('Trayectorias B'!$C$5:$I$45,3,1) -> -15987571 | C7: =B7+IF(ISNUMBER(MATCH(2,'B Supuestos'!$D$20:$D$23,0)),INDEX('B Supuestos'!$F$20:$F$23,MATCH(2,'B Supuestos'!$D$20:$D$23,0))*(INDEX('Trayectorias B'!$C$5:$I$45,3,1)-INDEX('Trayectorias B'!$C$5:$I$45,1,1)*(1+'B Supuestos'!$B$12)),0) -> -15987571 | D7: =-'B Supuestos'!$B$6*INDEX('Trayectorias B'!$C$5:$I$45,3,2) -> -19914919 | E7: =D7+IF(ISNUMBER(MATCH(2,'B Supuestos'!$D$20:$D$23,0)),INDEX('B Supuestos'!$F$20:$F$23,MATCH(2,'B Supuestos'!$D$20:$D$23,0))*(INDEX('Trayectorias B'!$C$5:$I$45,3,2)-INDEX('Trayectorias B'!$C$5:$I$45,1,2)*(1+'B Supuestos'!$B$12)),0) -> -19914919 | F7: =-'B Supuestos'!$B$6*INDEX('Trayectorias B'!$C$5:$I$45,3,3) -> -17855870 | G7: =F7+IF(ISNUMBER(MATCH(2,'B Supuestos'!$D$20:$D$23,0)),INDEX('B Supuestos'!$F$20:$F$23,MATCH(2,'B Supuestos'!$D$20:$D$23,0))*(INDEX('Trayectorias B'!$C$5:$I$45,3,3)-INDEX('Trayectorias B'!$C$5:$I$45,1,3)*(1+'B Supuestos'!$B$12)),0) -> -17855870 | H7: =-'B Supuestos'!$B$6*INDEX('Trayectorias B'!$C$5:$I$45,3,4) -> -15369145 | I7: =H7+IF(ISNUMBER(MATCH(2,'B Supuestos'!$D$20:$D$23,0)),INDEX('B Supuestos'!$F$20:$F$23,MATCH(2,'B Supuestos'!$D$20:$D$23,0))*(INDEX('Trayectorias B'!$C$5:$I$45,3,4)-INDEX('Trayectorias B'!$C$5:$I$45,1,4)*(1+'B Supuestos'!$B$12)),0) -> -15369145 | J7: =-'B Supuestos'!$B$6*INDEX('Trayectorias B'!$C$5:$I$45,3,5) -> -16744789 | K7: =J7+IF(ISNUMBER(MATCH(2,'B Supuestos'!$D$20:$D$23,0)),INDEX('B Supuestos'!$F$20:$F$23,MATCH(2,'B Supuestos'!$D$20:$D$23,0))*(INDEX('Trayectorias B'!$C$5:$I$45,3,5)-INDEX('Trayectorias B'!$C$5:$I$45,1,5)*(1+'B Supuestos'!$B$12)),0) -> -16744789 | L7: =-'B Supuestos'!$B$6*INDEX('Trayectorias B'!$C$5:$I$45,3,6) -> -15774761 | M7: =L7+IF(ISNUMBER(MATCH(2,'B Supuestos'!$D$20:$D$23,0)),INDEX('B Supuestos'!$F$20:$F$23,MATCH(2,'B Supuestos'!$D$20:$D$23,0))*(INDEX('Trayectorias B'!$C$5:$I$45,3,6)-INDEX('Trayectorias B'!$C$5:$I$45,1,6)*(1+'B Supuestos'!$B$12)),0) -> -15774761 | N7: =-'B Supuestos'!$B$6*INDEX('Trayectorias B'!$C$5:$I$45,3,7) -> -16707949 | O7: =N7+IF(ISNUMBER(MATCH(2,'B Supuestos'!$D$20:$D$23,0)),INDEX('B Supuestos'!$F$20:$F$23,MATCH(2,'B Supuestos'!$D$20:$D$23,0))*(INDEX('Trayectorias B'!$C$5:$I$45,3,7)-INDEX('Trayectorias B'!$C$5:$I$45,1,7)*(1+'B Supuestos'!$B$12)),0) -> -16707949
A8: 3 | B8: =-'B Supuestos'!$B$6*INDEX('Trayectorias B'!$C$5:$I$45,4,1) -> -17743298 | C8: =B8+IF(ISNUMBER(MATCH(3,'B Supuestos'!$D$20:$D$23,0)),INDEX('B Supuestos'!$F$20:$F$23,MATCH(3,'B Supuestos'!$D$20:$D$23,0))*(INDEX('Trayectorias B'!$C$5:$I$45,4,1)-INDEX('Trayectorias B'!$C$5:$I$45,1,1)*(1+'B Supuestos'!$B$12)),0) -> -17743298 | D8: =-'B Supuestos'!$B$6*INDEX('Trayectorias B'!$C$5:$I$45,4,2) -> -18926636 | E8: =D8+IF(ISNUMBER(MATCH(3,'B Supuestos'!$D$20:$D$23,0)),INDEX('B Supuestos'!$F$20:$F$23,MATCH(3,'B Supuestos'!$D$20:$D$23,0))*(INDEX('Trayectorias B'!$C$5:$I$45,4,2)-INDEX('Trayectorias B'!$C$5:$I$45,1,2)*(1+'B Supuestos'!$B$12)),0) -> -18926636 | F8: =-'B Supuestos'!$B$6*INDEX('Trayectorias B'!$C$5:$I$45,4,3) -> -19862966 | G8: =F8+IF(ISNUMBER(MATCH(3,'B Supuestos'!$D$20:$D$23,0)),INDEX('B Supuestos'!$F$20:$F$23,MATCH(3,'B Supuestos'!$D$20:$D$23,0))*(INDEX('Trayectorias B'!$C$5:$I$45,4,3)-INDEX('Trayectorias B'!$C$5:$I$45,1,3)*(1+'B Supuestos'!$B$12)),0) -> -19862966 | H8: =-'B Supuestos'!$B$6*INDEX('Trayectorias B'!$C$5:$I$45,4,4) -> -15836706 | I8: =H8+IF(ISNUMBER(MATCH(3,'B Supuestos'!$D$20:$D$23,0)),INDEX('B Supuestos'!$F$20:$F$23,MATCH(3,'B Supuestos'!$D$20:$D$23,0))*(INDEX('Trayectorias B'!$C$5:$I$45,4,4)-INDEX('Trayectorias B'!$C$5:$I$45,1,4)*(1+'B Supuestos'!$B$12)),0) -> -15836706 | J8: =-'B Supuestos'!$B$6*INDEX('Trayectorias B'!$C$5:$I$45,4,5) -> -16343686 | K8: =J8+IF(ISNUMBER(MATCH(3,'B Supuestos'!$D$20:$D$23,0)),INDEX('B Supuestos'!$F$20:$F$23,MATCH(3,'B Supuestos'!$D$20:$D$23,0))*(INDEX('Trayectorias B'!$C$5:$I$45,4,5)-INDEX('Trayectorias B'!$C$5:$I$45,1,5)*(1+'B Supuestos'!$B$12)),0) -> -16343686 | L8: =-'B Supuestos'!$B$6*INDEX('Trayectorias B'!$C$5:$I$45,4,6) -> -15178593 | M8: =L8+IF(ISNUMBER(MATCH(3,'B Supuestos'!$D$20:$D$23,0)),INDEX('B Supuestos'!$F$20:$F$23,MATCH(3,'B Supuestos'!$D$20:$D$23,0))*(INDEX('Trayectorias B'!$C$5:$I$45,4,6)-INDEX('Trayectorias B'!$C$5:$I$45,1,6)*(1+'B Supuestos'!$B$12)),0) -> -15178593 | N8: =-'B Supuestos'!$B$6*INDEX('Trayectorias B'!$C$5:$I$45,4,7) -> -16962600 | O8: =N8+IF(ISNUMBER(MATCH(3,'B Supuestos'!$D$20:$D$23,0)),INDEX('B Supuestos'!$F$20:$F$23,MATCH(3,'B Supuestos'!$D$20:$D$23,0))*(INDEX('Trayectorias B'!$C$5:$I$45,4,7)-INDEX('Trayectorias B'!$C$5:$I$45,1,7)*(1+'B Supuestos'!$B$12)),0) -> -16962600
A9: 4 | B9: =-'B Supuestos'!$B$6*INDEX('Trayectorias B'!$C$5:$I$45,5,1) -> -17280169 | C9: =B9+IF(ISNUMBER(MATCH(4,'B Supuestos'!$D$20:$D$23,0)),INDEX('B Supuestos'!$F$20:$F$23,MATCH(4,'B Supuestos'!$D$20:$D$23,0))*(INDEX('Trayectorias B'!$C$5:$I$45,5,1)-INDEX('Trayectorias B'!$C$5:$I$45,1,1)*(1+'B Supuestos'!$B$12)),0) -> -17280169 | D9: =-'B Supuestos'!$B$6*INDEX('Trayectorias B'!$C$5:$I$45,5,2) -> -18355945 | E9: =D9+IF(ISNUMBER(MATCH(4,'B Supuestos'!$D$20:$D$23,0)),INDEX('B Supuestos'!$F$20:$F$23,MATCH(4,'B Supuestos'!$D$20:$D$23,0))*(INDEX('Trayectorias B'!$C$5:$I$45,5,2)-INDEX('Trayectorias B'!$C$5:$I$45,1,2)*(1+'B Supuestos'!$B$12)),0) -> -18355945 | F9: =-'B Supuestos'!$B$6*INDEX('Trayectorias B'!$C$5:$I$45,5,3) -> -19792339 | G9: =F9+IF(ISNUMBER(MATCH(4,'B Supuestos'!$D$20:$D$23,0)),INDEX('B Supuestos'!$F$20:$F$23,MATCH(4,'B Supuestos'!$D$20:$D$23,0))*(INDEX('Trayectorias B'!$C$5:$I$45,5,3)-INDEX('Trayectorias B'!$C$5:$I$45,1,3)*(1+'B Supuestos'!$B$12)),0) -> -19792339 | H9: =-'B Supuestos'!$B$6*INDEX('Trayectorias B'!$C$5:$I$45,5,4) -> -16195890 | I9: =H9+IF(ISNUMBER(MATCH(4,'B Supuestos'!$D$20:$D$23,0)),INDEX('B Supuestos'!$F$20:$F$23,MATCH(4,'B Supuestos'!$D$20:$D$23,0))*(INDEX('Trayectorias B'!$C$5:$I$45,5,4)-INDEX('Trayectorias B'!$C$5:$I$45,1,4)*(1+'B Supuestos'!$B$12)),0) -> -16195890 | J9: =-'B Supuestos'!$B$6*INDEX('Trayectorias B'!$C$5:$I$45,5,5) -> -16629321 | K9: =J9+IF(ISNUMBER(MATCH(4,'B Supuestos'!$D$20:$D$23,0)),INDEX('B Supuestos'!$F$20:$F$23,MATCH(4,'B Supuestos'!$D$20:$D$23,0))*(INDEX('Trayectorias B'!$C$5:$I$45,5,5)-INDEX('Trayectorias B'!$C$5:$I$45,1,5)*(1+'B Supuestos'!$B$12)),0) -> -16629321 | L9: =-'B Supuestos'!$B$6*INDEX('Trayectorias B'!$C$5:$I$45,5,6) -> -15632673 | M9: =L9+IF(ISNUMBER(MATCH(4,'B Supuestos'!$D$20:$D$23,0)),INDEX('B Supuestos'!$F$20:$F$23,MATCH(4,'B Supuestos'!$D$20:$D$23,0))*(INDEX('Trayectorias B'!$C$5:$I$45,5,6)-INDEX('Trayectorias B'!$C$5:$I$45,1,6)*(1+'B Supuestos'!$B$12)),0) -> -15632673 | N9: =-'B Supuestos'!$B$6*INDEX('Trayectorias B'!$C$5:$I$45,5,7) -> -17221132 | O9: =N9+IF(ISNUMBER(MATCH(4,'B Supuestos'!$D$20:$D$23,0)),INDEX('B Supuestos'!$F$20:$F$23,MATCH(4,'B Supuestos'!$D$20:$D$23,0))*(INDEX('Trayectorias B'!$C$5:$I$45,5,7)-INDEX('Trayectorias B'!$C$5:$I$45,1,7)*(1+'B Supuestos'!$B$12)),0) -> -17221132
A10: 5 | B10: =-'B Supuestos'!$B$6*INDEX('Trayectorias B'!$C$5:$I$45,6,1) -> -17147057 | C10: =B10+IF(ISNUMBER(MATCH(5,'B Supuestos'!$D$20:$D$23,0)),INDEX('B Supuestos'!$F$20:$F$23,MATCH(5,'B Supuestos'!$D$20:$D$23,0))*(INDEX('Trayectorias B'!$C$5:$I$45,6,1)-INDEX('Trayectorias B'!$C$5:$I$45,2,1)*(1+'B Supuestos'!$B$12)),0) -> -17147057 | D10: =-'B Supuestos'!$B$6*INDEX('Trayectorias B'!$C$5:$I$45,6,2) -> -17722757 | E10: =D10+IF(ISNUMBER(MATCH(5,'B Supuestos'!$D$20:$D$23,0)),INDEX('B Supuestos'!$F$20:$F$23,MATCH(5,'B Supuestos'!$D$20:$D$23,0))*(INDEX('Trayectorias B'!$C$5:$I$45,6,2)-INDEX('Trayectorias B'!$C$5:$I$45,2,2)*(1+'B Supuestos'!$B$12)),0) -> -17722757 | F10: =-'B Supuestos'!$B$6*INDEX('Trayectorias B'!$C$5:$I$45,6,3) -> -19861986 | G10: =F10+IF(ISNUMBER(MATCH(5,'B Supuestos'!$D$20:$D$23,0)),INDEX('B Supuestos'!$F$20:$F$23,MATCH(5,'B Supuestos'!$D$20:$D$23,0))*(INDEX('Trayectorias B'!$C$5:$I$45,6,3)-INDEX('Trayectorias B'!$C$5:$I$45,2,3)*(1+'B Supuestos'!$B$12)),0) -> -19861986 | H10: =-'B Supuestos'!$B$6*INDEX('Trayectorias B'!$C$5:$I$45,6,4) -> -17892817 | I10: =H10+IF(ISNUMBER(MATCH(5,'B Supuestos'!$D$20:$D$23,0)),INDEX('B Supuestos'!$F$20:$F$23,MATCH(5,'B Supuestos'!$D$20:$D$23,0))*(INDEX('Trayectorias B'!$C$5:$I$45,6,4)-INDEX('Trayectorias B'!$C$5:$I$45,2,4)*(1+'B Supuestos'!$B$12)),0) -> -17892817 | J10: =-'B Supuestos'!$B$6*INDEX('Trayectorias B'!$C$5:$I$45,6,5) -> -16483264 | K10: =J10+IF(ISNUMBER(MATCH(5,'B Supuestos'!$D$20:$D$23,0)),INDEX('B Supuestos'!$F$20:$F$23,MATCH(5,'B Supuestos'!$D$20:$D$23,0))*(INDEX('Trayectorias B'!$C$5:$I$45,6,5)-INDEX('Trayectorias B'!$C$5:$I$45,2,5)*(1+'B Supuestos'!$B$12)),0) -> -16483264 | L10: =-'B Supuestos'!$B$6*INDEX('Trayectorias B'!$C$5:$I$45,6,6) -> -16610793 | M10: =L10+IF(ISNUMBER(MATCH(5,'B Supuestos'!$D$20:$D$23,0)),INDEX('B Supuestos'!$F$20:$F$23,MATCH(5,'B Supuestos'!$D$20:$D$23,0))*(INDEX('Trayectorias B'!$C$5:$I$45,6,6)-INDEX('Trayectorias B'!$C$5:$I$45,2,6)*(1+'B Supuestos'!$B$12)),0) -> -16610793 | N10: =-'B Supuestos'!$B$6*INDEX('Trayectorias B'!$C$5:$I$45,6,7) -> -17303022 | O10: =N10+IF(ISNUMBER(MATCH(5,'B Supuestos'!$D$20:$D$23,0)),INDEX('B Supuestos'!$F$20:$F$23,MATCH(5,'B Supuestos'!$D$20:$D$23,0))*(INDEX('Trayectorias B'!$C$5:$I$45,6,7)-INDEX('Trayectorias B'!$C$5:$I$45,2,7)*(1+'B Supuestos'!$B$12)),0) -> -17303022
A11: 6 | B11: =-'B Supuestos'!$B$6*INDEX('Trayectorias B'!$C$5:$I$45,7,1) -> -17513762 | C11: =B11+IF(ISNUMBER(MATCH(6,'B Supuestos'!$D$20:$D$23,0)),INDEX('B Supuestos'!$F$20:$F$23,MATCH(6,'B Supuestos'!$D$20:$D$23,0))*(INDEX('Trayectorias B'!$C$5:$I$45,7,1)-INDEX('Trayectorias B'!$C$5:$I$45,3,1)*(1+'B Supuestos'!$B$12)),0) -> -17513762 | D11: =-'B Supuestos'!$B$6*INDEX('Trayectorias B'!$C$5:$I$45,7,2) -> -16472902 | E11: =D11+IF(ISNUMBER(MATCH(6,'B Supuestos'!$D$20:$D$23,0)),INDEX('B Supuestos'!$F$20:$F$23,MATCH(6,'B Supuestos'!$D$20:$D$23,0))*(INDEX('Trayectorias B'!$C$5:$I$45,7,2)-INDEX('Trayectorias B'!$C$5:$I$45,3,2)*(1+'B Supuestos'!$B$12)),0) -> -16472902 | F11: =-'B Supuestos'!$B$6*INDEX('Trayectorias B'!$C$5:$I$45,7,3) -> -20619042 | G11: =F11+IF(ISNUMBER(MATCH(6,'B Supuestos'!$D$20:$D$23,0)),INDEX('B Supuestos'!$F$20:$F$23,MATCH(6,'B Supuestos'!$D$20:$D$23,0))*(INDEX('Trayectorias B'!$C$5:$I$45,7,3)-INDEX('Trayectorias B'!$C$5:$I$45,3,3)*(1+'B Supuestos'!$B$12)),0) -> -20619042 | H11: =-'B Supuestos'!$B$6*INDEX('Trayectorias B'!$C$5:$I$45,7,4) -> -16230018 | I11: =H11+IF(ISNUMBER(MATCH(6,'B Supuestos'!$D$20:$D$23,0)),INDEX('B Supuestos'!$F$20:$F$23,MATCH(6,'B Supuestos'!$D$20:$D$23,0))*(INDEX('Trayectorias B'!$C$5:$I$45,7,4)-INDEX('Trayectorias B'!$C$5:$I$45,3,4)*(1+'B Supuestos'!$B$12)),0) -> -16230018 | J11: =-'B Supuestos'!$B$6*INDEX('Trayectorias B'!$C$5:$I$45,7,5) -> -15975137 | K11: =J11+IF(ISNUMBER(MATCH(6,'B Supuestos'!$D$20:$D$23,0)),INDEX('B Supuestos'!$F$20:$F$23,MATCH(6,'B Supuestos'!$D$20:$D$23,0))*(INDEX('Trayectorias B'!$C$5:$I$45,7,5)-INDEX('Trayectorias B'!$C$5:$I$45,3,5)*(1+'B Supuestos'!$B$12)),0) -> -15975137 | L11: =-'B Supuestos'!$B$6*INDEX('Trayectorias B'!$C$5:$I$45,7,6) -> -16986144 | M11: =L11+IF(ISNUMBER(MATCH(6,'B Supuestos'!$D$20:$D$23,0)),INDEX('B Supuestos'!$F$20:$F$23,MATCH(6,'B Supuestos'!$D$20:$D$23,0))*(INDEX('Trayectorias B'!$C$5:$I$45,7,6)-INDEX('Trayectorias B'!$C$5:$I$45,3,6)*(1+'B Supuestos'!$B$12)),0) -> -16986144 | N11: =-'B Supuestos'!$B$6*INDEX('Trayectorias B'!$C$5:$I$45,7,7) -> -17385302 | O11: =N11+IF(ISNUMBER(MATCH(6,'B Supuestos'!$D$20:$D$23,0)),INDEX('B Supuestos'!$F$20:$F$23,MATCH(6,'B Supuestos'!$D$20:$D$23,0))*(INDEX('Trayectorias B'!$C$5:$I$45,7,7)-INDEX('Trayectorias B'!$C$5:$I$45,3,7)*(1+'B Supuestos'!$B$12)),0) -> -17385302
A12: 7 | B12: =-'B Supuestos'!$B$6*INDEX('Trayectorias B'!$C$5:$I$45,8,1) -> -16479968 | C12: =B12+IF(ISNUMBER(MATCH(7,'B Supuestos'!$D$20:$D$23,0)),INDEX('B Supuestos'!$F$20:$F$23,MATCH(7,'B Supuestos'!$D$20:$D$23,0))*(INDEX('Trayectorias B'!$C$5:$I$45,8,1)-INDEX('Trayectorias B'!$C$5:$I$45,4,1)*(1+'B Supuestos'!$B$12)),0) -> -16479968 | D12: =-'B Supuestos'!$B$6*INDEX('Trayectorias B'!$C$5:$I$45,8,2) -> -17310111 | E12: =D12+IF(ISNUMBER(MATCH(7,'B Supuestos'!$D$20:$D$23,0)),INDEX('B Supuestos'!$F$20:$F$23,MATCH(7,'B Supuestos'!$D$20:$D$23,0))*(INDEX('Trayectorias B'!$C$5:$I$45,8,2)-INDEX('Trayectorias B'!$C$5:$I$45,4,2)*(1+'B Supuestos'!$B$12)),0) -> -17310111 | F12: =-'B Supuestos'!$B$6*INDEX('Trayectorias B'!$C$5:$I$45,8,3) -> -18929753 | G12: =F12+IF(ISNUMBER(MATCH(7,'B Supuestos'!$D$20:$D$23,0)),INDEX('B Supuestos'!$F$20:$F$23,MATCH(7,'B Supuestos'!$D$20:$D$23,0))*(INDEX('Trayectorias B'!$C$5:$I$45,8,3)-INDEX('Trayectorias B'!$C$5:$I$45,4,3)*(1+'B Supuestos'!$B$12)),0) -> -18929753 | H12: =-'B Supuestos'!$B$6*INDEX('Trayectorias B'!$C$5:$I$45,8,4) -> -16158246 | I12: =H12+IF(ISNUMBER(MATCH(7,'B Supuestos'!$D$20:$D$23,0)),INDEX('B Supuestos'!$F$20:$F$23,MATCH(7,'B Supuestos'!$D$20:$D$23,0))*(INDEX('Trayectorias B'!$C$5:$I$45,8,4)-INDEX('Trayectorias B'!$C$5:$I$45,4,4)*(1+'B Supuestos'!$B$12)),0) -> -16158246 | J12: =-'B Supuestos'!$B$6*INDEX('Trayectorias B'!$C$5:$I$45,8,5) -> -16070764 | K12: =J12+IF(ISNUMBER(MATCH(7,'B Supuestos'!$D$20:$D$23,0)),INDEX('B Supuestos'!$F$20:$F$23,MATCH(7,'B Supuestos'!$D$20:$D$23,0))*(INDEX('Trayectorias B'!$C$5:$I$45,8,5)-INDEX('Trayectorias B'!$C$5:$I$45,4,5)*(1+'B Supuestos'!$B$12)),0) -> -16070764 | L12: =-'B Supuestos'!$B$6*INDEX('Trayectorias B'!$C$5:$I$45,8,6) -> -16594752 | M12: =L12+IF(ISNUMBER(MATCH(7,'B Supuestos'!$D$20:$D$23,0)),INDEX('B Supuestos'!$F$20:$F$23,MATCH(7,'B Supuestos'!$D$20:$D$23,0))*(INDEX('Trayectorias B'!$C$5:$I$45,8,6)-INDEX('Trayectorias B'!$C$5:$I$45,4,6)*(1+'B Supuestos'!$B$12)),0) -> -16594752 | N12: =-'B Supuestos'!$B$6*INDEX('Trayectorias B'!$C$5:$I$45,8,7) -> -17467972 | O12: =N12+IF(ISNUMBER(MATCH(7,'B Supuestos'!$D$20:$D$23,0)),INDEX('B Supuestos'!$F$20:$F$23,MATCH(7,'B Supuestos'!$D$20:$D$23,0))*(INDEX('Trayectorias B'!$C$5:$I$45,8,7)-INDEX('Trayectorias B'!$C$5:$I$45,4,7)*(1+'B Supuestos'!$B$12)),0) -> -17467972
A13: 8 | B13: =-'B Supuestos'!$B$6*INDEX('Trayectorias B'!$C$5:$I$45,9,1) -> -15588518 | C13: =B13+IF(ISNUMBER(MATCH(8,'B Supuestos'!$D$20:$D$23,0)),INDEX('B Supuestos'!$F$20:$F$23,MATCH(8,'B Supuestos'!$D$20:$D$23,0))*(INDEX('Trayectorias B'!$C$5:$I$45,9,1)-INDEX('Trayectorias B'!$C$5:$I$45,5,1)*(1+'B Supuestos'!$B$12)),0) -> -15588518 | D13: =-'B Supuestos'!$B$6*INDEX('Trayectorias B'!$C$5:$I$45,9,2) -> -16798706 | E13: =D13+IF(ISNUMBER(MATCH(8,'B Supuestos'!$D$20:$D$23,0)),INDEX('B Supuestos'!$F$20:$F$23,MATCH(8,'B Supuestos'!$D$20:$D$23,0))*(INDEX('Trayectorias B'!$C$5:$I$45,9,2)-INDEX('Trayectorias B'!$C$5:$I$45,5,2)*(1+'B Supuestos'!$B$12)),0) -> -16798706 | F13: =-'B Supuestos'!$B$6*INDEX('Trayectorias B'!$C$5:$I$45,9,3) -> -16169042 | G13: =F13+IF(ISNUMBER(MATCH(8,'B Supuestos'!$D$20:$D$23,0)),INDEX('B Supuestos'!$F$20:$F$23,MATCH(8,'B Supuestos'!$D$20:$D$23,0))*(INDEX('Trayectorias B'!$C$5:$I$45,9,3)-INDEX('Trayectorias B'!$C$5:$I$45,5,3)*(1+'B Supuestos'!$B$12)),0) -> -16169042 | H13: =-'B Supuestos'!$B$6*INDEX('Trayectorias B'!$C$5:$I$45,9,4) -> -17330059 | I13: =H13+IF(ISNUMBER(MATCH(8,'B Supuestos'!$D$20:$D$23,0)),INDEX('B Supuestos'!$F$20:$F$23,MATCH(8,'B Supuestos'!$D$20:$D$23,0))*(INDEX('Trayectorias B'!$C$5:$I$45,9,4)-INDEX('Trayectorias B'!$C$5:$I$45,5,4)*(1+'B Supuestos'!$B$12)),0) -> -17330059 | J13: =-'B Supuestos'!$B$6*INDEX('Trayectorias B'!$C$5:$I$45,9,5) -> -15732803 | K13: =J13+IF(ISNUMBER(MATCH(8,'B Supuestos'!$D$20:$D$23,0)),INDEX('B Supuestos'!$F$20:$F$23,MATCH(8,'B Supuestos'!$D$20:$D$23,0))*(INDEX('Trayectorias B'!$C$5:$I$45,9,5)-INDEX('Trayectorias B'!$C$5:$I$45,5,5)*(1+'B Supuestos'!$B$12)),0) -> -15732803 | L13: =-'B Supuestos'!$B$6*INDEX('Trayectorias B'!$C$5:$I$45,9,6) -> -16972069 | M13: =L13+IF(ISNUMBER(MATCH(8,'B Supuestos'!$D$20:$D$23,0)),INDEX('B Supuestos'!$F$20:$F$23,MATCH(8,'B Supuestos'!$D$20:$D$23,0))*(INDEX('Trayectorias B'!$C$5:$I$45,9,6)-INDEX('Trayectorias B'!$C$5:$I$45,5,6)*(1+'B Supuestos'!$B$12)),0) -> -16972069 | N13: =-'B Supuestos'!$B$6*INDEX('Trayectorias B'!$C$5:$I$45,9,7) -> -17551036 | O13: =N13+IF(ISNUMBER(MATCH(8,'B Supuestos'!$D$20:$D$23,0)),INDEX('B Supuestos'!$F$20:$F$23,MATCH(8,'B Supuestos'!$D$20:$D$23,0))*(INDEX('Trayectorias B'!$C$5:$I$45,9,7)-INDEX('Trayectorias B'!$C$5:$I$45,5,7)*(1+'B Supuestos'!$B$12)),0) -> -17551036
A14: 9 | B14: =-'B Supuestos'!$B$6*INDEX('Trayectorias B'!$C$5:$I$45,10,1) -> -15292700 | C14: =B14+IF(ISNUMBER(MATCH(9,'B Supuestos'!$D$20:$D$23,0)),INDEX('B Supuestos'!$F$20:$F$23,MATCH(9,'B Supuestos'!$D$20:$D$23,0))*(INDEX('Trayectorias B'!$C$5:$I$45,10,1)-INDEX('Trayectorias B'!$C$5:$I$45,6,1)*(1+'B Supuestos'!$B$12)),0) -> -15292700 | D14: =-'B Supuestos'!$B$6*INDEX('Trayectorias B'!$C$5:$I$45,10,2) -> -16663809 | E14: =D14+IF(ISNUMBER(MATCH(9,'B Supuestos'!$D$20:$D$23,0)),INDEX('B Supuestos'!$F$20:$F$23,MATCH(9,'B Supuestos'!$D$20:$D$23,0))*(INDEX('Trayectorias B'!$C$5:$I$45,10,2)-INDEX('Trayectorias B'!$C$5:$I$45,6,2)*(1+'B Supuestos'!$B$12)),0) -> -16663809 | F14: =-'B Supuestos'!$B$6*INDEX('Trayectorias B'!$C$5:$I$45,10,3) -> -16254130 | G14: =F14+IF(ISNUMBER(MATCH(9,'B Supuestos'!$D$20:$D$23,0)),INDEX('B Supuestos'!$F$20:$F$23,MATCH(9,'B Supuestos'!$D$20:$D$23,0))*(INDEX('Trayectorias B'!$C$5:$I$45,10,3)-INDEX('Trayectorias B'!$C$5:$I$45,6,3)*(1+'B Supuestos'!$B$12)),0) -> -16254130 | H14: =-'B Supuestos'!$B$6*INDEX('Trayectorias B'!$C$5:$I$45,10,4) -> -17449894 | I14: =H14+IF(ISNUMBER(MATCH(9,'B Supuestos'!$D$20:$D$23,0)),INDEX('B Supuestos'!$F$20:$F$23,MATCH(9,'B Supuestos'!$D$20:$D$23,0))*(INDEX('Trayectorias B'!$C$5:$I$45,10,4)-INDEX('Trayectorias B'!$C$5:$I$45,6,4)*(1+'B Supuestos'!$B$12)),0) -> -17449894 | J14: =-'B Supuestos'!$B$6*INDEX('Trayectorias B'!$C$5:$I$45,10,5) -> -16385599 | K14: =J14+IF(ISNUMBER(MATCH(9,'B Supuestos'!$D$20:$D$23,0)),INDEX('B Supuestos'!$F$20:$F$23,MATCH(9,'B Supuestos'!$D$20:$D$23,0))*(INDEX('Trayectorias B'!$C$5:$I$45,10,5)-INDEX('Trayectorias B'!$C$5:$I$45,6,5)*(1+'B Supuestos'!$B$12)),0) -> -16385599 | L14: =-'B Supuestos'!$B$6*INDEX('Trayectorias B'!$C$5:$I$45,10,6) -> -16513391 | M14: =L14+IF(ISNUMBER(MATCH(9,'B Supuestos'!$D$20:$D$23,0)),INDEX('B Supuestos'!$F$20:$F$23,MATCH(9,'B Supuestos'!$D$20:$D$23,0))*(INDEX('Trayectorias B'!$C$5:$I$45,10,6)-INDEX('Trayectorias B'!$C$5:$I$45,6,6)*(1+'B Supuestos'!$B$12)),0) -> -16513391 | N14: =-'B Supuestos'!$B$6*INDEX('Trayectorias B'!$C$5:$I$45,10,7) -> -17634495 | O14: =N14+IF(ISNUMBER(MATCH(9,'B Supuestos'!$D$20:$D$23,0)),INDEX('B Supuestos'!$F$20:$F$23,MATCH(9,'B Supuestos'!$D$20:$D$23,0))*(INDEX('Trayectorias B'!$C$5:$I$45,10,7)-INDEX('Trayectorias B'!$C$5:$I$45,6,7)*(1+'B Supuestos'!$B$12)),0) -> -17634495
A15: 10 | B15: =-'B Supuestos'!$B$6*INDEX('Trayectorias B'!$C$5:$I$45,11,1) -> -14946164 | C15: =B15+IF(ISNUMBER(MATCH(10,'B Supuestos'!$D$20:$D$23,0)),INDEX('B Supuestos'!$F$20:$F$23,MATCH(10,'B Supuestos'!$D$20:$D$23,0))*(INDEX('Trayectorias B'!$C$5:$I$45,11,1)-INDEX('Trayectorias B'!$C$5:$I$45,7,1)*(1+'B Supuestos'!$B$12)),0) -> -14946164 | D15: =-'B Supuestos'!$B$6*INDEX('Trayectorias B'!$C$5:$I$45,11,2) -> -17697706 | E15: =D15+IF(ISNUMBER(MATCH(10,'B Supuestos'!$D$20:$D$23,0)),INDEX('B Supuestos'!$F$20:$F$23,MATCH(10,'B Supuestos'!$D$20:$D$23,0))*(INDEX('Trayectorias B'!$C$5:$I$45,11,2)-INDEX('Trayectorias B'!$C$5:$I$45,7,2)*(1+'B Supuestos'!$B$12)),0) -> -17697706 | F15: =-'B Supuestos'!$B$6*INDEX('Trayectorias B'!$C$5:$I$45,11,3) -> -19180329 | G15: =F15+IF(ISNUMBER(MATCH(10,'B Supuestos'!$D$20:$D$23,0)),INDEX('B Supuestos'!$F$20:$F$23,MATCH(10,'B Supuestos'!$D$20:$D$23,0))*(INDEX('Trayectorias B'!$C$5:$I$45,11,3)-INDEX('Trayectorias B'!$C$5:$I$45,7,3)*(1+'B Supuestos'!$B$12)),0) -> -19180329 | H15: =-'B Supuestos'!$B$6*INDEX('Trayectorias B'!$C$5:$I$45,11,4) -> -17604439 | I15: =H15+IF(ISNUMBER(MATCH(10,'B Supuestos'!$D$20:$D$23,0)),INDEX('B Supuestos'!$F$20:$F$23,MATCH(10,'B Supuestos'!$D$20:$D$23,0))*(INDEX('Trayectorias B'!$C$5:$I$45,11,4)-INDEX('Trayectorias B'!$C$5:$I$45,7,4)*(1+'B Supuestos'!$B$12)),0) -> -17604439 | J15: =-'B Supuestos'!$B$6*INDEX('Trayectorias B'!$C$5:$I$45,11,5) -> -15827892 | K15: =J15+IF(ISNUMBER(MATCH(10,'B Supuestos'!$D$20:$D$23,0)),INDEX('B Supuestos'!$F$20:$F$23,MATCH(10,'B Supuestos'!$D$20:$D$23,0))*(INDEX('Trayectorias B'!$C$5:$I$45,11,5)-INDEX('Trayectorias B'!$C$5:$I$45,7,5)*(1+'B Supuestos'!$B$12)),0) -> -15827892 | L15: =-'B Supuestos'!$B$6*INDEX('Trayectorias B'!$C$5:$I$45,11,6) -> -17187047 | M15: =L15+IF(ISNUMBER(MATCH(10,'B Supuestos'!$D$20:$D$23,0)),INDEX('B Supuestos'!$F$20:$F$23,MATCH(10,'B Supuestos'!$D$20:$D$23,0))*(INDEX('Trayectorias B'!$C$5:$I$45,11,6)-INDEX('Trayectorias B'!$C$5:$I$45,7,6)*(1+'B Supuestos'!$B$12)),0) -> -17187047 | N15: =-'B Supuestos'!$B$6*INDEX('Trayectorias B'!$C$5:$I$45,11,7) -> -17718351 | O15: =N15+IF(ISNUMBER(MATCH(10,'B Supuestos'!$D$20:$D$23,0)),INDEX('B Supuestos'!$F$20:$F$23,MATCH(10,'B Supuestos'!$D$20:$D$23,0))*(INDEX('Trayectorias B'!$C$5:$I$45,11,7)-INDEX('Trayectorias B'!$C$5:$I$45,7,7)*(1+'B Supuestos'!$B$12)),0) -> -17718351
A16: 11 | B16: =-'B Supuestos'!$B$6*INDEX('Trayectorias B'!$C$5:$I$45,12,1) -> -13975245 | C16: =B16+IF(ISNUMBER(MATCH(11,'B Supuestos'!$D$20:$D$23,0)),INDEX('B Supuestos'!$F$20:$F$23,MATCH(11,'B Supuestos'!$D$20:$D$23,0))*(INDEX('Trayectorias B'!$C$5:$I$45,12,1)-INDEX('Trayectorias B'!$C$5:$I$45,8,1)*(1+'B Supuestos'!$B$12)),0) -> -13975245 | D16: =-'B Supuestos'!$B$6*INDEX('Trayectorias B'!$C$5:$I$45,12,2) -> -17267932 | E16: =D16+IF(ISNUMBER(MATCH(11,'B Supuestos'!$D$20:$D$23,0)),INDEX('B Supuestos'!$F$20:$F$23,MATCH(11,'B Supuestos'!$D$20:$D$23,0))*(INDEX('Trayectorias B'!$C$5:$I$45,12,2)-INDEX('Trayectorias B'!$C$5:$I$45,8,2)*(1+'B Supuestos'!$B$12)),0) -> -17267932 | F16: =-'B Supuestos'!$B$6*INDEX('Trayectorias B'!$C$5:$I$45,12,3) -> -17363126 | G16: =F16+IF(ISNUMBER(MATCH(11,'B Supuestos'!$D$20:$D$23,0)),INDEX('B Supuestos'!$F$20:$F$23,MATCH(11,'B Supuestos'!$D$20:$D$23,0))*(INDEX('Trayectorias B'!$C$5:$I$45,12,3)-INDEX('Trayectorias B'!$C$5:$I$45,8,3)*(1+'B Supuestos'!$B$12)),0) -> -17363126 | H16: =-'B Supuestos'!$B$6*INDEX('Trayectorias B'!$C$5:$I$45,12,4) -> -19205060 | I16: =H16+IF(ISNUMBER(MATCH(11,'B Supuestos'!$D$20:$D$23,0)),INDEX('B Supuestos'!$F$20:$F$23,MATCH(11,'B Supuestos'!$D$20:$D$23,0))*(INDEX('Trayectorias B'!$C$5:$I$45,12,4)-INDEX('Trayectorias B'!$C$5:$I$45,8,4)*(1+'B Supuestos'!$B$12)),0) -> -19205060 | J16: =-'B Supuestos'!$B$6*INDEX('Trayectorias B'!$C$5:$I$45,12,5) -> -16979751 | K16: =J16+IF(ISNUMBER(MATCH(11,'B Supuestos'!$D$20:$D$23,0)),INDEX('B Supuestos'!$F$20:$F$23,MATCH(11,'B Supuestos'!$D$20:$D$23,0))*(INDEX('Trayectorias B'!$C$5:$I$45,12,5)-INDEX('Trayectorias B'!$C$5:$I$45,8,5)*(1+'B Supuestos'!$B$12)),0) -> -16979751 | L16: =-'B Supuestos'!$B$6*INDEX('Trayectorias B'!$C$5:$I$45,12,6) -> -17129342 | M16: =L16+IF(ISNUMBER(MATCH(11,'B Supuestos'!$D$20:$D$23,0)),INDEX('B Supuestos'!$F$20:$F$23,MATCH(11,'B Supuestos'!$D$20:$D$23,0))*(INDEX('Trayectorias B'!$C$5:$I$45,12,6)-INDEX('Trayectorias B'!$C$5:$I$45,8,6)*(1+'B Supuestos'!$B$12)),0) -> -17129342 | N16: =-'B Supuestos'!$B$6*INDEX('Trayectorias B'!$C$5:$I$45,12,7) -> -17802605 | O16: =N16+IF(ISNUMBER(MATCH(11,'B Supuestos'!$D$20:$D$23,0)),INDEX('B Supuestos'!$F$20:$F$23,MATCH(11,'B Supuestos'!$D$20:$D$23,0))*(INDEX('Trayectorias B'!$C$5:$I$45,12,7)-INDEX('Trayectorias B'!$C$5:$I$45,8,7)*(1+'B Supuestos'!$B$12)),0) -> -17802605
A17: 12 | B17: =-'B Supuestos'!$B$6*INDEX('Trayectorias B'!$C$5:$I$45,13,1) -> -16266162 | C17: =B17+IF(ISNUMBER(MATCH(12,'B Supuestos'!$D$20:$D$23,0)),INDEX('B Supuestos'!$F$20:$F$23,MATCH(12,'B Supuestos'!$D$20:$D$23,0))*(INDEX('Trayectorias B'!$C$5:$I$45,13,1)-INDEX('Trayectorias B'!$C$5:$I$45,9,1)*(1+'B Supuestos'!$B$12)),0) -> -16266162 | D17: =-'B Supuestos'!$B$6*INDEX('Trayectorias B'!$C$5:$I$45,13,2) -> -18214030 | E17: =D17+IF(ISNUMBER(MATCH(12,'B Supuestos'!$D$20:$D$23,0)),INDEX('B Supuestos'!$F$20:$F$23,MATCH(12,'B Supuestos'!$D$20:$D$23,0))*(INDEX('Trayectorias B'!$C$5:$I$45,13,2)-INDEX('Trayectorias B'!$C$5:$I$45,9,2)*(1+'B Supuestos'!$B$12)),0) -> -18214030 | F17: =-'B Supuestos'!$B$6*INDEX('Trayectorias B'!$C$5:$I$45,13,3) -> -17470351 | G17: =F17+IF(ISNUMBER(MATCH(12,'B Supuestos'!$D$20:$D$23,0)),INDEX('B Supuestos'!$F$20:$F$23,MATCH(12,'B Supuestos'!$D$20:$D$23,0))*(INDEX('Trayectorias B'!$C$5:$I$45,13,3)-INDEX('Trayectorias B'!$C$5:$I$45,9,3)*(1+'B Supuestos'!$B$12)),0) -> -17470351 | H17: =-'B Supuestos'!$B$6*INDEX('Trayectorias B'!$C$5:$I$45,13,4) -> -17965665 | I17: =H17+IF(ISNUMBER(MATCH(12,'B Supuestos'!$D$20:$D$23,0)),INDEX('B Supuestos'!$F$20:$F$23,MATCH(12,'B Supuestos'!$D$20:$D$23,0))*(INDEX('Trayectorias B'!$C$5:$I$45,13,4)-INDEX('Trayectorias B'!$C$5:$I$45,9,4)*(1+'B Supuestos'!$B$12)),0) -> -17965665 | J17: =-'B Supuestos'!$B$6*INDEX('Trayectorias B'!$C$5:$I$45,13,5) -> -18030049 | K17: =J17+IF(ISNUMBER(MATCH(12,'B Supuestos'!$D$20:$D$23,0)),INDEX('B Supuestos'!$F$20:$F$23,MATCH(12,'B Supuestos'!$D$20:$D$23,0))*(INDEX('Trayectorias B'!$C$5:$I$45,13,5)-INDEX('Trayectorias B'!$C$5:$I$45,9,5)*(1+'B Supuestos'!$B$12)),0) -> -18030049 | L17: =-'B Supuestos'!$B$6*INDEX('Trayectorias B'!$C$5:$I$45,13,6) -> -16815177 | M17: =L17+IF(ISNUMBER(MATCH(12,'B Supuestos'!$D$20:$D$23,0)),INDEX('B Supuestos'!$F$20:$F$23,MATCH(12,'B Supuestos'!$D$20:$D$23,0))*(INDEX('Trayectorias B'!$C$5:$I$45,13,6)-INDEX('Trayectorias B'!$C$5:$I$45,9,6)*(1+'B Supuestos'!$B$12)),0) -> -16815177 | N17: =-'B Supuestos'!$B$6*INDEX('Trayectorias B'!$C$5:$I$45,13,7) -> -17887261 | O17: =N17+IF(ISNUMBER(MATCH(12,'B Supuestos'!$D$20:$D$23,0)),INDEX('B Supuestos'!$F$20:$F$23,MATCH(12,'B Supuestos'!$D$20:$D$23,0))*(INDEX('Trayectorias B'!$C$5:$I$45,13,7)-INDEX('Trayectorias B'!$C$5:$I$45,9,7)*(1+'B Supuestos'!$B$12)),0) -> -17887261
A18: 13 | B18: =-'B Supuestos'!$B$6*INDEX('Trayectorias B'!$C$5:$I$45,14,1) -> -18114031 | C18: =B18+IF(ISNUMBER(MATCH(13,'B Supuestos'!$D$20:$D$23,0)),INDEX('B Supuestos'!$F$20:$F$23,MATCH(13,'B Supuestos'!$D$20:$D$23,0))*(INDEX('Trayectorias B'!$C$5:$I$45,14,1)-INDEX('Trayectorias B'!$C$5:$I$45,10,1)*(1+'B Supuestos'!$B$12)),0) -> -18114031 | D18: =-'B Supuestos'!$B$6*INDEX('Trayectorias B'!$C$5:$I$45,14,2) -> -19815637 | E18: =D18+IF(ISNUMBER(MATCH(13,'B Supuestos'!$D$20:$D$23,0)),INDEX('B Supuestos'!$F$20:$F$23,MATCH(13,'B Supuestos'!$D$20:$D$23,0))*(INDEX('Trayectorias B'!$C$5:$I$45,14,2)-INDEX('Trayectorias B'!$C$5:$I$45,10,2)*(1+'B Supuestos'!$B$12)),0) -> -19815637 | F18: =-'B Supuestos'!$B$6*INDEX('Trayectorias B'!$C$5:$I$45,14,3) -> -16443406 | G18: =F18+IF(ISNUMBER(MATCH(13,'B Supuestos'!$D$20:$D$23,0)),INDEX('B Supuestos'!$F$20:$F$23,MATCH(13,'B Supuestos'!$D$20:$D$23,0))*(INDEX('Trayectorias B'!$C$5:$I$45,14,3)-INDEX('Trayectorias B'!$C$5:$I$45,10,3)*(1+'B Supuestos'!$B$12)),0) -> -16443406 | H18: =-'B Supuestos'!$B$6*INDEX('Trayectorias B'!$C$5:$I$45,14,4) -> -16542023 | I18: =H18+IF(ISNUMBER(MATCH(13,'B Supuestos'!$D$20:$D$23,0)),INDEX('B Supuestos'!$F$20:$F$23,MATCH(13,'B Supuestos'!$D$20:$D$23,0))*(INDEX('Trayectorias B'!$C$5:$I$45,14,4)-INDEX('Trayectorias B'!$C$5:$I$45,10,4)*(1+'B Supuestos'!$B$12)),0) -> -16542023 | J18: =-'B Supuestos'!$B$6*INDEX('Trayectorias B'!$C$5:$I$45,14,5) -> -18849119 | K18: =J18+IF(ISNUMBER(MATCH(13,'B Supuestos'!$D$20:$D$23,0)),INDEX('B Supuestos'!$F$20:$F$23,MATCH(13,'B Supuestos'!$D$20:$D$23,0))*(INDEX('Trayectorias B'!$C$5:$I$45,14,5)-INDEX('Trayectorias B'!$C$5:$I$45,10,5)*(1+'B Supuestos'!$B$12)),0) -> -18849119 | L18: =-'B Supuestos'!$B$6*INDEX('Trayectorias B'!$C$5:$I$45,14,6) -> -17707050 | M18: =L18+IF(ISNUMBER(MATCH(13,'B Supuestos'!$D$20:$D$23,0)),INDEX('B Supuestos'!$F$20:$F$23,MATCH(13,'B Supuestos'!$D$20:$D$23,0))*(INDEX('Trayectorias B'!$C$5:$I$45,14,6)-INDEX('Trayectorias B'!$C$5:$I$45,10,6)*(1+'B Supuestos'!$B$12)),0) -> -17707050 | N18: =-'B Supuestos'!$B$6*INDEX('Trayectorias B'!$C$5:$I$45,14,7) -> -17972318 | O18: =N18+IF(ISNUMBER(MATCH(13,'B Supuestos'!$D$20:$D$23,0)),INDEX('B Supuestos'!$F$20:$F$23,MATCH(13,'B Supuestos'!$D$20:$D$23,0))*(INDEX('Trayectorias B'!$C$5:$I$45,14,7)-INDEX('Trayectorias B'!$C$5:$I$45,10,7)*(1+'B Supuestos'!$B$12)),0) -> -17972318
A19: 14 | B19: =-'B Supuestos'!$B$6*INDEX('Trayectorias B'!$C$5:$I$45,15,1) -> -19457967 | C19: =B19+IF(ISNUMBER(MATCH(14,'B Supuestos'!$D$20:$D$23,0)),INDEX('B Supuestos'!$F$20:$F$23,MATCH(14,'B Supuestos'!$D$20:$D$23,0))*(INDEX('Trayectorias B'!$C$5:$I$45,15,1)-INDEX('Trayectorias B'!$C$5:$I$45,11,1)*(1+'B Supuestos'!$B$12)),0) -> -19457967 | D19: =-'B Supuestos'!$B$6*INDEX('Trayectorias B'!$C$5:$I$45,15,2) -> -20397205 | E19: =D19+IF(ISNUMBER(MATCH(14,'B Supuestos'!$D$20:$D$23,0)),INDEX('B Supuestos'!$F$20:$F$23,MATCH(14,'B Supuestos'!$D$20:$D$23,0))*(INDEX('Trayectorias B'!$C$5:$I$45,15,2)-INDEX('Trayectorias B'!$C$5:$I$45,11,2)*(1+'B Supuestos'!$B$12)),0) -> -20397205 | F19: =-'B Supuestos'!$B$6*INDEX('Trayectorias B'!$C$5:$I$45,15,3) -> -16982787 | G19: =F19+IF(ISNUMBER(MATCH(14,'B Supuestos'!$D$20:$D$23,0)),INDEX('B Supuestos'!$F$20:$F$23,MATCH(14,'B Supuestos'!$D$20:$D$23,0))*(INDEX('Trayectorias B'!$C$5:$I$45,15,3)-INDEX('Trayectorias B'!$C$5:$I$45,11,3)*(1+'B Supuestos'!$B$12)),0) -> -16982787 | H19: =-'B Supuestos'!$B$6*INDEX('Trayectorias B'!$C$5:$I$45,15,4) -> -16886710 | I19: =H19+IF(ISNUMBER(MATCH(14,'B Supuestos'!$D$20:$D$23,0)),INDEX('B Supuestos'!$F$20:$F$23,MATCH(14,'B Supuestos'!$D$20:$D$23,0))*(INDEX('Trayectorias B'!$C$5:$I$45,15,4)-INDEX('Trayectorias B'!$C$5:$I$45,11,4)*(1+'B Supuestos'!$B$12)),0) -> -16886710 | J19: =-'B Supuestos'!$B$6*INDEX('Trayectorias B'!$C$5:$I$45,15,5) -> -17704857 | K19: =J19+IF(ISNUMBER(MATCH(14,'B Supuestos'!$D$20:$D$23,0)),INDEX('B Supuestos'!$F$20:$F$23,MATCH(14,'B Supuestos'!$D$20:$D$23,0))*(INDEX('Trayectorias B'!$C$5:$I$45,15,5)-INDEX('Trayectorias B'!$C$5:$I$45,11,5)*(1+'B Supuestos'!$B$12)),0) -> -17704857 | L19: =-'B Supuestos'!$B$6*INDEX('Trayectorias B'!$C$5:$I$45,15,6) -> -17685333 | M19: =L19+IF(ISNUMBER(MATCH(14,'B Supuestos'!$D$20:$D$23,0)),INDEX('B Supuestos'!$F$20:$F$23,MATCH(14,'B Supuestos'!$D$20:$D$23,0))*(INDEX('Trayectorias B'!$C$5:$I$45,15,6)-INDEX('Trayectorias B'!$C$5:$I$45,11,6)*(1+'B Supuestos'!$B$12)),0) -> -17685333 | N19: =-'B Supuestos'!$B$6*INDEX('Trayectorias B'!$C$5:$I$45,15,7) -> -18057781 | O19: =N19+IF(ISNUMBER(MATCH(14,'B Supuestos'!$D$20:$D$23,0)),INDEX('B Supuestos'!$F$20:$F$23,MATCH(14,'B Supuestos'!$D$20:$D$23,0))*(INDEX('Trayectorias B'!$C$5:$I$45,15,7)-INDEX('Trayectorias B'!$C$5:$I$45,11,7)*(1+'B Supuestos'!$B$12)),0) -> -18057781
A20: 15 | B20: =-'B Supuestos'!$B$6*INDEX('Trayectorias B'!$C$5:$I$45,16,1) -> -19172885 | C20: =B20+IF(ISNUMBER(MATCH(15,'B Supuestos'!$D$20:$D$23,0)),INDEX('B Supuestos'!$F$20:$F$23,MATCH(15,'B Supuestos'!$D$20:$D$23,0))*(INDEX('Trayectorias B'!$C$5:$I$45,16,1)-INDEX('Trayectorias B'!$C$5:$I$45,12,1)*(1+'B Supuestos'!$B$12)),0) -> -19172885 | D20: =-'B Supuestos'!$B$6*INDEX('Trayectorias B'!$C$5:$I$45,16,2) -> -20008456 | E20: =D20+IF(ISNUMBER(MATCH(15,'B Supuestos'!$D$20:$D$23,0)),INDEX('B Supuestos'!$F$20:$F$23,MATCH(15,'B Supuestos'!$D$20:$D$23,0))*(INDEX('Trayectorias B'!$C$5:$I$45,16,2)-INDEX('Trayectorias B'!$C$5:$I$45,12,2)*(1+'B Supuestos'!$B$12)),0) -> -20008456 | F20: =-'B Supuestos'!$B$6*INDEX('Trayectorias B'!$C$5:$I$45,16,3) -> -17352836 | G20: =F20+IF(ISNUMBER(MATCH(15,'B Supuestos'!$D$20:$D$23,0)),INDEX('B Supuestos'!$F$20:$F$23,MATCH(15,'B Supuestos'!$D$20:$D$23,0))*(INDEX('Trayectorias B'!$C$5:$I$45,16,3)-INDEX('Trayectorias B'!$C$5:$I$45,12,3)*(1+'B Supuestos'!$B$12)),0) -> -17352836 | H20: =-'B Supuestos'!$B$6*INDEX('Trayectorias B'!$C$5:$I$45,16,4) -> -18624854 | I20: =H20+IF(ISNUMBER(MATCH(15,'B Supuestos'!$D$20:$D$23,0)),INDEX('B Supuestos'!$F$20:$F$23,MATCH(15,'B Supuestos'!$D$20:$D$23,0))*(INDEX('Trayectorias B'!$C$5:$I$45,16,4)-INDEX('Trayectorias B'!$C$5:$I$45,12,4)*(1+'B Supuestos'!$B$12)),0) -> -18624854 | J20: =-'B Supuestos'!$B$6*INDEX('Trayectorias B'!$C$5:$I$45,16,5) -> -19022606 | K20: =J20+IF(ISNUMBER(MATCH(15,'B Supuestos'!$D$20:$D$23,0)),INDEX('B Supuestos'!$F$20:$F$23,MATCH(15,'B Supuestos'!$D$20:$D$23,0))*(INDEX('Trayectorias B'!$C$5:$I$45,16,5)-INDEX('Trayectorias B'!$C$5:$I$45,12,5)*(1+'B Supuestos'!$B$12)),0) -> -19022606 | L20: =-'B Supuestos'!$B$6*INDEX('Trayectorias B'!$C$5:$I$45,16,6) -> -18773051 | M20: =L20+IF(ISNUMBER(MATCH(15,'B Supuestos'!$D$20:$D$23,0)),INDEX('B Supuestos'!$F$20:$F$23,MATCH(15,'B Supuestos'!$D$20:$D$23,0))*(INDEX('Trayectorias B'!$C$5:$I$45,16,6)-INDEX('Trayectorias B'!$C$5:$I$45,12,6)*(1+'B Supuestos'!$B$12)),0) -> -18773051 | N20: =-'B Supuestos'!$B$6*INDEX('Trayectorias B'!$C$5:$I$45,16,7) -> -18143649 | O20: =N20+IF(ISNUMBER(MATCH(15,'B Supuestos'!$D$20:$D$23,0)),INDEX('B Supuestos'!$F$20:$F$23,MATCH(15,'B Supuestos'!$D$20:$D$23,0))*(INDEX('Trayectorias B'!$C$5:$I$45,16,7)-INDEX('Trayectorias B'!$C$5:$I$45,12,7)*(1+'B Supuestos'!$B$12)),0) -> -18143649
A21: 16 | B21: =-'B Supuestos'!$B$6*INDEX('Trayectorias B'!$C$5:$I$45,17,1) -> -20469857 | C21: =B21+IF(ISNUMBER(MATCH(16,'B Supuestos'!$D$20:$D$23,0)),INDEX('B Supuestos'!$F$20:$F$23,MATCH(16,'B Supuestos'!$D$20:$D$23,0))*(INDEX('Trayectorias B'!$C$5:$I$45,17,1)-INDEX('Trayectorias B'!$C$5:$I$45,13,1)*(1+'B Supuestos'!$B$12)),0) -> -20469857 | D21: =-'B Supuestos'!$B$6*INDEX('Trayectorias B'!$C$5:$I$45,17,2) -> -18532430 | E21: =D21+IF(ISNUMBER(MATCH(16,'B Supuestos'!$D$20:$D$23,0)),INDEX('B Supuestos'!$F$20:$F$23,MATCH(16,'B Supuestos'!$D$20:$D$23,0))*(INDEX('Trayectorias B'!$C$5:$I$45,17,2)-INDEX('Trayectorias B'!$C$5:$I$45,13,2)*(1+'B Supuestos'!$B$12)),0) -> -18532430 | F21: =-'B Supuestos'!$B$6*INDEX('Trayectorias B'!$C$5:$I$45,17,3) -> -16877170 | G21: =F21+IF(ISNUMBER(MATCH(16,'B Supuestos'!$D$20:$D$23,0)),INDEX('B Supuestos'!$F$20:$F$23,MATCH(16,'B Supuestos'!$D$20:$D$23,0))*(INDEX('Trayectorias B'!$C$5:$I$45,17,3)-INDEX('Trayectorias B'!$C$5:$I$45,13,3)*(1+'B Supuestos'!$B$12)),0) -> -16877170 | H21: =-'B Supuestos'!$B$6*INDEX('Trayectorias B'!$C$5:$I$45,17,4) -> -17660894 | I21: =H21+IF(ISNUMBER(MATCH(16,'B Supuestos'!$D$20:$D$23,0)),INDEX('B Supuestos'!$F$20:$F$23,MATCH(16,'B Supuestos'!$D$20:$D$23,0))*(INDEX('Trayectorias B'!$C$5:$I$45,17,4)-INDEX('Trayectorias B'!$C$5:$I$45,13,4)*(1+'B Supuestos'!$B$12)),0) -> -17660894 | J21: =-'B Supuestos'!$B$6*INDEX('Trayectorias B'!$C$5:$I$45,17,5) -> -19679623 | K21: =J21+IF(ISNUMBER(MATCH(16,'B Supuestos'!$D$20:$D$23,0)),INDEX('B Supuestos'!$F$20:$F$23,MATCH(16,'B Supuestos'!$D$20:$D$23,0))*(INDEX('Trayectorias B'!$C$5:$I$45,17,5)-INDEX('Trayectorias B'!$C$5:$I$45,13,5)*(1+'B Supuestos'!$B$12)),0) -> -19679623 | L21: =-'B Supuestos'!$B$6*INDEX('Trayectorias B'!$C$5:$I$45,17,6) -> -18278439 | M21: =L21+IF(ISNUMBER(MATCH(16,'B Supuestos'!$D$20:$D$23,0)),INDEX('B Supuestos'!$F$20:$F$23,MATCH(16,'B Supuestos'!$D$20:$D$23,0))*(INDEX('Trayectorias B'!$C$5:$I$45,17,6)-INDEX('Trayectorias B'!$C$5:$I$45,13,6)*(1+'B Supuestos'!$B$12)),0) -> -18278439 | N21: =-'B Supuestos'!$B$6*INDEX('Trayectorias B'!$C$5:$I$45,17,7) -> -18229926 | O21: =N21+IF(ISNUMBER(MATCH(16,'B Supuestos'!$D$20:$D$23,0)),INDEX('B Supuestos'!$F$20:$F$23,MATCH(16,'B Supuestos'!$D$20:$D$23,0))*(INDEX('Trayectorias B'!$C$5:$I$45,17,7)-INDEX('Trayectorias B'!$C$5:$I$45,13,7)*(1+'B Supuestos'!$B$12)),0) -> -18229926
A22: 17 | B22: =-'B Supuestos'!$B$6*INDEX('Trayectorias B'!$C$5:$I$45,18,1) -> -18943422 | C22: =B22+IF(ISNUMBER(MATCH(17,'B Supuestos'!$D$20:$D$23,0)),INDEX('B Supuestos'!$F$20:$F$23,MATCH(17,'B Supuestos'!$D$20:$D$23,0))*(INDEX('Trayectorias B'!$C$5:$I$45,18,1)-INDEX('Trayectorias B'!$C$5:$I$45,14,1)*(1+'B Supuestos'!$B$12)),0) -> -18943422 | D22: =-'B Supuestos'!$B$6*INDEX('Trayectorias B'!$C$5:$I$45,18,2) -> -18707290 | E22: =D22+IF(ISNUMBER(MATCH(17,'B Supuestos'!$D$20:$D$23,0)),INDEX('B Supuestos'!$F$20:$F$23,MATCH(17,'B Supuestos'!$D$20:$D$23,0))*(INDEX('Trayectorias B'!$C$5:$I$45,18,2)-INDEX('Trayectorias B'!$C$5:$I$45,14,2)*(1+'B Supuestos'!$B$12)),0) -> -18707290 | F22: =-'B Supuestos'!$B$6*INDEX('Trayectorias B'!$C$5:$I$45,18,3) -> -15775152 | G22: =F22+IF(ISNUMBER(MATCH(17,'B Supuestos'!$D$20:$D$23,0)),INDEX('B Supuestos'!$F$20:$F$23,MATCH(17,'B Supuestos'!$D$20:$D$23,0))*(INDEX('Trayectorias B'!$C$5:$I$45,18,3)-INDEX('Trayectorias B'!$C$5:$I$45,14,3)*(1+'B Supuestos'!$B$12)),0) -> -15775152 | H22: =-'B Supuestos'!$B$6*INDEX('Trayectorias B'!$C$5:$I$45,18,4) -> -18124735 | I22: =H22+IF(ISNUMBER(MATCH(17,'B Supuestos'!$D$20:$D$23,0)),INDEX('B Supuestos'!$F$20:$F$23,MATCH(17,'B Supuestos'!$D$20:$D$23,0))*(INDEX('Trayectorias B'!$C$5:$I$45,18,4)-INDEX('Trayectorias B'!$C$5:$I$45,14,4)*(1+'B Supuestos'!$B$12)),0) -> -18124735 | J22: =-'B Supuestos'!$B$6*INDEX('Trayectorias B'!$C$5:$I$45,18,5) -> -18521206 | K22: =J22+IF(ISNUMBER(MATCH(17,'B Supuestos'!$D$20:$D$23,0)),INDEX('B Supuestos'!$F$20:$F$23,MATCH(17,'B Supuestos'!$D$20:$D$23,0))*(INDEX('Trayectorias B'!$C$5:$I$45,18,5)-INDEX('Trayectorias B'!$C$5:$I$45,14,5)*(1+'B Supuestos'!$B$12)),0) -> -18521206 | L22: =-'B Supuestos'!$B$6*INDEX('Trayectorias B'!$C$5:$I$45,18,6) -> -17934201 | M22: =L22+IF(ISNUMBER(MATCH(17,'B Supuestos'!$D$20:$D$23,0)),INDEX('B Supuestos'!$F$20:$F$23,MATCH(17,'B Supuestos'!$D$20:$D$23,0))*(INDEX('Trayectorias B'!$C$5:$I$45,18,6)-INDEX('Trayectorias B'!$C$5:$I$45,14,6)*(1+'B Supuestos'!$B$12)),0) -> -17934201 | N22: =-'B Supuestos'!$B$6*INDEX('Trayectorias B'!$C$5:$I$45,18,7) -> -18316613 | O22: =N22+IF(ISNUMBER(MATCH(17,'B Supuestos'!$D$20:$D$23,0)),INDEX('B Supuestos'!$F$20:$F$23,MATCH(17,'B Supuestos'!$D$20:$D$23,0))*(INDEX('Trayectorias B'!$C$5:$I$45,18,7)-INDEX('Trayectorias B'!$C$5:$I$45,14,7)*(1+'B Supuestos'!$B$12)),0) -> -18316613
A23: 18 | B23: =-'B Supuestos'!$B$6*INDEX('Trayectorias B'!$C$5:$I$45,19,1) -> -19206244 | C23: =B23+IF(ISNUMBER(MATCH(18,'B Supuestos'!$D$20:$D$23,0)),INDEX('B Supuestos'!$F$20:$F$23,MATCH(18,'B Supuestos'!$D$20:$D$23,0))*(INDEX('Trayectorias B'!$C$5:$I$45,19,1)-INDEX('Trayectorias B'!$C$5:$I$45,15,1)*(1+'B Supuestos'!$B$12)),0) -> -19206244 | D23: =-'B Supuestos'!$B$6*INDEX('Trayectorias B'!$C$5:$I$45,19,2) -> -18665787 | E23: =D23+IF(ISNUMBER(MATCH(18,'B Supuestos'!$D$20:$D$23,0)),INDEX('B Supuestos'!$F$20:$F$23,MATCH(18,'B Supuestos'!$D$20:$D$23,0))*(INDEX('Trayectorias B'!$C$5:$I$45,19,2)-INDEX('Trayectorias B'!$C$5:$I$45,15,2)*(1+'B Supuestos'!$B$12)),0) -> -18665787 | F23: =-'B Supuestos'!$B$6*INDEX('Trayectorias B'!$C$5:$I$45,19,3) -> -16573616 | G23: =F23+IF(ISNUMBER(MATCH(18,'B Supuestos'!$D$20:$D$23,0)),INDEX('B Supuestos'!$F$20:$F$23,MATCH(18,'B Supuestos'!$D$20:$D$23,0))*(INDEX('Trayectorias B'!$C$5:$I$45,19,3)-INDEX('Trayectorias B'!$C$5:$I$45,15,3)*(1+'B Supuestos'!$B$12)),0) -> -16573616 | H23: =-'B Supuestos'!$B$6*INDEX('Trayectorias B'!$C$5:$I$45,19,4) -> -18237562 | I23: =H23+IF(ISNUMBER(MATCH(18,'B Supuestos'!$D$20:$D$23,0)),INDEX('B Supuestos'!$F$20:$F$23,MATCH(18,'B Supuestos'!$D$20:$D$23,0))*(INDEX('Trayectorias B'!$C$5:$I$45,19,4)-INDEX('Trayectorias B'!$C$5:$I$45,15,4)*(1+'B Supuestos'!$B$12)),0) -> -18237562 | J23: =-'B Supuestos'!$B$6*INDEX('Trayectorias B'!$C$5:$I$45,19,5) -> -17697347 | K23: =J23+IF(ISNUMBER(MATCH(18,'B Supuestos'!$D$20:$D$23,0)),INDEX('B Supuestos'!$F$20:$F$23,MATCH(18,'B Supuestos'!$D$20:$D$23,0))*(INDEX('Trayectorias B'!$C$5:$I$45,19,5)-INDEX('Trayectorias B'!$C$5:$I$45,15,5)*(1+'B Supuestos'!$B$12)),0) -> -17697347 | L23: =-'B Supuestos'!$B$6*INDEX('Trayectorias B'!$C$5:$I$45,19,6) -> -17812485 | M23: =L23+IF(ISNUMBER(MATCH(18,'B Supuestos'!$D$20:$D$23,0)),INDEX('B Supuestos'!$F$20:$F$23,MATCH(18,'B Supuestos'!$D$20:$D$23,0))*(INDEX('Trayectorias B'!$C$5:$I$45,19,6)-INDEX('Trayectorias B'!$C$5:$I$45,15,6)*(1+'B Supuestos'!$B$12)),0) -> -17812485 | N23: =-'B Supuestos'!$B$6*INDEX('Trayectorias B'!$C$5:$I$45,19,7) -> -18403713 | O23: =N23+IF(ISNUMBER(MATCH(18,'B Supuestos'!$D$20:$D$23,0)),INDEX('B Supuestos'!$F$20:$F$23,MATCH(18,'B Supuestos'!$D$20:$D$23,0))*(INDEX('Trayectorias B'!$C$5:$I$45,19,7)-INDEX('Trayectorias B'!$C$5:$I$45,15,7)*(1+'B Supuestos'!$B$12)),0) -> -18403713
A24: 19 | B24: =-'B Supuestos'!$B$6*INDEX('Trayectorias B'!$C$5:$I$45,20,1) -> -19649534 | C24: =B24+IF(ISNUMBER(MATCH(19,'B Supuestos'!$D$20:$D$23,0)),INDEX('B Supuestos'!$F$20:$F$23,MATCH(19,'B Supuestos'!$D$20:$D$23,0))*(INDEX('Trayectorias B'!$C$5:$I$45,20,1)-INDEX('Trayectorias B'!$C$5:$I$45,16,1)*(1+'B Supuestos'!$B$12)),0) -> -19649534 | D24: =-'B Supuestos'!$B$6*INDEX('Trayectorias B'!$C$5:$I$45,20,2) -> -18815616 | E24: =D24+IF(ISNUMBER(MATCH(19,'B Supuestos'!$D$20:$D$23,0)),INDEX('B Supuestos'!$F$20:$F$23,MATCH(19,'B Supuestos'!$D$20:$D$23,0))*(INDEX('Trayectorias B'!$C$5:$I$45,20,2)-INDEX('Trayectorias B'!$C$5:$I$45,16,2)*(1+'B Supuestos'!$B$12)),0) -> -18815616 | F24: =-'B Supuestos'!$B$6*INDEX('Trayectorias B'!$C$5:$I$45,20,3) -> -16596171 | G24: =F24+IF(ISNUMBER(MATCH(19,'B Supuestos'!$D$20:$D$23,0)),INDEX('B Supuestos'!$F$20:$F$23,MATCH(19,'B Supuestos'!$D$20:$D$23,0))*(INDEX('Trayectorias B'!$C$5:$I$45,20,3)-INDEX('Trayectorias B'!$C$5:$I$45,16,3)*(1+'B Supuestos'!$B$12)),0) -> -16596171 | H24: =-'B Supuestos'!$B$6*INDEX('Trayectorias B'!$C$5:$I$45,20,4) -> -19087733 | I24: =H24+IF(ISNUMBER(MATCH(19,'B Supuestos'!$D$20:$D$23,0)),INDEX('B Supuestos'!$F$20:$F$23,MATCH(19,'B Supuestos'!$D$20:$D$23,0))*(INDEX('Trayectorias B'!$C$5:$I$45,20,4)-INDEX('Trayectorias B'!$C$5:$I$45,16,4)*(1+'B Supuestos'!$B$12)),0) -> -19087733 | J24: =-'B Supuestos'!$B$6*INDEX('Trayectorias B'!$C$5:$I$45,20,5) -> -18834912 | K24: =J24+IF(ISNUMBER(MATCH(19,'B Supuestos'!$D$20:$D$23,0)),INDEX('B Supuestos'!$F$20:$F$23,MATCH(19,'B Supuestos'!$D$20:$D$23,0))*(INDEX('Trayectorias B'!$C$5:$I$45,20,5)-INDEX('Trayectorias B'!$C$5:$I$45,16,5)*(1+'B Supuestos'!$B$12)),0) -> -18834912 | L24: =-'B Supuestos'!$B$6*INDEX('Trayectorias B'!$C$5:$I$45,20,6) -> -17266751 | M24: =L24+IF(ISNUMBER(MATCH(19,'B Supuestos'!$D$20:$D$23,0)),INDEX('B Supuestos'!$F$20:$F$23,MATCH(19,'B Supuestos'!$D$20:$D$23,0))*(INDEX('Trayectorias B'!$C$5:$I$45,20,6)-INDEX('Trayectorias B'!$C$5:$I$45,16,6)*(1+'B Supuestos'!$B$12)),0) -> -17266751 | N24: =-'B Supuestos'!$B$6*INDEX('Trayectorias B'!$C$5:$I$45,20,7) -> -18491226 | O24: =N24+IF(ISNUMBER(MATCH(19,'B Supuestos'!$D$20:$D$23,0)),INDEX('B Supuestos'!$F$20:$F$23,MATCH(19,'B Supuestos'!$D$20:$D$23,0))*(INDEX('Trayectorias B'!$C$5:$I$45,20,7)-INDEX('Trayectorias B'!$C$5:$I$45,16,7)*(1+'B Supuestos'!$B$12)),0) -> -18491226
A25: 20 | B25: =-'B Supuestos'!$B$6*INDEX('Trayectorias B'!$C$5:$I$45,21,1) -> -20679218 | C25: =B25+IF(ISNUMBER(MATCH(20,'B Supuestos'!$D$20:$D$23,0)),INDEX('B Supuestos'!$F$20:$F$23,MATCH(20,'B Supuestos'!$D$20:$D$23,0))*(INDEX('Trayectorias B'!$C$5:$I$45,21,1)-INDEX('Trayectorias B'!$C$5:$I$45,17,1)*(1+'B Supuestos'!$B$12)),0) -> -20679218 | D25: =-'B Supuestos'!$B$6*INDEX('Trayectorias B'!$C$5:$I$45,21,2) -> -17911500 | E25: =D25+IF(ISNUMBER(MATCH(20,'B Supuestos'!$D$20:$D$23,0)),INDEX('B Supuestos'!$F$20:$F$23,MATCH(20,'B Supuestos'!$D$20:$D$23,0))*(INDEX('Trayectorias B'!$C$5:$I$45,21,2)-INDEX('Trayectorias B'!$C$5:$I$45,17,2)*(1+'B Supuestos'!$B$12)),0) -> -17911500 | F25: =-'B Supuestos'!$B$6*INDEX('Trayectorias B'!$C$5:$I$45,21,3) -> -17419772 | G25: =F25+IF(ISNUMBER(MATCH(20,'B Supuestos'!$D$20:$D$23,0)),INDEX('B Supuestos'!$F$20:$F$23,MATCH(20,'B Supuestos'!$D$20:$D$23,0))*(INDEX('Trayectorias B'!$C$5:$I$45,21,3)-INDEX('Trayectorias B'!$C$5:$I$45,17,3)*(1+'B Supuestos'!$B$12)),0) -> -17419772 | H25: =-'B Supuestos'!$B$6*INDEX('Trayectorias B'!$C$5:$I$45,21,4) -> -19727127 | I25: =H25+IF(ISNUMBER(MATCH(20,'B Supuestos'!$D$20:$D$23,0)),INDEX('B Supuestos'!$F$20:$F$23,MATCH(20,'B Supuestos'!$D$20:$D$23,0))*(INDEX('Trayectorias B'!$C$5:$I$45,21,4)-INDEX('Trayectorias B'!$C$5:$I$45,17,4)*(1+'B Supuestos'!$B$12)),0) -> -19727127 | J25: =-'B Supuestos'!$B$6*INDEX('Trayectorias B'!$C$5:$I$45,21,5) -> -20268099 | K25: =J25+IF(ISNUMBER(MATCH(20,'B Supuestos'!$D$20:$D$23,0)),INDEX('B Supuestos'!$F$20:$F$23,MATCH(20,'B Supuestos'!$D$20:$D$23,0))*(INDEX('Trayectorias B'!$C$5:$I$45,21,5)-INDEX('Trayectorias B'!$C$5:$I$45,17,5)*(1+'B Supuestos'!$B$12)),0) -> -20268099 | L25: =-'B Supuestos'!$B$6*INDEX('Trayectorias B'!$C$5:$I$45,21,6) -> -18262440 | M25: =L25+IF(ISNUMBER(MATCH(20,'B Supuestos'!$D$20:$D$23,0)),INDEX('B Supuestos'!$F$20:$F$23,MATCH(20,'B Supuestos'!$D$20:$D$23,0))*(INDEX('Trayectorias B'!$C$5:$I$45,21,6)-INDEX('Trayectorias B'!$C$5:$I$45,17,6)*(1+'B Supuestos'!$B$12)),0) -> -18262440 | N25: =-'B Supuestos'!$B$6*INDEX('Trayectorias B'!$C$5:$I$45,21,7) -> -18579156 | O25: =N25+IF(ISNUMBER(MATCH(20,'B Supuestos'!$D$20:$D$23,0)),INDEX('B Supuestos'!$F$20:$F$23,MATCH(20,'B Supuestos'!$D$20:$D$23,0))*(INDEX('Trayectorias B'!$C$5:$I$45,21,7)-INDEX('Trayectorias B'!$C$5:$I$45,17,7)*(1+'B Supuestos'!$B$12)),0) -> -18579156
A26: 21 | B26: =-'B Supuestos'!$B$6*INDEX('Trayectorias B'!$C$5:$I$45,22,1) -> -20412413 | C26: =B26+IF(ISNUMBER(MATCH(21,'B Supuestos'!$D$20:$D$23,0)),INDEX('B Supuestos'!$F$20:$F$23,MATCH(21,'B Supuestos'!$D$20:$D$23,0))*(INDEX('Trayectorias B'!$C$5:$I$45,22,1)-INDEX('Trayectorias B'!$C$5:$I$45,18,1)*(1+'B Supuestos'!$B$12)),0) -> -20412413 | D26: =-'B Supuestos'!$B$6*INDEX('Trayectorias B'!$C$5:$I$45,22,2) -> -20488690 | E26: =D26+IF(ISNUMBER(MATCH(21,'B Supuestos'!$D$20:$D$23,0)),INDEX('B Supuestos'!$F$20:$F$23,MATCH(21,'B Supuestos'!$D$20:$D$23,0))*(INDEX('Trayectorias B'!$C$5:$I$45,22,2)-INDEX('Trayectorias B'!$C$5:$I$45,18,2)*(1+'B Supuestos'!$B$12)),0) -> -20488690 | F26: =-'B Supuestos'!$B$6*INDEX('Trayectorias B'!$C$5:$I$45,22,3) -> -17803110 | G26: =F26+IF(ISNUMBER(MATCH(21,'B Supuestos'!$D$20:$D$23,0)),INDEX('B Supuestos'!$F$20:$F$23,MATCH(21,'B Supuestos'!$D$20:$D$23,0))*(INDEX('Trayectorias B'!$C$5:$I$45,22,3)-INDEX('Trayectorias B'!$C$5:$I$45,18,3)*(1+'B Supuestos'!$B$12)),0) -> -17803110 | H26: =-'B Supuestos'!$B$6*INDEX('Trayectorias B'!$C$5:$I$45,22,4) -> -19819278 | I26: =H26+IF(ISNUMBER(MATCH(21,'B Supuestos'!$D$20:$D$23,0)),INDEX('B Supuestos'!$F$20:$F$23,MATCH(21,'B Supuestos'!$D$20:$D$23,0))*(INDEX('Trayectorias B'!$C$5:$I$45,22,4)-INDEX('Trayectorias B'!$C$5:$I$45,18,4)*(1+'B Supuestos'!$B$12)),0) -> -19819278 | J26: =-'B Supuestos'!$B$6*INDEX('Trayectorias B'!$C$5:$I$45,22,5) -> -21504318 | K26: =J26+IF(ISNUMBER(MATCH(21,'B Supuestos'!$D$20:$D$23,0)),INDEX('B Supuestos'!$F$20:$F$23,MATCH(21,'B Supuestos'!$D$20:$D$23,0))*(INDEX('Trayectorias B'!$C$5:$I$45,22,5)-INDEX('Trayectorias B'!$C$5:$I$45,18,5)*(1+'B Supuestos'!$B$12)),0) -> -21504318 | L26: =-'B Supuestos'!$B$6*INDEX('Trayectorias B'!$C$5:$I$45,22,6) -> -19813393 | M26: =L26+IF(ISNUMBER(MATCH(21,'B Supuestos'!$D$20:$D$23,0)),INDEX('B Supuestos'!$F$20:$F$23,MATCH(21,'B Supuestos'!$D$20:$D$23,0))*(INDEX('Trayectorias B'!$C$5:$I$45,22,6)-INDEX('Trayectorias B'!$C$5:$I$45,18,6)*(1+'B Supuestos'!$B$12)),0) -> -19813393 | N26: =-'B Supuestos'!$B$6*INDEX('Trayectorias B'!$C$5:$I$45,22,7) -> -18667504 | O26: =N26+IF(ISNUMBER(MATCH(21,'B Supuestos'!$D$20:$D$23,0)),INDEX('B Supuestos'!$F$20:$F$23,MATCH(21,'B Supuestos'!$D$20:$D$23,0))*(INDEX('Trayectorias B'!$C$5:$I$45,22,7)-INDEX('Trayectorias B'!$C$5:$I$45,18,7)*(1+'B Supuestos'!$B$12)),0) -> -18667504
A27: 22 | B27: =-'B Supuestos'!$B$6*INDEX('Trayectorias B'!$C$5:$I$45,23,1) -> -19560510 | C27: =B27+IF(ISNUMBER(MATCH(22,'B Supuestos'!$D$20:$D$23,0)),INDEX('B Supuestos'!$F$20:$F$23,MATCH(22,'B Supuestos'!$D$20:$D$23,0))*(INDEX('Trayectorias B'!$C$5:$I$45,23,1)-INDEX('Trayectorias B'!$C$5:$I$45,19,1)*(1+'B Supuestos'!$B$12)),0) -> -19560510 | D27: =-'B Supuestos'!$B$6*INDEX('Trayectorias B'!$C$5:$I$45,23,2) -> -19381345 | E27: =D27+IF(ISNUMBER(MATCH(22,'B Supuestos'!$D$20:$D$23,0)),INDEX('B Supuestos'!$F$20:$F$23,MATCH(22,'B Supuestos'!$D$20:$D$23,0))*(INDEX('Trayectorias B'!$C$5:$I$45,23,2)-INDEX('Trayectorias B'!$C$5:$I$45,19,2)*(1+'B Supuestos'!$B$12)),0) -> -19381345 | F27: =-'B Supuestos'!$B$6*INDEX('Trayectorias B'!$C$5:$I$45,23,3) -> -17487984 | G27: =F27+IF(ISNUMBER(MATCH(22,'B Supuestos'!$D$20:$D$23,0)),INDEX('B Supuestos'!$F$20:$F$23,MATCH(22,'B Supuestos'!$D$20:$D$23,0))*(INDEX('Trayectorias B'!$C$5:$I$45,23,3)-INDEX('Trayectorias B'!$C$5:$I$45,19,3)*(1+'B Supuestos'!$B$12)),0) -> -17487984 | H27: =-'B Supuestos'!$B$6*INDEX('Trayectorias B'!$C$5:$I$45,23,4) -> -20323316 | I27: =H27+IF(ISNUMBER(MATCH(22,'B Supuestos'!$D$20:$D$23,0)),INDEX('B Supuestos'!$F$20:$F$23,MATCH(22,'B Supuestos'!$D$20:$D$23,0))*(INDEX('Trayectorias B'!$C$5:$I$45,23,4)-INDEX('Trayectorias B'!$C$5:$I$45,19,4)*(1+'B Supuestos'!$B$12)),0) -> -20323316 | J27: =-'B Supuestos'!$B$6*INDEX('Trayectorias B'!$C$5:$I$45,23,5) -> -20185960 | K27: =J27+IF(ISNUMBER(MATCH(22,'B Supuestos'!$D$20:$D$23,0)),INDEX('B Supuestos'!$F$20:$F$23,MATCH(22,'B Supuestos'!$D$20:$D$23,0))*(INDEX('Trayectorias B'!$C$5:$I$45,23,5)-INDEX('Trayectorias B'!$C$5:$I$45,19,5)*(1+'B Supuestos'!$B$12)),0) -> -20185960 | L27: =-'B Supuestos'!$B$6*INDEX('Trayectorias B'!$C$5:$I$45,23,6) -> -20361804 | M27: =L27+IF(ISNUMBER(MATCH(22,'B Supuestos'!$D$20:$D$23,0)),INDEX('B Supuestos'!$F$20:$F$23,MATCH(22,'B Supuestos'!$D$20:$D$23,0))*(INDEX('Trayectorias B'!$C$5:$I$45,23,6)-INDEX('Trayectorias B'!$C$5:$I$45,19,6)*(1+'B Supuestos'!$B$12)),0) -> -20361804 | N27: =-'B Supuestos'!$B$6*INDEX('Trayectorias B'!$C$5:$I$45,23,7) -> -18756272 | O27: =N27+IF(ISNUMBER(MATCH(22,'B Supuestos'!$D$20:$D$23,0)),INDEX('B Supuestos'!$F$20:$F$23,MATCH(22,'B Supuestos'!$D$20:$D$23,0))*(INDEX('Trayectorias B'!$C$5:$I$45,23,7)-INDEX('Trayectorias B'!$C$5:$I$45,19,7)*(1+'B Supuestos'!$B$12)),0) -> -18756272
A28: 23 | B28: =-'B Supuestos'!$B$6*INDEX('Trayectorias B'!$C$5:$I$45,24,1) -> -20050430 | C28: =B28+IF(ISNUMBER(MATCH(23,'B Supuestos'!$D$20:$D$23,0)),INDEX('B Supuestos'!$F$20:$F$23,MATCH(23,'B Supuestos'!$D$20:$D$23,0))*(INDEX('Trayectorias B'!$C$5:$I$45,24,1)-INDEX('Trayectorias B'!$C$5:$I$45,20,1)*(1+'B Supuestos'!$B$12)),0) -> -20050430 | D28: =-'B Supuestos'!$B$6*INDEX('Trayectorias B'!$C$5:$I$45,24,2) -> -18665986 | E28: =D28+IF(ISNUMBER(MATCH(23,'B Supuestos'!$D$20:$D$23,0)),INDEX('B Supuestos'!$F$20:$F$23,MATCH(23,'B Supuestos'!$D$20:$D$23,0))*(INDEX('Trayectorias B'!$C$5:$I$45,24,2)-INDEX('Trayectorias B'!$C$5:$I$45,20,2)*(1+'B Supuestos'!$B$12)),0) -> -18665986 | F28: =-'B Supuestos'!$B$6*INDEX('Trayectorias B'!$C$5:$I$45,24,3) -> -18436338 | G28: =F28+IF(ISNUMBER(MATCH(23,'B Supuestos'!$D$20:$D$23,0)),INDEX('B Supuestos'!$F$20:$F$23,MATCH(23,'B Supuestos'!$D$20:$D$23,0))*(INDEX('Trayectorias B'!$C$5:$I$45,24,3)-INDEX('Trayectorias B'!$C$5:$I$45,20,3)*(1+'B Supuestos'!$B$12)),0) -> -18436338 | H28: =-'B Supuestos'!$B$6*INDEX('Trayectorias B'!$C$5:$I$45,24,4) -> -16904401 | I28: =H28+IF(ISNUMBER(MATCH(23,'B Supuestos'!$D$20:$D$23,0)),INDEX('B Supuestos'!$F$20:$F$23,MATCH(23,'B Supuestos'!$D$20:$D$23,0))*(INDEX('Trayectorias B'!$C$5:$I$45,24,4)-INDEX('Trayectorias B'!$C$5:$I$45,20,4)*(1+'B Supuestos'!$B$12)),0) -> -16904401 | J28: =-'B Supuestos'!$B$6*INDEX('Trayectorias B'!$C$5:$I$45,24,5) -> -19694830 | K28: =J28+IF(ISNUMBER(MATCH(23,'B Supuestos'!$D$20:$D$23,0)),INDEX('B Supuestos'!$F$20:$F$23,MATCH(23,'B Supuestos'!$D$20:$D$23,0))*(INDEX('Trayectorias B'!$C$5:$I$45,24,5)-INDEX('Trayectorias B'!$C$5:$I$45,20,5)*(1+'B Supuestos'!$B$12)),0) -> -19694830 | L28: =-'B Supuestos'!$B$6*INDEX('Trayectorias B'!$C$5:$I$45,24,6) -> -20669767 | M28: =L28+IF(ISNUMBER(MATCH(23,'B Supuestos'!$D$20:$D$23,0)),INDEX('B Supuestos'!$F$20:$F$23,MATCH(23,'B Supuestos'!$D$20:$D$23,0))*(INDEX('Trayectorias B'!$C$5:$I$45,24,6)-INDEX('Trayectorias B'!$C$5:$I$45,20,6)*(1+'B Supuestos'!$B$12)),0) -> -20669767 | N28: =-'B Supuestos'!$B$6*INDEX('Trayectorias B'!$C$5:$I$45,24,7) -> -18845462 | O28: =N28+IF(ISNUMBER(MATCH(23,'B Supuestos'!$D$20:$D$23,0)),INDEX('B Supuestos'!$F$20:$F$23,MATCH(23,'B Supuestos'!$D$20:$D$23,0))*(INDEX('Trayectorias B'!$C$5:$I$45,24,7)-INDEX('Trayectorias B'!$C$5:$I$45,20,7)*(1+'B Supuestos'!$B$12)),0) -> -18845462
A29: 24 | B29: =-'B Supuestos'!$B$6*INDEX('Trayectorias B'!$C$5:$I$45,25,1) -> -19539134 | C29: =B29+IF(ISNUMBER(MATCH(24,'B Supuestos'!$D$20:$D$23,0)),INDEX('B Supuestos'!$F$20:$F$23,MATCH(24,'B Supuestos'!$D$20:$D$23,0))*(INDEX('Trayectorias B'!$C$5:$I$45,25,1)-INDEX('Trayectorias B'!$C$5:$I$45,21,1)*(1+'B Supuestos'!$B$12)),0) -> -19539134 | D29: =-'B Supuestos'!$B$6*INDEX('Trayectorias B'!$C$5:$I$45,25,2) -> -18868211 | E29: =D29+IF(ISNUMBER(MATCH(24,'B Supuestos'!$D$20:$D$23,0)),INDEX('B Supuestos'!$F$20:$F$23,MATCH(24,'B Supuestos'!$D$20:$D$23,0))*(INDEX('Trayectorias B'!$C$5:$I$45,25,2)-INDEX('Trayectorias B'!$C$5:$I$45,21,2)*(1+'B Supuestos'!$B$12)),0) -> -18868211 | F29: =-'B Supuestos'!$B$6*INDEX('Trayectorias B'!$C$5:$I$45,25,3) -> -19521180 | G29: =F29+IF(ISNUMBER(MATCH(24,'B Supuestos'!$D$20:$D$23,0)),INDEX('B Supuestos'!$F$20:$F$23,MATCH(24,'B Supuestos'!$D$20:$D$23,0))*(INDEX('Trayectorias B'!$C$5:$I$45,25,3)-INDEX('Trayectorias B'!$C$5:$I$45,21,3)*(1+'B Supuestos'!$B$12)),0) -> -19521180 | H29: =-'B Supuestos'!$B$6*INDEX('Trayectorias B'!$C$5:$I$45,25,4) -> -18335199 | I29: =H29+IF(ISNUMBER(MATCH(24,'B Supuestos'!$D$20:$D$23,0)),INDEX('B Supuestos'!$F$20:$F$23,MATCH(24,'B Supuestos'!$D$20:$D$23,0))*(INDEX('Trayectorias B'!$C$5:$I$45,25,4)-INDEX('Trayectorias B'!$C$5:$I$45,21,4)*(1+'B Supuestos'!$B$12)),0) -> -18335199 | J29: =-'B Supuestos'!$B$6*INDEX('Trayectorias B'!$C$5:$I$45,25,5) -> -19324705 | K29: =J29+IF(ISNUMBER(MATCH(24,'B Supuestos'!$D$20:$D$23,0)),INDEX('B Supuestos'!$F$20:$F$23,MATCH(24,'B Supuestos'!$D$20:$D$23,0))*(INDEX('Trayectorias B'!$C$5:$I$45,25,5)-INDEX('Trayectorias B'!$C$5:$I$45,21,5)*(1+'B Supuestos'!$B$12)),0) -> -19324705 | L29: =-'B Supuestos'!$B$6*INDEX('Trayectorias B'!$C$5:$I$45,25,6) -> -18849373 | M29: =L29+IF(ISNUMBER(MATCH(24,'B Supuestos'!$D$20:$D$23,0)),INDEX('B Supuestos'!$F$20:$F$23,MATCH(24,'B Supuestos'!$D$20:$D$23,0))*(INDEX('Trayectorias B'!$C$5:$I$45,25,6)-INDEX('Trayectorias B'!$C$5:$I$45,21,6)*(1+'B Supuestos'!$B$12)),0) -> -18849373 | N29: =-'B Supuestos'!$B$6*INDEX('Trayectorias B'!$C$5:$I$45,25,7) -> -18935076 | O29: =N29+IF(ISNUMBER(MATCH(24,'B Supuestos'!$D$20:$D$23,0)),INDEX('B Supuestos'!$F$20:$F$23,MATCH(24,'B Supuestos'!$D$20:$D$23,0))*(INDEX('Trayectorias B'!$C$5:$I$45,25,7)-INDEX('Trayectorias B'!$C$5:$I$45,21,7)*(1+'B Supuestos'!$B$12)),0) -> -18935076
A30: 25 | B30: =-'B Supuestos'!$B$6*INDEX('Trayectorias B'!$C$5:$I$45,26,1) -> -19387104 | C30: =B30+IF(ISNUMBER(MATCH(25,'B Supuestos'!$D$20:$D$23,0)),INDEX('B Supuestos'!$F$20:$F$23,MATCH(25,'B Supuestos'!$D$20:$D$23,0))*(INDEX('Trayectorias B'!$C$5:$I$45,26,1)-INDEX('Trayectorias B'!$C$5:$I$45,22,1)*(1+'B Supuestos'!$B$12)),0) -> -19387104 | D30: =-'B Supuestos'!$B$6*INDEX('Trayectorias B'!$C$5:$I$45,26,2) -> -17595455 | E30: =D30+IF(ISNUMBER(MATCH(25,'B Supuestos'!$D$20:$D$23,0)),INDEX('B Supuestos'!$F$20:$F$23,MATCH(25,'B Supuestos'!$D$20:$D$23,0))*(INDEX('Trayectorias B'!$C$5:$I$45,26,2)-INDEX('Trayectorias B'!$C$5:$I$45,22,2)*(1+'B Supuestos'!$B$12)),0) -> -17595455 | F30: =-'B Supuestos'!$B$6*INDEX('Trayectorias B'!$C$5:$I$45,26,3) -> -20395843 | G30: =F30+IF(ISNUMBER(MATCH(25,'B Supuestos'!$D$20:$D$23,0)),INDEX('B Supuestos'!$F$20:$F$23,MATCH(25,'B Supuestos'!$D$20:$D$23,0))*(INDEX('Trayectorias B'!$C$5:$I$45,26,3)-INDEX('Trayectorias B'!$C$5:$I$45,22,3)*(1+'B Supuestos'!$B$12)),0) -> -20395843 | H30: =-'B Supuestos'!$B$6*INDEX('Trayectorias B'!$C$5:$I$45,26,4) -> -17402348 | I30: =H30+IF(ISNUMBER(MATCH(25,'B Supuestos'!$D$20:$D$23,0)),INDEX('B Supuestos'!$F$20:$F$23,MATCH(25,'B Supuestos'!$D$20:$D$23,0))*(INDEX('Trayectorias B'!$C$5:$I$45,26,4)-INDEX('Trayectorias B'!$C$5:$I$45,22,4)*(1+'B Supuestos'!$B$12)),0) -> -17402348 | J30: =-'B Supuestos'!$B$6*INDEX('Trayectorias B'!$C$5:$I$45,26,5) -> -20082026 | K30: =J30+IF(ISNUMBER(MATCH(25,'B Supuestos'!$D$20:$D$23,0)),INDEX('B Supuestos'!$F$20:$F$23,MATCH(25,'B Supuestos'!$D$20:$D$23,0))*(INDEX('Trayectorias B'!$C$5:$I$45,26,5)-INDEX('Trayectorias B'!$C$5:$I$45,22,5)*(1+'B Supuestos'!$B$12)),0) -> -20082026 | L30: =-'B Supuestos'!$B$6*INDEX('Trayectorias B'!$C$5:$I$45,26,6) -> -19027549 | M30: =L30+IF(ISNUMBER(MATCH(25,'B Supuestos'!$D$20:$D$23,0)),INDEX('B Supuestos'!$F$20:$F$23,MATCH(25,'B Supuestos'!$D$20:$D$23,0))*(INDEX('Trayectorias B'!$C$5:$I$45,26,6)-INDEX('Trayectorias B'!$C$5:$I$45,22,6)*(1+'B Supuestos'!$B$12)),0) -> -19027549 | N30: =-'B Supuestos'!$B$6*INDEX('Trayectorias B'!$C$5:$I$45,26,7) -> -19025116 | O30: =N30+IF(ISNUMBER(MATCH(25,'B Supuestos'!$D$20:$D$23,0)),INDEX('B Supuestos'!$F$20:$F$23,MATCH(25,'B Supuestos'!$D$20:$D$23,0))*(INDEX('Trayectorias B'!$C$5:$I$45,26,7)-INDEX('Trayectorias B'!$C$5:$I$45,22,7)*(1+'B Supuestos'!$B$12)),0) -> -19025116
A31: 26 | B31: =-'B Supuestos'!$B$6*INDEX('Trayectorias B'!$C$5:$I$45,27,1) -> -18611047 | C31: =B31+IF(ISNUMBER(MATCH(26,'B Supuestos'!$D$20:$D$23,0)),INDEX('B Supuestos'!$F$20:$F$23,MATCH(26,'B Supuestos'!$D$20:$D$23,0))*(INDEX('Trayectorias B'!$C$5:$I$45,27,1)-INDEX('Trayectorias B'!$C$5:$I$45,23,1)*(1+'B Supuestos'!$B$12)),0) -> -18611047 | D31: =-'B Supuestos'!$B$6*INDEX('Trayectorias B'!$C$5:$I$45,27,2) -> -17638875 | E31: =D31+IF(ISNUMBER(MATCH(26,'B Supuestos'!$D$20:$D$23,0)),INDEX('B Supuestos'!$F$20:$F$23,MATCH(26,'B Supuestos'!$D$20:$D$23,0))*(INDEX('Trayectorias B'!$C$5:$I$45,27,2)-INDEX('Trayectorias B'!$C$5:$I$45,23,2)*(1+'B Supuestos'!$B$12)),0) -> -17638875 | F31: =-'B Supuestos'!$B$6*INDEX('Trayectorias B'!$C$5:$I$45,27,3) -> -21867853 | G31: =F31+IF(ISNUMBER(MATCH(26,'B Supuestos'!$D$20:$D$23,0)),INDEX('B Supuestos'!$F$20:$F$23,MATCH(26,'B Supuestos'!$D$20:$D$23,0))*(INDEX('Trayectorias B'!$C$5:$I$45,27,3)-INDEX('Trayectorias B'!$C$5:$I$45,23,3)*(1+'B Supuestos'!$B$12)),0) -> -21867853 | H31: =-'B Supuestos'!$B$6*INDEX('Trayectorias B'!$C$5:$I$45,27,4) -> -18199831 | I31: =H31+IF(ISNUMBER(MATCH(26,'B Supuestos'!$D$20:$D$23,0)),INDEX('B Supuestos'!$F$20:$F$23,MATCH(26,'B Supuestos'!$D$20:$D$23,0))*(INDEX('Trayectorias B'!$C$5:$I$45,27,4)-INDEX('Trayectorias B'!$C$5:$I$45,23,4)*(1+'B Supuestos'!$B$12)),0) -> -18199831 | J31: =-'B Supuestos'!$B$6*INDEX('Trayectorias B'!$C$5:$I$45,27,5) -> -21258686 | K31: =J31+IF(ISNUMBER(MATCH(26,'B Supuestos'!$D$20:$D$23,0)),INDEX('B Supuestos'!$F$20:$F$23,MATCH(26,'B Supuestos'!$D$20:$D$23,0))*(INDEX('Trayectorias B'!$C$5:$I$45,27,5)-INDEX('Trayectorias B'!$C$5:$I$45,23,5)*(1+'B Supuestos'!$B$12)),0) -> -21258686 | L31: =-'B Supuestos'!$B$6*INDEX('Trayectorias B'!$C$5:$I$45,27,6) -> -19540957 | M31: =L31+IF(ISNUMBER(MATCH(26,'B Supuestos'!$D$20:$D$23,0)),INDEX('B Supuestos'!$F$20:$F$23,MATCH(26,'B Supuestos'!$D$20:$D$23,0))*(INDEX('Trayectorias B'!$C$5:$I$45,27,6)-INDEX('Trayectorias B'!$C$5:$I$45,23,6)*(1+'B Supuestos'!$B$12)),0) -> -19540957 | N31: =-'B Supuestos'!$B$6*INDEX('Trayectorias B'!$C$5:$I$45,27,7) -> -19115585 | O31: =N31+IF(ISNUMBER(MATCH(26,'B Supuestos'!$D$20:$D$23,0)),INDEX('B Supuestos'!$F$20:$F$23,MATCH(26,'B Supuestos'!$D$20:$D$23,0))*(INDEX('Trayectorias B'!$C$5:$I$45,27,7)-INDEX('Trayectorias B'!$C$5:$I$45,23,7)*(1+'B Supuestos'!$B$12)),0) -> -19115585
A32: 27 | B32: =-'B Supuestos'!$B$6*INDEX('Trayectorias B'!$C$5:$I$45,28,1) -> -18776692 | C32: =B32+IF(ISNUMBER(MATCH(27,'B Supuestos'!$D$20:$D$23,0)),INDEX('B Supuestos'!$F$20:$F$23,MATCH(27,'B Supuestos'!$D$20:$D$23,0))*(INDEX('Trayectorias B'!$C$5:$I$45,28,1)-INDEX('Trayectorias B'!$C$5:$I$45,24,1)*(1+'B Supuestos'!$B$12)),0) -> -18776692 | D32: =-'B Supuestos'!$B$6*INDEX('Trayectorias B'!$C$5:$I$45,28,2) -> -19552302 | E32: =D32+IF(ISNUMBER(MATCH(27,'B Supuestos'!$D$20:$D$23,0)),INDEX('B Supuestos'!$F$20:$F$23,MATCH(27,'B Supuestos'!$D$20:$D$23,0))*(INDEX('Trayectorias B'!$C$5:$I$45,28,2)-INDEX('Trayectorias B'!$C$5:$I$45,24,2)*(1+'B Supuestos'!$B$12)),0) -> -19552302 | F32: =-'B Supuestos'!$B$6*INDEX('Trayectorias B'!$C$5:$I$45,28,3) -> -21650189 | G32: =F32+IF(ISNUMBER(MATCH(27,'B Supuestos'!$D$20:$D$23,0)),INDEX('B Supuestos'!$F$20:$F$23,MATCH(27,'B Supuestos'!$D$20:$D$23,0))*(INDEX('Trayectorias B'!$C$5:$I$45,28,3)-INDEX('Trayectorias B'!$C$5:$I$45,24,3)*(1+'B Supuestos'!$B$12)),0) -> -21650189 | H32: =-'B Supuestos'!$B$6*INDEX('Trayectorias B'!$C$5:$I$45,28,4) -> -18083227 | I32: =H32+IF(ISNUMBER(MATCH(27,'B Supuestos'!$D$20:$D$23,0)),INDEX('B Supuestos'!$F$20:$F$23,MATCH(27,'B Supuestos'!$D$20:$D$23,0))*(INDEX('Trayectorias B'!$C$5:$I$45,28,4)-INDEX('Trayectorias B'!$C$5:$I$45,24,4)*(1+'B Supuestos'!$B$12)),0) -> -18083227 | J32: =-'B Supuestos'!$B$6*INDEX('Trayectorias B'!$C$5:$I$45,28,5) -> -21761568 | K32: =J32+IF(ISNUMBER(MATCH(27,'B Supuestos'!$D$20:$D$23,0)),INDEX('B Supuestos'!$F$20:$F$23,MATCH(27,'B Supuestos'!$D$20:$D$23,0))*(INDEX('Trayectorias B'!$C$5:$I$45,28,5)-INDEX('Trayectorias B'!$C$5:$I$45,24,5)*(1+'B Supuestos'!$B$12)),0) -> -21761568 | L32: =-'B Supuestos'!$B$6*INDEX('Trayectorias B'!$C$5:$I$45,28,6) -> -20275064 | M32: =L32+IF(ISNUMBER(MATCH(27,'B Supuestos'!$D$20:$D$23,0)),INDEX('B Supuestos'!$F$20:$F$23,MATCH(27,'B Supuestos'!$D$20:$D$23,0))*(INDEX('Trayectorias B'!$C$5:$I$45,28,6)-INDEX('Trayectorias B'!$C$5:$I$45,24,6)*(1+'B Supuestos'!$B$12)),0) -> -20275064 | N32: =-'B Supuestos'!$B$6*INDEX('Trayectorias B'!$C$5:$I$45,28,7) -> -19206483 | O32: =N32+IF(ISNUMBER(MATCH(27,'B Supuestos'!$D$20:$D$23,0)),INDEX('B Supuestos'!$F$20:$F$23,MATCH(27,'B Supuestos'!$D$20:$D$23,0))*(INDEX('Trayectorias B'!$C$5:$I$45,28,7)-INDEX('Trayectorias B'!$C$5:$I$45,24,7)*(1+'B Supuestos'!$B$12)),0) -> -19206483
A33: 28 | B33: =-'B Supuestos'!$B$6*INDEX('Trayectorias B'!$C$5:$I$45,29,1) -> -15347912 | C33: =B33+IF(ISNUMBER(MATCH(28,'B Supuestos'!$D$20:$D$23,0)),INDEX('B Supuestos'!$F$20:$F$23,MATCH(28,'B Supuestos'!$D$20:$D$23,0))*(INDEX('Trayectorias B'!$C$5:$I$45,29,1)-INDEX('Trayectorias B'!$C$5:$I$45,25,1)*(1+'B Supuestos'!$B$12)),0) -> -32679551 | D33: =-'B Supuestos'!$B$6*INDEX('Trayectorias B'!$C$5:$I$45,29,2) -> -19002882 | E33: =D33+IF(ISNUMBER(MATCH(28,'B Supuestos'!$D$20:$D$23,0)),INDEX('B Supuestos'!$F$20:$F$23,MATCH(28,'B Supuestos'!$D$20:$D$23,0))*(INDEX('Trayectorias B'!$C$5:$I$45,29,2)-INDEX('Trayectorias B'!$C$5:$I$45,25,2)*(1+'B Supuestos'!$B$12)),0) -> -23193466 | F33: =-'B Supuestos'!$B$6*INDEX('Trayectorias B'!$C$5:$I$45,29,3) -> -24048839 | G33: =F33+IF(ISNUMBER(MATCH(28,'B Supuestos'!$D$20:$D$23,0)),INDEX('B Supuestos'!$F$20:$F$23,MATCH(28,'B Supuestos'!$D$20:$D$23,0))*(INDEX('Trayectorias B'!$C$5:$I$45,29,3)-INDEX('Trayectorias B'!$C$5:$I$45,25,3)*(1+'B Supuestos'!$B$12)),0) -> -15219461 | H33: =-'B Supuestos'!$B$6*INDEX('Trayectorias B'!$C$5:$I$45,29,4) -> -16440476 | I33: =H33+IF(ISNUMBER(MATCH(28,'B Supuestos'!$D$20:$D$23,0)),INDEX('B Supuestos'!$F$20:$F$23,MATCH(28,'B Supuestos'!$D$20:$D$23,0))*(INDEX('Trayectorias B'!$C$5:$I$45,29,4)-INDEX('Trayectorias B'!$C$5:$I$45,25,4)*(1+'B Supuestos'!$B$12)),0) -> -26589447 | J33: =-'B Supuestos'!$B$6*INDEX('Trayectorias B'!$C$5:$I$45,29,5) -> -22190226 | K33: =J33+IF(ISNUMBER(MATCH(28,'B Supuestos'!$D$20:$D$23,0)),INDEX('B Supuestos'!$F$20:$F$23,MATCH(28,'B Supuestos'!$D$20:$D$23,0))*(INDEX('Trayectorias B'!$C$5:$I$45,29,5)-INDEX('Trayectorias B'!$C$5:$I$45,25,5)*(1+'B Supuestos'!$B$12)),0) -> -18299421 | L33: =-'B Supuestos'!$B$6*INDEX('Trayectorias B'!$C$5:$I$45,29,6) -> -20190064 | M33: =L33+IF(ISNUMBER(MATCH(28,'B Supuestos'!$D$20:$D$23,0)),INDEX('B Supuestos'!$F$20:$F$23,MATCH(28,'B Supuestos'!$D$20:$D$23,0))*(INDEX('Trayectorias B'!$C$5:$I$45,29,6)-INDEX('Trayectorias B'!$C$5:$I$45,25,6)*(1+'B Supuestos'!$B$12)),0) -> -20758001 | N33: =-'B Supuestos'!$B$6*INDEX('Trayectorias B'!$C$5:$I$45,29,7) -> -19297814 | O33: =N33+IF(ISNUMBER(MATCH(28,'B Supuestos'!$D$20:$D$23,0)),INDEX('B Supuestos'!$F$20:$F$23,MATCH(28,'B Supuestos'!$D$20:$D$23,0))*(INDEX('Trayectorias B'!$C$5:$I$45,29,7)-INDEX('Trayectorias B'!$C$5:$I$45,25,7)*(1+'B Supuestos'!$B$12)),0) -> -22820477
A34: 29 | B34: =-'B Supuestos'!$B$6*INDEX('Trayectorias B'!$C$5:$I$45,30,1) -> -16236359 | C34: =B34+IF(ISNUMBER(MATCH(29,'B Supuestos'!$D$20:$D$23,0)),INDEX('B Supuestos'!$F$20:$F$23,MATCH(29,'B Supuestos'!$D$20:$D$23,0))*(INDEX('Trayectorias B'!$C$5:$I$45,30,1)-INDEX('Trayectorias B'!$C$5:$I$45,26,1)*(1+'B Supuestos'!$B$12)),0) -> -16236359 | D34: =-'B Supuestos'!$B$6*INDEX('Trayectorias B'!$C$5:$I$45,30,2) -> -18723636 | E34: =D34+IF(ISNUMBER(MATCH(29,'B Supuestos'!$D$20:$D$23,0)),INDEX('B Supuestos'!$F$20:$F$23,MATCH(29,'B Supuestos'!$D$20:$D$23,0))*(INDEX('Trayectorias B'!$C$5:$I$45,30,2)-INDEX('Trayectorias B'!$C$5:$I$45,26,2)*(1+'B Supuestos'!$B$12)),0) -> -18723636 | F34: =-'B Supuestos'!$B$6*INDEX('Trayectorias B'!$C$5:$I$45,30,3) -> -24827894 | G34: =F34+IF(ISNUMBER(MATCH(29,'B Supuestos'!$D$20:$D$23,0)),INDEX('B Supuestos'!$F$20:$F$23,MATCH(29,'B Supuestos'!$D$20:$D$23,0))*(INDEX('Trayectorias B'!$C$5:$I$45,30,3)-INDEX('Trayectorias B'!$C$5:$I$45,26,3)*(1+'B Supuestos'!$B$12)),0) -> -24827894 | H34: =-'B Supuestos'!$B$6*INDEX('Trayectorias B'!$C$5:$I$45,30,4) -> -16134532 | I34: =H34+IF(ISNUMBER(MATCH(29,'B Supuestos'!$D$20:$D$23,0)),INDEX('B Supuestos'!$F$20:$F$23,MATCH(29,'B Supuestos'!$D$20:$D$23,0))*(INDEX('Trayectorias B'!$C$5:$I$45,30,4)-INDEX('Trayectorias B'!$C$5:$I$45,26,4)*(1+'B Supuestos'!$B$12)),0) -> -16134532 | J34: =-'B Supuestos'!$B$6*INDEX('Trayectorias B'!$C$5:$I$45,30,5) -> -23386774 | K34: =J34+IF(ISNUMBER(MATCH(29,'B Supuestos'!$D$20:$D$23,0)),INDEX('B Supuestos'!$F$20:$F$23,MATCH(29,'B Supuestos'!$D$20:$D$23,0))*(INDEX('Trayectorias B'!$C$5:$I$45,30,5)-INDEX('Trayectorias B'!$C$5:$I$45,26,5)*(1+'B Supuestos'!$B$12)),0) -> -23386774 | L34: =-'B Supuestos'!$B$6*INDEX('Trayectorias B'!$C$5:$I$45,30,6) -> -22604374 | M34: =L34+IF(ISNUMBER(MATCH(29,'B Supuestos'!$D$20:$D$23,0)),INDEX('B Supuestos'!$F$20:$F$23,MATCH(29,'B Supuestos'!$D$20:$D$23,0))*(INDEX('Trayectorias B'!$C$5:$I$45,30,6)-INDEX('Trayectorias B'!$C$5:$I$45,26,6)*(1+'B Supuestos'!$B$12)),0) -> -22604374 | N34: =-'B Supuestos'!$B$6*INDEX('Trayectorias B'!$C$5:$I$45,30,7) -> -19389579 | O34: =N34+IF(ISNUMBER(MATCH(29,'B Supuestos'!$D$20:$D$23,0)),INDEX('B Supuestos'!$F$20:$F$23,MATCH(29,'B Supuestos'!$D$20:$D$23,0))*(INDEX('Trayectorias B'!$C$5:$I$45,30,7)-INDEX('Trayectorias B'!$C$5:$I$45,26,7)*(1+'B Supuestos'!$B$12)),0) -> -19389579
A35: 30 | B35: =-'B Supuestos'!$B$6*INDEX('Trayectorias B'!$C$5:$I$45,31,1) -> -15380087 | C35: =B35+IF(ISNUMBER(MATCH(30,'B Supuestos'!$D$20:$D$23,0)),INDEX('B Supuestos'!$F$20:$F$23,MATCH(30,'B Supuestos'!$D$20:$D$23,0))*(INDEX('Trayectorias B'!$C$5:$I$45,31,1)-INDEX('Trayectorias B'!$C$5:$I$45,27,1)*(1+'B Supuestos'!$B$12)),0) -> -15380087 | D35: =-'B Supuestos'!$B$6*INDEX('Trayectorias B'!$C$5:$I$45,31,2) -> -19116680 | E35: =D35+IF(ISNUMBER(MATCH(30,'B Supuestos'!$D$20:$D$23,0)),INDEX('B Supuestos'!$F$20:$F$23,MATCH(30,'B Supuestos'!$D$20:$D$23,0))*(INDEX('Trayectorias B'!$C$5:$I$45,31,2)-INDEX('Trayectorias B'!$C$5:$I$45,27,2)*(1+'B Supuestos'!$B$12)),0) -> -19116680 | F35: =-'B Supuestos'!$B$6*INDEX('Trayectorias B'!$C$5:$I$45,31,3) -> -24520495 | G35: =F35+IF(ISNUMBER(MATCH(30,'B Supuestos'!$D$20:$D$23,0)),INDEX('B Supuestos'!$F$20:$F$23,MATCH(30,'B Supuestos'!$D$20:$D$23,0))*(INDEX('Trayectorias B'!$C$5:$I$45,31,3)-INDEX('Trayectorias B'!$C$5:$I$45,27,3)*(1+'B Supuestos'!$B$12)),0) -> -24520495 | H35: =-'B Supuestos'!$B$6*INDEX('Trayectorias B'!$C$5:$I$45,31,4) -> -16776960 | I35: =H35+IF(ISNUMBER(MATCH(30,'B Supuestos'!$D$20:$D$23,0)),INDEX('B Supuestos'!$F$20:$F$23,MATCH(30,'B Supuestos'!$D$20:$D$23,0))*(INDEX('Trayectorias B'!$C$5:$I$45,31,4)-INDEX('Trayectorias B'!$C$5:$I$45,27,4)*(1+'B Supuestos'!$B$12)),0) -> -16776960 | J35: =-'B Supuestos'!$B$6*INDEX('Trayectorias B'!$C$5:$I$45,31,5) -> -24302358 | K35: =J35+IF(ISNUMBER(MATCH(30,'B Supuestos'!$D$20:$D$23,0)),INDEX('B Supuestos'!$F$20:$F$23,MATCH(30,'B Supuestos'!$D$20:$D$23,0))*(INDEX('Trayectorias B'!$C$5:$I$45,31,5)-INDEX('Trayectorias B'!$C$5:$I$45,27,5)*(1+'B Supuestos'!$B$12)),0) -> -24302358 | L35: =-'B Supuestos'!$B$6*INDEX('Trayectorias B'!$C$5:$I$45,31,6) -> -24525419 | M35: =L35+IF(ISNUMBER(MATCH(30,'B Supuestos'!$D$20:$D$23,0)),INDEX('B Supuestos'!$F$20:$F$23,MATCH(30,'B Supuestos'!$D$20:$D$23,0))*(INDEX('Trayectorias B'!$C$5:$I$45,31,6)-INDEX('Trayectorias B'!$C$5:$I$45,27,6)*(1+'B Supuestos'!$B$12)),0) -> -24525419 | N35: =-'B Supuestos'!$B$6*INDEX('Trayectorias B'!$C$5:$I$45,31,7) -> -19481781 | O35: =N35+IF(ISNUMBER(MATCH(30,'B Supuestos'!$D$20:$D$23,0)),INDEX('B Supuestos'!$F$20:$F$23,MATCH(30,'B Supuestos'!$D$20:$D$23,0))*(INDEX('Trayectorias B'!$C$5:$I$45,31,7)-INDEX('Trayectorias B'!$C$5:$I$45,27,7)*(1+'B Supuestos'!$B$12)),0) -> -19481781
A36: 31 | B36: =-'B Supuestos'!$B$6*INDEX('Trayectorias B'!$C$5:$I$45,32,1) -> -15719338 | C36: =B36+IF(ISNUMBER(MATCH(31,'B Supuestos'!$D$20:$D$23,0)),INDEX('B Supuestos'!$F$20:$F$23,MATCH(31,'B Supuestos'!$D$20:$D$23,0))*(INDEX('Trayectorias B'!$C$5:$I$45,32,1)-INDEX('Trayectorias B'!$C$5:$I$45,28,1)*(1+'B Supuestos'!$B$12)),0) -> -15719338 | D36: =-'B Supuestos'!$B$6*INDEX('Trayectorias B'!$C$5:$I$45,32,2) -> -19319608 | E36: =D36+IF(ISNUMBER(MATCH(31,'B Supuestos'!$D$20:$D$23,0)),INDEX('B Supuestos'!$F$20:$F$23,MATCH(31,'B Supuestos'!$D$20:$D$23,0))*(INDEX('Trayectorias B'!$C$5:$I$45,32,2)-INDEX('Trayectorias B'!$C$5:$I$45,28,2)*(1+'B Supuestos'!$B$12)),0) -> -19319608 | F36: =-'B Supuestos'!$B$6*INDEX('Trayectorias B'!$C$5:$I$45,32,3) -> -21709653 | G36: =F36+IF(ISNUMBER(MATCH(31,'B Supuestos'!$D$20:$D$23,0)),INDEX('B Supuestos'!$F$20:$F$23,MATCH(31,'B Supuestos'!$D$20:$D$23,0))*(INDEX('Trayectorias B'!$C$5:$I$45,32,3)-INDEX('Trayectorias B'!$C$5:$I$45,28,3)*(1+'B Supuestos'!$B$12)),0) -> -21709653 | H36: =-'B Supuestos'!$B$6*INDEX('Trayectorias B'!$C$5:$I$45,32,4) -> -16020813 | I36: =H36+IF(ISNUMBER(MATCH(31,'B Supuestos'!$D$20:$D$23,0)),INDEX('B Supuestos'!$F$20:$F$23,MATCH(31,'B Supuestos'!$D$20:$D$23,0))*(INDEX('Trayectorias B'!$C$5:$I$45,32,4)-INDEX('Trayectorias B'!$C$5:$I$45,28,4)*(1+'B Supuestos'!$B$12)),0) -> -16020813 | J36: =-'B Supuestos'!$B$6*INDEX('Trayectorias B'!$C$5:$I$45,32,5) -> -23787770 | K36: =J36+IF(ISNUMBER(MATCH(31,'B Supuestos'!$D$20:$D$23,0)),INDEX('B Supuestos'!$F$20:$F$23,MATCH(31,'B Supuestos'!$D$20:$D$23,0))*(INDEX('Trayectorias B'!$C$5:$I$45,32,5)-INDEX('Trayectorias B'!$C$5:$I$45,28,5)*(1+'B Supuestos'!$B$12)),0) -> -23787770 | L36: =-'B Supuestos'!$B$6*INDEX('Trayectorias B'!$C$5:$I$45,32,6) -> -26626341 | M36: =L36+IF(ISNUMBER(MATCH(31,'B Supuestos'!$D$20:$D$23,0)),INDEX('B Supuestos'!$F$20:$F$23,MATCH(31,'B Supuestos'!$D$20:$D$23,0))*(INDEX('Trayectorias B'!$C$5:$I$45,32,6)-INDEX('Trayectorias B'!$C$5:$I$45,28,6)*(1+'B Supuestos'!$B$12)),0) -> -26626341 | N36: =-'B Supuestos'!$B$6*INDEX('Trayectorias B'!$C$5:$I$45,32,7) -> -19574421 | O36: =N36+IF(ISNUMBER(MATCH(31,'B Supuestos'!$D$20:$D$23,0)),INDEX('B Supuestos'!$F$20:$F$23,MATCH(31,'B Supuestos'!$D$20:$D$23,0))*(INDEX('Trayectorias B'!$C$5:$I$45,32,7)-INDEX('Trayectorias B'!$C$5:$I$45,28,7)*(1+'B Supuestos'!$B$12)),0) -> -19574421
A37: 32 | B37: =-'B Supuestos'!$B$6*INDEX('Trayectorias B'!$C$5:$I$45,33,1) -> -15530089 | C37: =B37+IF(ISNUMBER(MATCH(32,'B Supuestos'!$D$20:$D$23,0)),INDEX('B Supuestos'!$F$20:$F$23,MATCH(32,'B Supuestos'!$D$20:$D$23,0))*(INDEX('Trayectorias B'!$C$5:$I$45,33,1)-INDEX('Trayectorias B'!$C$5:$I$45,29,1)*(1+'B Supuestos'!$B$12)),0) -> -18720926 | D37: =-'B Supuestos'!$B$6*INDEX('Trayectorias B'!$C$5:$I$45,33,2) -> -17037944 | E37: =D37+IF(ISNUMBER(MATCH(32,'B Supuestos'!$D$20:$D$23,0)),INDEX('B Supuestos'!$F$20:$F$23,MATCH(32,'B Supuestos'!$D$20:$D$23,0))*(INDEX('Trayectorias B'!$C$5:$I$45,33,2)-INDEX('Trayectorias B'!$C$5:$I$45,29,2)*(1+'B Supuestos'!$B$12)),0) -> -27560145 | F37: =-'B Supuestos'!$B$6*INDEX('Trayectorias B'!$C$5:$I$45,33,3) -> -25833333 | G37: =F37+IF(ISNUMBER(MATCH(32,'B Supuestos'!$D$20:$D$23,0)),INDEX('B Supuestos'!$F$20:$F$23,MATCH(32,'B Supuestos'!$D$20:$D$23,0))*(INDEX('Trayectorias B'!$C$5:$I$45,33,3)-INDEX('Trayectorias B'!$C$5:$I$45,29,3)*(1+'B Supuestos'!$B$12)),0) -> -26335982 | H37: =-'B Supuestos'!$B$6*INDEX('Trayectorias B'!$C$5:$I$45,33,4) -> -15149429 | I37: =H37+IF(ISNUMBER(MATCH(32,'B Supuestos'!$D$20:$D$23,0)),INDEX('B Supuestos'!$F$20:$F$23,MATCH(32,'B Supuestos'!$D$20:$D$23,0))*(INDEX('Trayectorias B'!$C$5:$I$45,33,4)-INDEX('Trayectorias B'!$C$5:$I$45,29,4)*(1+'B Supuestos'!$B$12)),0) -> -23025990 | J37: =-'B Supuestos'!$B$6*INDEX('Trayectorias B'!$C$5:$I$45,33,5) -> -23158936 | K37: =J37+IF(ISNUMBER(MATCH(32,'B Supuestos'!$D$20:$D$23,0)),INDEX('B Supuestos'!$F$20:$F$23,MATCH(32,'B Supuestos'!$D$20:$D$23,0))*(INDEX('Trayectorias B'!$C$5:$I$45,33,5)-INDEX('Trayectorias B'!$C$5:$I$45,29,5)*(1+'B Supuestos'!$B$12)),0) -> -25656344 | L37: =-'B Supuestos'!$B$6*INDEX('Trayectorias B'!$C$5:$I$45,33,6) -> -27350797 | M37: =L37+IF(ISNUMBER(MATCH(32,'B Supuestos'!$D$20:$D$23,0)),INDEX('B Supuestos'!$F$20:$F$23,MATCH(32,'B Supuestos'!$D$20:$D$23,0))*(INDEX('Trayectorias B'!$C$5:$I$45,33,6)-INDEX('Trayectorias B'!$C$5:$I$45,29,6)*(1+'B Supuestos'!$B$12)),0) -> -10785077 | N37: =-'B Supuestos'!$B$6*INDEX('Trayectorias B'!$C$5:$I$45,33,7) -> -19667501 | O37: =N37+IF(ISNUMBER(MATCH(32,'B Supuestos'!$D$20:$D$23,0)),INDEX('B Supuestos'!$F$20:$F$23,MATCH(32,'B Supuestos'!$D$20:$D$23,0))*(INDEX('Trayectorias B'!$C$5:$I$45,33,7)-INDEX('Trayectorias B'!$C$5:$I$45,29,7)*(1+'B Supuestos'!$B$12)),0) -> -23257648
A38: 33 | B38: =-'B Supuestos'!$B$6*INDEX('Trayectorias B'!$C$5:$I$45,34,1) -> -16890615 | C38: =B38+IF(ISNUMBER(MATCH(33,'B Supuestos'!$D$20:$D$23,0)),INDEX('B Supuestos'!$F$20:$F$23,MATCH(33,'B Supuestos'!$D$20:$D$23,0))*(INDEX('Trayectorias B'!$C$5:$I$45,34,1)-INDEX('Trayectorias B'!$C$5:$I$45,30,1)*(1+'B Supuestos'!$B$12)),0) -> -16890615 | D38: =-'B Supuestos'!$B$6*INDEX('Trayectorias B'!$C$5:$I$45,34,2) -> -16414075 | E38: =D38+IF(ISNUMBER(MATCH(33,'B Supuestos'!$D$20:$D$23,0)),INDEX('B Supuestos'!$F$20:$F$23,MATCH(33,'B Supuestos'!$D$20:$D$23,0))*(INDEX('Trayectorias B'!$C$5:$I$45,34,2)-INDEX('Trayectorias B'!$C$5:$I$45,30,2)*(1+'B Supuestos'!$B$12)),0) -> -16414075 | F38: =-'B Supuestos'!$B$6*INDEX('Trayectorias B'!$C$5:$I$45,34,3) -> -24878829 | G38: =F38+IF(ISNUMBER(MATCH(33,'B Supuestos'!$D$20:$D$23,0)),INDEX('B Supuestos'!$F$20:$F$23,MATCH(33,'B Supuestos'!$D$20:$D$23,0))*(INDEX('Trayectorias B'!$C$5:$I$45,34,3)-INDEX('Trayectorias B'!$C$5:$I$45,30,3)*(1+'B Supuestos'!$B$12)),0) -> -24878829 | H38: =-'B Supuestos'!$B$6*INDEX('Trayectorias B'!$C$5:$I$45,34,4) -> -16276068 | I38: =H38+IF(ISNUMBER(MATCH(33,'B Supuestos'!$D$20:$D$23,0)),INDEX('B Supuestos'!$F$20:$F$23,MATCH(33,'B Supuestos'!$D$20:$D$23,0))*(INDEX('Trayectorias B'!$C$5:$I$45,34,4)-INDEX('Trayectorias B'!$C$5:$I$45,30,4)*(1+'B Supuestos'!$B$12)),0) -> -16276068 | J38: =-'B Supuestos'!$B$6*INDEX('Trayectorias B'!$C$5:$I$45,34,5) -> -22558091 | K38: =J38+IF(ISNUMBER(MATCH(33,'B Supuestos'!$D$20:$D$23,0)),INDEX('B Supuestos'!$F$20:$F$23,MATCH(33,'B Supuestos'!$D$20:$D$23,0))*(INDEX('Trayectorias B'!$C$5:$I$45,34,5)-INDEX('Trayectorias B'!$C$5:$I$45,30,5)*(1+'B Supuestos'!$B$12)),0) -> -22558091 | L38: =-'B Supuestos'!$B$6*INDEX('Trayectorias B'!$C$5:$I$45,34,6) -> -26062842 | M38: =L38+IF(ISNUMBER(MATCH(33,'B Supuestos'!$D$20:$D$23,0)),INDEX('B Supuestos'!$F$20:$F$23,MATCH(33,'B Supuestos'!$D$20:$D$23,0))*(INDEX('Trayectorias B'!$C$5:$I$45,34,6)-INDEX('Trayectorias B'!$C$5:$I$45,30,6)*(1+'B Supuestos'!$B$12)),0) -> -26062842 | N38: =-'B Supuestos'!$B$6*INDEX('Trayectorias B'!$C$5:$I$45,34,7) -> -19761024 | O38: =N38+IF(ISNUMBER(MATCH(33,'B Supuestos'!$D$20:$D$23,0)),INDEX('B Supuestos'!$F$20:$F$23,MATCH(33,'B Supuestos'!$D$20:$D$23,0))*(INDEX('Trayectorias B'!$C$5:$I$45,34,7)-INDEX('Trayectorias B'!$C$5:$I$45,30,7)*(1+'B Supuestos'!$B$12)),0) -> -19761024
A39: 34 | B39: =-'B Supuestos'!$B$6*INDEX('Trayectorias B'!$C$5:$I$45,35,1) -> -16872114 | C39: =B39+IF(ISNUMBER(MATCH(34,'B Supuestos'!$D$20:$D$23,0)),INDEX('B Supuestos'!$F$20:$F$23,MATCH(34,'B Supuestos'!$D$20:$D$23,0))*(INDEX('Trayectorias B'!$C$5:$I$45,35,1)-INDEX('Trayectorias B'!$C$5:$I$45,31,1)*(1+'B Supuestos'!$B$12)),0) -> -16872114 | D39: =-'B Supuestos'!$B$6*INDEX('Trayectorias B'!$C$5:$I$45,35,2) -> -17022472 | E39: =D39+IF(ISNUMBER(MATCH(34,'B Supuestos'!$D$20:$D$23,0)),INDEX('B Supuestos'!$F$20:$F$23,MATCH(34,'B Supuestos'!$D$20:$D$23,0))*(INDEX('Trayectorias B'!$C$5:$I$45,35,2)-INDEX('Trayectorias B'!$C$5:$I$45,31,2)*(1+'B Supuestos'!$B$12)),0) -> -17022472 | F39: =-'B Supuestos'!$B$6*INDEX('Trayectorias B'!$C$5:$I$45,35,3) -> -23444825 | G39: =F39+IF(ISNUMBER(MATCH(34,'B Supuestos'!$D$20:$D$23,0)),INDEX('B Supuestos'!$F$20:$F$23,MATCH(34,'B Supuestos'!$D$20:$D$23,0))*(INDEX('Trayectorias B'!$C$5:$I$45,35,3)-INDEX('Trayectorias B'!$C$5:$I$45,31,3)*(1+'B Supuestos'!$B$12)),0) -> -23444825 | H39: =-'B Supuestos'!$B$6*INDEX('Trayectorias B'!$C$5:$I$45,35,4) -> -15213036 | I39: =H39+IF(ISNUMBER(MATCH(34,'B Supuestos'!$D$20:$D$23,0)),INDEX('B Supuestos'!$F$20:$F$23,MATCH(34,'B Supuestos'!$D$20:$D$23,0))*(INDEX('Trayectorias B'!$C$5:$I$45,35,4)-INDEX('Trayectorias B'!$C$5:$I$45,31,4)*(1+'B Supuestos'!$B$12)),0) -> -15213036 | J39: =-'B Supuestos'!$B$6*INDEX('Trayectorias B'!$C$5:$I$45,35,5) -> -24282696 | K39: =J39+IF(ISNUMBER(MATCH(34,'B Supuestos'!$D$20:$D$23,0)),INDEX('B Supuestos'!$F$20:$F$23,MATCH(34,'B Supuestos'!$D$20:$D$23,0))*(INDEX('Trayectorias B'!$C$5:$I$45,35,5)-INDEX('Trayectorias B'!$C$5:$I$45,31,5)*(1+'B Supuestos'!$B$12)),0) -> -24282696 | L39: =-'B Supuestos'!$B$6*INDEX('Trayectorias B'!$C$5:$I$45,35,6) -> -23656087 | M39: =L39+IF(ISNUMBER(MATCH(34,'B Supuestos'!$D$20:$D$23,0)),INDEX('B Supuestos'!$F$20:$F$23,MATCH(34,'B Supuestos'!$D$20:$D$23,0))*(INDEX('Trayectorias B'!$C$5:$I$45,35,6)-INDEX('Trayectorias B'!$C$5:$I$45,31,6)*(1+'B Supuestos'!$B$12)),0) -> -23656087 | N39: =-'B Supuestos'!$B$6*INDEX('Trayectorias B'!$C$5:$I$45,35,7) -> -19854992 | O39: =N39+IF(ISNUMBER(MATCH(34,'B Supuestos'!$D$20:$D$23,0)),INDEX('B Supuestos'!$F$20:$F$23,MATCH(34,'B Supuestos'!$D$20:$D$23,0))*(INDEX('Trayectorias B'!$C$5:$I$45,35,7)-INDEX('Trayectorias B'!$C$5:$I$45,31,7)*(1+'B Supuestos'!$B$12)),0) -> -19854992
A40: 35 | B40: =-'B Supuestos'!$B$6*INDEX('Trayectorias B'!$C$5:$I$45,36,1) -> -16585698 | C40: =B40+IF(ISNUMBER(MATCH(35,'B Supuestos'!$D$20:$D$23,0)),INDEX('B Supuestos'!$F$20:$F$23,MATCH(35,'B Supuestos'!$D$20:$D$23,0))*(INDEX('Trayectorias B'!$C$5:$I$45,36,1)-INDEX('Trayectorias B'!$C$5:$I$45,32,1)*(1+'B Supuestos'!$B$12)),0) -> -16585698 | D40: =-'B Supuestos'!$B$6*INDEX('Trayectorias B'!$C$5:$I$45,36,2) -> -17185057 | E40: =D40+IF(ISNUMBER(MATCH(35,'B Supuestos'!$D$20:$D$23,0)),INDEX('B Supuestos'!$F$20:$F$23,MATCH(35,'B Supuestos'!$D$20:$D$23,0))*(INDEX('Trayectorias B'!$C$5:$I$45,36,2)-INDEX('Trayectorias B'!$C$5:$I$45,32,2)*(1+'B Supuestos'!$B$12)),0) -> -17185057 | F40: =-'B Supuestos'!$B$6*INDEX('Trayectorias B'!$C$5:$I$45,36,3) -> -26036412 | G40: =F40+IF(ISNUMBER(MATCH(35,'B Supuestos'!$D$20:$D$23,0)),INDEX('B Supuestos'!$F$20:$F$23,MATCH(35,'B Supuestos'!$D$20:$D$23,0))*(INDEX('Trayectorias B'!$C$5:$I$45,36,3)-INDEX('Trayectorias B'!$C$5:$I$45,32,3)*(1+'B Supuestos'!$B$12)),0) -> -26036412 | H40: =-'B Supuestos'!$B$6*INDEX('Trayectorias B'!$C$5:$I$45,36,4) -> -16765614 | I40: =H40+IF(ISNUMBER(MATCH(35,'B Supuestos'!$D$20:$D$23,0)),INDEX('B Supuestos'!$F$20:$F$23,MATCH(35,'B Supuestos'!$D$20:$D$23,0))*(INDEX('Trayectorias B'!$C$5:$I$45,36,4)-INDEX('Trayectorias B'!$C$5:$I$45,32,4)*(1+'B Supuestos'!$B$12)),0) -> -16765614 | J40: =-'B Supuestos'!$B$6*INDEX('Trayectorias B'!$C$5:$I$45,36,5) -> -24512399 | K40: =J40+IF(ISNUMBER(MATCH(35,'B Supuestos'!$D$20:$D$23,0)),INDEX('B Supuestos'!$F$20:$F$23,MATCH(35,'B Supuestos'!$D$20:$D$23,0))*(INDEX('Trayectorias B'!$C$5:$I$45,36,5)-INDEX('Trayectorias B'!$C$5:$I$45,32,5)*(1+'B Supuestos'!$B$12)),0) -> -24512399 | L40: =-'B Supuestos'!$B$6*INDEX('Trayectorias B'!$C$5:$I$45,36,6) -> -24895935 | M40: =L40+IF(ISNUMBER(MATCH(35,'B Supuestos'!$D$20:$D$23,0)),INDEX('B Supuestos'!$F$20:$F$23,MATCH(35,'B Supuestos'!$D$20:$D$23,0))*(INDEX('Trayectorias B'!$C$5:$I$45,36,6)-INDEX('Trayectorias B'!$C$5:$I$45,32,6)*(1+'B Supuestos'!$B$12)),0) -> -24895935 | N40: =-'B Supuestos'!$B$6*INDEX('Trayectorias B'!$C$5:$I$45,36,7) -> -19949407 | O40: =N40+IF(ISNUMBER(MATCH(35,'B Supuestos'!$D$20:$D$23,0)),INDEX('B Supuestos'!$F$20:$F$23,MATCH(35,'B Supuestos'!$D$20:$D$23,0))*(INDEX('Trayectorias B'!$C$5:$I$45,36,7)-INDEX('Trayectorias B'!$C$5:$I$45,32,7)*(1+'B Supuestos'!$B$12)),0) -> -19949407
